Workbook

Sheet Test Case Summary
A1: BUSINESS & TRADE ACCOUNT — MANUAL TEST EXECUTION DASHBOARD
A2: Counts below are live formulas over the Status column of every test sheet. Set Status on each step as you go and this dashboard updates itself. A blank Status counts as Not Run.
A4: OVERALL EXECUTION
A5: Total Test Cases | B5: 231 | C5: Distinct test case IDs across all 19 test sheets.
A6: Total Test Steps | B6: =COUNTA('Business Registration'!$K$4:$K$121)+COUNTA('Business Profile'!$K$4:$K$57)+COUNTA('Trade Registration'!$K$4:$K$67)+COUNTA('Trade Approval'!$K$4:$K$64)+COUNTA('Trade Rejection'!$K$4:$K$46)+COUNTA('Trade Suspension'!$K$4:$K$42)+COUNTA('Pricing & Quantity Bands'!$K$4:$K$77)+COUNTA('Cart & Cart Repricing'!$K$4:$K$61)+COUNTA('VAT & Tax'!$K$4:$K$49)+COUNTA('Checkout'!$K$4:$K$61)+COUNTA('Payment'!$K$4:$K$48)+COUNTA('Orders'!$K$4:$K$48)+COUNTA('Invoice'!$K$4:$K$40)+COUNTA('Email Notifications'!$K$4:$K$68)+COUNTA('Admin'!$K$4:$K$55)+COUNTA('Security & Authorization'!$K$4:$K$55)+COUNTA('Mobile & Responsive'!$K$4:$K$48)+COUNTA('Regression Testing'!$K$4:$K$47)+COUNTA('End-to-End Scenarios'!$K$4:$K$80)+COUNTA('Admin Customer Preview'!$K$4:$K$162)+COUNTA('Wizard Type Switching'!$K$4:$K$97)+COUNTA('Suspended Account Access'!$K$4:$K$91) -> 1418 | C6: Individually executable steps. Each step carries its own Status.
A7: Not Run | B7: =COUNTIF('Business Registration'!$K$4:$K$121,"Not Run")+COUNTBLANK('Business Registration'!$K$4:$K$121)+COUNTIF('Business Profile'!$K$4:$K$57,"Not Run")+COUNTBLANK('Business Profile'!$K$4:$K$57)+COUNTIF('Trade Registration'!$K$4:$K$67,"Not Run")+COUNTBLANK('Trade Registration'!$K$4:$K$67)+COUNTIF('Trade Approval'!$K$4:$K$64,"Not Run")+COUNTBLANK('Trade Approval'!$K$4:$K$64)+COUNTIF('Trade Rejection'!$K$4:$K$46,"Not Run")+COUNTBLANK('Trade Rejection'!$K$4:$K$46)+COUNTIF('Trade Suspension'!$K$4:$K$42,"Not Run")+COUNTBLANK('Trade Suspension'!$K$4:$K$42)+COUNTIF('Pricing & Quantity Bands'!$K$4:$K$77,"Not Run")+COUNTBLANK('Pricing & Quantity Bands'!$K$4:$K$77)+COUNTIF('Cart & Cart Repricing'!$K$4:$K$61,"Not Run")+COUNTBLANK('Cart & Cart Repricing'!$K$4:$K$61)+COUNTIF('VAT & Tax'!$K$4:$K$49,"Not Run")+COUNTBLANK('VAT & Tax'!$K$4:$K$49)+COUNTIF('Checkout'!$K$4:$K$61,"Not Run")+COUNTBLANK('Checkout'!$K$4:$K$61)+COUNTIF('Payment'!$K$4:$K$48,"Not Run")+COUNTBLANK('Payment'!$K$4:$K$48)+COUNTIF('Orders'!$K$4:$K$48,"Not Run")+COUNTBLANK('Orders'!$K$4:$K$48)+COUNTIF('Invoice'!$K$4:$K$40,"Not Run")+COUNTBLANK('Invoice'!$K$4:$K$40)+COUNTIF('Email Notifications'!$K$4:$K$68,"Not Run")+COUNTBLANK('Email Notifications'!$K$4:$K$68)+COUNTIF('Admin'!$K$4:$K$55,"Not Run")+COUNTBLANK('Admin'!$K$4:$K$55)+COUNTIF('Security & Authorization'!$K$4:$K$55,"Not Run")+COUNTBLANK('Security & Authorization'!$K$4:$K$55)+COUNTIF('Mobile & Responsive'!$K$4:$K$48,"Not Run")+COUNTBLANK('Mobile & Responsive'!$K$4:$K$48)+COUNTIF('Regression Testing'!$K$4:$K$47,"Not Run")+COUNTBLANK('Regression Testing'!$K$4:$K$47)+COUNTIF('End-to-End Scenarios'!$K$4:$K$80,"Not Run")+COUNTBLANK('End-to-End Scenarios'!$K$4:$K$80)+COUNTIF('Admin Customer Preview'!$K$4:$K$162,"Not Run")+COUNTBLANK('Admin Customer Preview'!$K$4:$K$162)+COUNTIF('Wizard Type Switching'!$K$4:$K$97,"Not Run")+COUNTBLANK('Wizard Type Switching'!$K$4:$K$97)+COUNTIF('Suspended Account Access'!$K$4:$K$91,"Not Run")+COUNTBLANK('Suspended Account Access'!$K$4:$K$91) -> 1418 | C7: Steps not yet attempted.
A8: Passed | B8: =COUNTIF('Business Registration'!$K$4:$K$121,"Pass")+COUNTIF('Business Profile'!$K$4:$K$57,"Pass")+COUNTIF('Trade Registration'!$K$4:$K$67,"Pass")+COUNTIF('Trade Approval'!$K$4:$K$64,"Pass")+COUNTIF('Trade Rejection'!$K$4:$K$46,"Pass")+COUNTIF('Trade Suspension'!$K$4:$K$42,"Pass")+COUNTIF('Pricing & Quantity Bands'!$K$4:$K$77,"Pass")+COUNTIF('Cart & Cart Repricing'!$K$4:$K$61,"Pass")+COUNTIF('VAT & Tax'!$K$4:$K$49,"Pass")+COUNTIF('Checkout'!$K$4:$K$61,"Pass")+COUNTIF('Payment'!$K$4:$K$48,"Pass")+COUNTIF('Orders'!$K$4:$K$48,"Pass")+COUNTIF('Invoice'!$K$4:$K$40,"Pass")+COUNTIF('Email Notifications'!$K$4:$K$68,"Pass")+COUNTIF('Admin'!$K$4:$K$55,"Pass")+COUNTIF('Security & Authorization'!$K$4:$K$55,"Pass")+COUNTIF('Mobile & Responsive'!$K$4:$K$48,"Pass")+COUNTIF('Regression Testing'!$K$4:$K$47,"Pass")+COUNTIF('End-to-End Scenarios'!$K$4:$K$80,"Pass")+COUNTIF('Admin Customer Preview'!$K$4:$K$162,"Pass")+COUNTIF('Wizard Type Switching'!$K$4:$K$97,"Pass")+COUNTIF('Suspended Account Access'!$K$4:$K$91,"Pass") -> 0 | C8: Steps where actual behaviour matched the expected result.
A9: Failed | B9: =COUNTIF('Business Registration'!$K$4:$K$121,"Fail")+COUNTIF('Business Profile'!$K$4:$K$57,"Fail")+COUNTIF('Trade Registration'!$K$4:$K$67,"Fail")+COUNTIF('Trade Approval'!$K$4:$K$64,"Fail")+COUNTIF('Trade Rejection'!$K$4:$K$46,"Fail")+COUNTIF('Trade Suspension'!$K$4:$K$42,"Fail")+COUNTIF('Pricing & Quantity Bands'!$K$4:$K$77,"Fail")+COUNTIF('Cart & Cart Repricing'!$K$4:$K$61,"Fail")+COUNTIF('VAT & Tax'!$K$4:$K$49,"Fail")+COUNTIF('Checkout'!$K$4:$K$61,"Fail")+COUNTIF('Payment'!$K$4:$K$48,"Fail")+COUNTIF('Orders'!$K$4:$K$48,"Fail")+COUNTIF('Invoice'!$K$4:$K$40,"Fail")+COUNTIF('Email Notifications'!$K$4:$K$68,"Fail")+COUNTIF('Admin'!$K$4:$K$55,"Fail")+COUNTIF('Security & Authorization'!$K$4:$K$55,"Fail")+COUNTIF('Mobile & Responsive'!$K$4:$K$48,"Fail")+COUNTIF('Regression Testing'!$K$4:$K$47,"Fail")+COUNTIF('End-to-End Scenarios'!$K$4:$K$80,"Fail")+COUNTIF('Admin Customer Preview'!$K$4:$K$162,"Fail")+COUNTIF('Wizard Type Switching'!$K$4:$K$97,"Fail")+COUNTIF('Suspended Account Access'!$K$4:$K$91,"Fail") -> 0 | C9: Steps where actual behaviour differed. Raise a defect for each.
A10: Blocked | B10: =COUNTIF('Business Registration'!$K$4:$K$121,"Blocked")+COUNTIF('Business Profile'!$K$4:$K$57,"Blocked")+COUNTIF('Trade Registration'!$K$4:$K$67,"Blocked")+COUNTIF('Trade Approval'!$K$4:$K$64,"Blocked")+COUNTIF('Trade Rejection'!$K$4:$K$46,"Blocked")+COUNTIF('Trade Suspension'!$K$4:$K$42,"Blocked")+COUNTIF('Pricing & Quantity Bands'!$K$4:$K$77,"Blocked")+COUNTIF('Cart & Cart Repricing'!$K$4:$K$61,"Blocked")+COUNTIF('VAT & Tax'!$K$4:$K$49,"Blocked")+COUNTIF('Checkout'!$K$4:$K$61,"Blocked")+COUNTIF('Payment'!$K$4:$K$48,"Blocked")+COUNTIF('Orders'!$K$4:$K$48,"Blocked")+COUNTIF('Invoice'!$K$4:$K$40,"Blocked")+COUNTIF('Email Notifications'!$K$4:$K$68,"Blocked")+COUNTIF('Admin'!$K$4:$K$55,"Blocked")+COUNTIF('Security & Authorization'!$K$4:$K$55,"Blocked")+COUNTIF('Mobile & Responsive'!$K$4:$K$48,"Blocked")+COUNTIF('Regression Testing'!$K$4:$K$47,"Blocked")+COUNTIF('End-to-End Scenarios'!$K$4:$K$80,"Blocked")+COUNTIF('Admin Customer Preview'!$K$4:$K$162,"Blocked")+COUNTIF('Wizard Type Switching'!$K$4:$K$97,"Blocked")+COUNTIF('Suspended Account Access'!$K$4:$K$91,"Blocked") -> 0 | C10: Could not be executed (environment, data or an earlier failure).
A11: Not Applicable | B11: =COUNTIF('Business Registration'!$K$4:$K$121,"Not Applicable")+COUNTIF('Business Profile'!$K$4:$K$57,"Not Applicable")+COUNTIF('Trade Registration'!$K$4:$K$67,"Not Applicable")+COUNTIF('Trade Approval'!$K$4:$K$64,"Not Applicable")+COUNTIF('Trade Rejection'!$K$4:$K$46,"Not Applicable")+COUNTIF('Trade Suspension'!$K$4:$K$42,"Not Applicable")+COUNTIF('Pricing & Quantity Bands'!$K$4:$K$77,"Not Applicable")+COUNTIF('Cart & Cart Repricing'!$K$4:$K$61,"Not Applicable")+COUNTIF('VAT & Tax'!$K$4:$K$49,"Not Applicable")+COUNTIF('Checkout'!$K$4:$K$61,"Not Applicable")+COUNTIF('Payment'!$K$4:$K$48,"Not Applicable")+COUNTIF('Orders'!$K$4:$K$48,"Not Applicable")+COUNTIF('Invoice'!$K$4:$K$40,"Not Applicable")+COUNTIF('Email Notifications'!$K$4:$K$68,"Not Applicable")+COUNTIF('Admin'!$K$4:$K$55,"Not Applicable")+COUNTIF('Security & Authorization'!$K$4:$K$55,"Not Applicable")+COUNTIF('Mobile & Responsive'!$K$4:$K$48,"Not Applicable")+COUNTIF('Regression Testing'!$K$4:$K$47,"Not Applicable")+COUNTIF('End-to-End Scenarios'!$K$4:$K$80,"Not Applicable")+COUNTIF('Admin Customer Preview'!$K$4:$K$162,"Not Applicable")+COUNTIF('Wizard Type Switching'!$K$4:$K$97,"Not Applicable")+COUNTIF('Suspended Account Access'!$K$4:$K$91,"Not Applicable") -> 0 | C11: Feature not implemented in this build. NOT a failure.
A12: Pass Rate (of executed) | B12: =IF((B8+B9)=0,"—",B8/(B8+B9)) -> — | C12: Passed / (Passed + Failed). Blocked and Not Applicable steps are excluded.
A14: FAILURES BY SEVERITY
A15: Critical Failures | B15: =_xlfn.COUNTIFS('Business Registration'!$K$4:$K$121,"Fail",'Business Registration'!$L$4:$L$121,"Critical")+_xlfn.COUNTIFS('Business Profile'!$K$4:$K$57,"Fail",'Business Profile'!$L$4:$L$57,"Critical")+_xlfn.COUNTIFS('Trade Registration'!$K$4:$K$67,"Fail",'Trade Registration'!$L$4:$L$67,"Critical")+_xlfn.COUNTIFS('Trade Approval'!$K$4:$K$64,"Fail",'Trade Approval'!$L$4:$L$64,"Critical")+_xlfn.COUNTIFS('Trade Rejection'!$K$4:$K$46,"Fail",'Trade Rejection'!$L$4:$L$46,"Critical")+_xlfn.COUNTIFS('Trade Suspension'!$K$4:$K$42,"Fail",'Trade Suspension'!$L$4:$L$42,"Critical")+_xlfn.COUNTIFS('Pricing & Quantity Bands'!$K$4:$K$77,"Fail",'Pricing & Quantity Bands'!$L$4:$L$77,"Critical")+_xlfn.COUNTIFS('Cart & Cart Repricing'!$K$4:$K$61,"Fail",'Cart & Cart Repricing'!$L$4:$L$61,"Critical")+_xlfn.COUNTIFS('VAT & Tax'!$K$4:$K$49,"Fail",'VAT & Tax'!$L$4:$L$49,"Critical")+_xlfn.COUNTIFS('Checkout'!$K$4:$K$61,"Fail",'Checkout'!$L$4:$L$61,"Critical")+_xlfn.COUNTIFS('Payment'!$K$4:$K$48,"Fail",'Payment'!$L$4:$L$48,"Critical")+_xlfn.COUNTIFS('Orders'!$K$4:$K$48,"Fail",'Orders'!$L$4:$L$48,"Critical")+_xlfn.COUNTIFS('Invoice'!$K$4:$K$40,"Fail",'Invoice'!$L$4:$L$40,"Critical")+_xlfn.COUNTIFS('Email Notifications'!$K$4:$K$68,"Fail",'Email Notifications'!$L$4:$L$68,"Critical")+_xlfn.COUNTIFS('Admin'!$K$4:$K$55,"Fail",'Admin'!$L$4:$L$55,"Critical")+_xlfn.COUNTIFS('Security & Authorization'!$K$4:$K$55,"Fail",'Security & Authorization'!$L$4:$L$55,"Critical")+_xlfn.COUNTIFS('Mobile & Responsive'!$K$4:$K$48,"Fail",'Mobile & Responsive'!$L$4:$L$48,"Critical")+_xlfn.COUNTIFS('Regression Testing'!$K$4:$K$47,"Fail",'Regression Testing'!$L$4:$L$47,"Critical")+_xlfn.COUNTIFS('End-to-End Scenarios'!$K$4:$K$80,"Fail",'End-to-End Scenarios'!$L$4:$L$80,"Critical")+_xlfn.COUNTIFS('Admin Customer Preview'!$K$4:$K$162,"Fail",'Admin Customer Preview'!$L$4:$L$162,"Critical")+_xlfn.COUNTIFS('Wizard Type Switching'!$K$4:$K$97,"Fail",'Wizard Type Switching'!$L$4:$L$97,"Critical")+_xlfn.COUNTIFS('Suspended Account Access'!$K$4:$K$91,"Fail",'Suspended Account Access'!$L$4:$L$91,"Critical") -> 0 | C15: Blocks release. Business/trade cannot transact, or money/permissions are wrong.
A16: Major Failures | B16: =_xlfn.COUNTIFS('Business Registration'!$K$4:$K$121,"Fail",'Business Registration'!$L$4:$L$121,"Major")+_xlfn.COUNTIFS('Business Profile'!$K$4:$K$57,"Fail",'Business Profile'!$L$4:$L$57,"Major")+_xlfn.COUNTIFS('Trade Registration'!$K$4:$K$67,"Fail",'Trade Registration'!$L$4:$L$67,"Major")+_xlfn.COUNTIFS('Trade Approval'!$K$4:$K$64,"Fail",'Trade Approval'!$L$4:$L$64,"Major")+_xlfn.COUNTIFS('Trade Rejection'!$K$4:$K$46,"Fail",'Trade Rejection'!$L$4:$L$46,"Major")+_xlfn.COUNTIFS('Trade Suspension'!$K$4:$K$42,"Fail",'Trade Suspension'!$L$4:$L$42,"Major")+_xlfn.COUNTIFS('Pricing & Quantity Bands'!$K$4:$K$77,"Fail",'Pricing & Quantity Bands'!$L$4:$L$77,"Major")+_xlfn.COUNTIFS('Cart & Cart Repricing'!$K$4:$K$61,"Fail",'Cart & Cart Repricing'!$L$4:$L$61,"Major")+_xlfn.COUNTIFS('VAT & Tax'!$K$4:$K$49,"Fail",'VAT & Tax'!$L$4:$L$49,"Major")+_xlfn.COUNTIFS('Checkout'!$K$4:$K$61,"Fail",'Checkout'!$L$4:$L$61,"Major")+_xlfn.COUNTIFS('Payment'!$K$4:$K$48,"Fail",'Payment'!$L$4:$L$48,"Major")+_xlfn.COUNTIFS('Orders'!$K$4:$K$48,"Fail",'Orders'!$L$4:$L$48,"Major")+_xlfn.COUNTIFS('Invoice'!$K$4:$K$40,"Fail",'Invoice'!$L$4:$L$40,"Major")+_xlfn.COUNTIFS('Email Notifications'!$K$4:$K$68,"Fail",'Email Notifications'!$L$4:$L$68,"Major")+_xlfn.COUNTIFS('Admin'!$K$4:$K$55,"Fail",'Admin'!$L$4:$L$55,"Major")+_xlfn.COUNTIFS('Security & Authorization'!$K$4:$K$55,"Fail",'Security & Authorization'!$L$4:$L$55,"Major")+_xlfn.COUNTIFS('Mobile & Responsive'!$K$4:$K$48,"Fail",'Mobile & Responsive'!$L$4:$L$48,"Major")+_xlfn.COUNTIFS('Regression Testing'!$K$4:$K$47,"Fail",'Regression Testing'!$L$4:$L$47,"Major")+_xlfn.COUNTIFS('End-to-End Scenarios'!$K$4:$K$80,"Fail",'End-to-End Scenarios'!$L$4:$L$80,"Major")+_xlfn.COUNTIFS('Admin Customer Preview'!$K$4:$K$162,"Fail",'Admin Customer Preview'!$L$4:$L$162,"Major")+_xlfn.COUNTIFS('Wizard Type Switching'!$K$4:$K$97,"Fail",'Wizard Type Switching'!$L$4:$L$97,"Major")+_xlfn.COUNTIFS('Suspended Account Access'!$K$4:$K$91,"Fail",'Suspended Account Access'!$L$4:$L$91,"Major") -> 0 | C16: Core function broken with no workaround.
A17: Minor Failures | B17: =_xlfn.COUNTIFS('Business Registration'!$K$4:$K$121,"Fail",'Business Registration'!$L$4:$L$121,"Minor")+_xlfn.COUNTIFS('Business Profile'!$K$4:$K$57,"Fail",'Business Profile'!$L$4:$L$57,"Minor")+_xlfn.COUNTIFS('Trade Registration'!$K$4:$K$67,"Fail",'Trade Registration'!$L$4:$L$67,"Minor")+_xlfn.COUNTIFS('Trade Approval'!$K$4:$K$64,"Fail",'Trade Approval'!$L$4:$L$64,"Minor")+_xlfn.COUNTIFS('Trade Rejection'!$K$4:$K$46,"Fail",'Trade Rejection'!$L$4:$L$46,"Minor")+_xlfn.COUNTIFS('Trade Suspension'!$K$4:$K$42,"Fail",'Trade Suspension'!$L$4:$L$42,"Minor")+_xlfn.COUNTIFS('Pricing & Quantity Bands'!$K$4:$K$77,"Fail",'Pricing & Quantity Bands'!$L$4:$L$77,"Minor")+_xlfn.COUNTIFS('Cart & Cart Repricing'!$K$4:$K$61,"Fail",'Cart & Cart Repricing'!$L$4:$L$61,"Minor")+_xlfn.COUNTIFS('VAT & Tax'!$K$4:$K$49,"Fail",'VAT & Tax'!$L$4:$L$49,"Minor")+_xlfn.COUNTIFS('Checkout'!$K$4:$K$61,"Fail",'Checkout'!$L$4:$L$61,"Minor")+_xlfn.COUNTIFS('Payment'!$K$4:$K$48,"Fail",'Payment'!$L$4:$L$48,"Minor")+_xlfn.COUNTIFS('Orders'!$K$4:$K$48,"Fail",'Orders'!$L$4:$L$48,"Minor")+_xlfn.COUNTIFS('Invoice'!$K$4:$K$40,"Fail",'Invoice'!$L$4:$L$40,"Minor")+_xlfn.COUNTIFS('Email Notifications'!$K$4:$K$68,"Fail",'Email Notifications'!$L$4:$L$68,"Minor")+_xlfn.COUNTIFS('Admin'!$K$4:$K$55,"Fail",'Admin'!$L$4:$L$55,"Minor")+_xlfn.COUNTIFS('Security & Authorization'!$K$4:$K$55,"Fail",'Security & Authorization'!$L$4:$L$55,"Minor")+_xlfn.COUNTIFS('Mobile & Responsive'!$K$4:$K$48,"Fail",'Mobile & Responsive'!$L$4:$L$48,"Minor")+_xlfn.COUNTIFS('Regression Testing'!$K$4:$K$47,"Fail",'Regression Testing'!$L$4:$L$47,"Minor")+_xlfn.COUNTIFS('End-to-End Scenarios'!$K$4:$K$80,"Fail",'End-to-End Scenarios'!$L$4:$L$80,"Minor")+_xlfn.COUNTIFS('Admin Customer Preview'!$K$4:$K$162,"Fail",'Admin Customer Preview'!$L$4:$L$162,"Minor")+_xlfn.COUNTIFS('Wizard Type Switching'!$K$4:$K$97,"Fail",'Wizard Type Switching'!$L$4:$L$97,"Minor")+_xlfn.COUNTIFS('Suspended Account Access'!$K$4:$K$91,"Fail",'Suspended Account Access'!$L$4:$L$91,"Minor") -> 0 | C17: Function works with a workaround, or a small data/display error.
A18: Cosmetic Failures | B18: =_xlfn.COUNTIFS('Business Registration'!$K$4:$K$121,"Fail",'Business Registration'!$L$4:$L$121,"Cosmetic")+_xlfn.COUNTIFS('Business Profile'!$K$4:$K$57,"Fail",'Business Profile'!$L$4:$L$57,"Cosmetic")+_xlfn.COUNTIFS('Trade Registration'!$K$4:$K$67,"Fail",'Trade Registration'!$L$4:$L$67,"Cosmetic")+_xlfn.COUNTIFS('Trade Approval'!$K$4:$K$64,"Fail",'Trade Approval'!$L$4:$L$64,"Cosmetic")+_xlfn.COUNTIFS('Trade Rejection'!$K$4:$K$46,"Fail",'Trade Rejection'!$L$4:$L$46,"Cosmetic")+_xlfn.COUNTIFS('Trade Suspension'!$K$4:$K$42,"Fail",'Trade Suspension'!$L$4:$L$42,"Cosmetic")+_xlfn.COUNTIFS('Pricing & Quantity Bands'!$K$4:$K$77,"Fail",'Pricing & Quantity Bands'!$L$4:$L$77,"Cosmetic")+_xlfn.COUNTIFS('Cart & Cart Repricing'!$K$4:$K$61,"Fail",'Cart & Cart Repricing'!$L$4:$L$61,"Cosmetic")+_xlfn.COUNTIFS('VAT & Tax'!$K$4:$K$49,"Fail",'VAT & Tax'!$L$4:$L$49,"Cosmetic")+_xlfn.COUNTIFS('Checkout'!$K$4:$K$61,"Fail",'Checkout'!$L$4:$L$61,"Cosmetic")+_xlfn.COUNTIFS('Payment'!$K$4:$K$48,"Fail",'Payment'!$L$4:$L$48,"Cosmetic")+_xlfn.COUNTIFS('Orders'!$K$4:$K$48,"Fail",'Orders'!$L$4:$L$48,"Cosmetic")+_xlfn.COUNTIFS('Invoice'!$K$4:$K$40,"Fail",'Invoice'!$L$4:$L$40,"Cosmetic")+_xlfn.COUNTIFS('Email Notifications'!$K$4:$K$68,"Fail",'Email Notifications'!$L$4:$L$68,"Cosmetic")+_xlfn.COUNTIFS('Admin'!$K$4:$K$55,"Fail",'Admin'!$L$4:$L$55,"Cosmetic")+_xlfn.COUNTIFS('Security & Authorization'!$K$4:$K$55,"Fail",'Security & Authorization'!$L$4:$L$55,"Cosmetic")+_xlfn.COUNTIFS('Mobile & Responsive'!$K$4:$K$48,"Fail",'Mobile & Responsive'!$L$4:$L$48,"Cosmetic")+_xlfn.COUNTIFS('Regression Testing'!$K$4:$K$47,"Fail",'Regression Testing'!$L$4:$L$47,"Cosmetic")+_xlfn.COUNTIFS('End-to-End Scenarios'!$K$4:$K$80,"Fail",'End-to-End Scenarios'!$L$4:$L$80,"Cosmetic")+_xlfn.COUNTIFS('Admin Customer Preview'!$K$4:$K$162,"Fail",'Admin Customer Preview'!$L$4:$L$162,"Cosmetic")+_xlfn.COUNTIFS('Wizard Type Switching'!$K$4:$K$97,"Fail",'Wizard Type Switching'!$L$4:$L$97,"Cosmetic")+_xlfn.COUNTIFS('Suspended Account Access'!$K$4:$K$91,"Fail",'Suspended Account Access'!$L$4:$L$91,"Cosmetic") -> 0 | C18: Visual or wording only; no functional impact.
A19: Failures with no Severity set | B19: =_xlfn.COUNTIFS('Business Registration'!$K$4:$K$121,"Fail",'Business Registration'!$L$4:$L$121,"")+_xlfn.COUNTIFS('Business Profile'!$K$4:$K$57,"Fail",'Business Profile'!$L$4:$L$57,"")+_xlfn.COUNTIFS('Trade Registration'!$K$4:$K$67,"Fail",'Trade Registration'!$L$4:$L$67,"")+_xlfn.COUNTIFS('Trade Approval'!$K$4:$K$64,"Fail",'Trade Approval'!$L$4:$L$64,"")+_xlfn.COUNTIFS('Trade Rejection'!$K$4:$K$46,"Fail",'Trade Rejection'!$L$4:$L$46,"")+_xlfn.COUNTIFS('Trade Suspension'!$K$4:$K$42,"Fail",'Trade Suspension'!$L$4:$L$42,"")+_xlfn.COUNTIFS('Pricing & Quantity Bands'!$K$4:$K$77,"Fail",'Pricing & Quantity Bands'!$L$4:$L$77,"")+_xlfn.COUNTIFS('Cart & Cart Repricing'!$K$4:$K$61,"Fail",'Cart & Cart Repricing'!$L$4:$L$61,"")+_xlfn.COUNTIFS('VAT & Tax'!$K$4:$K$49,"Fail",'VAT & Tax'!$L$4:$L$49,"")+_xlfn.COUNTIFS('Checkout'!$K$4:$K$61,"Fail",'Checkout'!$L$4:$L$61,"")+_xlfn.COUNTIFS('Payment'!$K$4:$K$48,"Fail",'Payment'!$L$4:$L$48,"")+_xlfn.COUNTIFS('Orders'!$K$4:$K$48,"Fail",'Orders'!$L$4:$L$48,"")+_xlfn.COUNTIFS('Invoice'!$K$4:$K$40,"Fail",'Invoice'!$L$4:$L$40,"")+_xlfn.COUNTIFS('Email Notifications'!$K$4:$K$68,"Fail",'Email Notifications'!$L$4:$L$68,"")+_xlfn.COUNTIFS('Admin'!$K$4:$K$55,"Fail",'Admin'!$L$4:$L$55,"")+_xlfn.COUNTIFS('Security & Authorization'!$K$4:$K$55,"Fail",'Security & Authorization'!$L$4:$L$55,"")+_xlfn.COUNTIFS('Mobile & Responsive'!$K$4:$K$48,"Fail",'Mobile & Responsive'!$L$4:$L$48,"")+_xlfn.COUNTIFS('Regression Testing'!$K$4:$K$47,"Fail",'Regression Testing'!$L$4:$L$47,"")+_xlfn.COUNTIFS('End-to-End Scenarios'!$K$4:$K$80,"Fail",'End-to-End Scenarios'!$L$4:$L$80,"")+_xlfn.COUNTIFS('Admin Customer Preview'!$K$4:$K$162,"Fail",'Admin Customer Preview'!$L$4:$L$162,"")+_xlfn.COUNTIFS('Wizard Type Switching'!$K$4:$K$97,"Fail",'Wizard Type Switching'!$L$4:$L$97,"")+_xlfn.COUNTIFS('Suspended Account Access'!$K$4:$K$91,"Fail",'Suspended Account Access'!$L$4:$L$91,"") -> 0 | C19: Set a Severity on every failed step, or it will not appear in the counts above.
A21: MODULE-WISE BREAKDOWN — EXECUTE IN THIS ORDER (top to bottom)
A22: Module / Sheet (execute in this order) | B22: Cases | C22: Steps | D22: Not Run | E22: Pass | F22: Fail | G22: Blocked | H22: N/A
A23: 1. Business Registration | B23: 20 | C23: =COUNTA('Business Registration'!$K$4:$K$121) -> 118 | D23: =COUNTIF('Business Registration'!$K$4:$K$121,"Not Run")+COUNTBLANK('Business Registration'!$K$4:$K$121) -> 118 | E23: =COUNTIF('Business Registration'!$K$4:$K$121,"Pass") -> 0 | F23: =COUNTIF('Business Registration'!$K$4:$K$121,"Fail") -> 0 | G23: =COUNTIF('Business Registration'!$K$4:$K$121,"Blocked") -> 0 | H23: =COUNTIF('Business Registration'!$K$4:$K$121,"Not Applicable") -> 0
A24: 2. Business Profile | B24: 10 | C24: =COUNTA('Business Profile'!$K$4:$K$57) -> 54 | D24: =COUNTIF('Business Profile'!$K$4:$K$57,"Not Run")+COUNTBLANK('Business Profile'!$K$4:$K$57) -> 54 | E24: =COUNTIF('Business Profile'!$K$4:$K$57,"Pass") -> 0 | F24: =COUNTIF('Business Profile'!$K$4:$K$57,"Fail") -> 0 | G24: =COUNTIF('Business Profile'!$K$4:$K$57,"Blocked") -> 0 | H24: =COUNTIF('Business Profile'!$K$4:$K$57,"Not Applicable") -> 0
A25: 3. Trade Registration | B25: 10 | C25: =COUNTA('Trade Registration'!$K$4:$K$67) -> 64 | D25: =COUNTIF('Trade Registration'!$K$4:$K$67,"Not Run")+COUNTBLANK('Trade Registration'!$K$4:$K$67) -> 64 | E25: =COUNTIF('Trade Registration'!$K$4:$K$67,"Pass") -> 0 | F25: =COUNTIF('Trade Registration'!$K$4:$K$67,"Fail") -> 0 | G25: =COUNTIF('Trade Registration'!$K$4:$K$67,"Blocked") -> 0 | H25: =COUNTIF('Trade Registration'!$K$4:$K$67,"Not Applicable") -> 0
A26: 4. Trade Approval | B26: 10 | C26: =COUNTA('Trade Approval'!$K$4:$K$64) -> 61 | D26: =COUNTIF('Trade Approval'!$K$4:$K$64,"Not Run")+COUNTBLANK('Trade Approval'!$K$4:$K$64) -> 61 | E26: =COUNTIF('Trade Approval'!$K$4:$K$64,"Pass") -> 0 | F26: =COUNTIF('Trade Approval'!$K$4:$K$64,"Fail") -> 0 | G26: =COUNTIF('Trade Approval'!$K$4:$K$64,"Blocked") -> 0 | H26: =COUNTIF('Trade Approval'!$K$4:$K$64,"Not Applicable") -> 0
A27: 5. Trade Rejection | B27: 8 | C27: =COUNTA('Trade Rejection'!$K$4:$K$46) -> 43 | D27: =COUNTIF('Trade Rejection'!$K$4:$K$46,"Not Run")+COUNTBLANK('Trade Rejection'!$K$4:$K$46) -> 43 | E27: =COUNTIF('Trade Rejection'!$K$4:$K$46,"Pass") -> 0 | F27: =COUNTIF('Trade Rejection'!$K$4:$K$46,"Fail") -> 0 | G27: =COUNTIF('Trade Rejection'!$K$4:$K$46,"Blocked") -> 0 | H27: =COUNTIF('Trade Rejection'!$K$4:$K$46,"Not Applicable") -> 0
A28: 6. Trade Suspension | B28: 7 | C28: =COUNTA('Trade Suspension'!$K$4:$K$42) -> 39 | D28: =COUNTIF('Trade Suspension'!$K$4:$K$42,"Not Run")+COUNTBLANK('Trade Suspension'!$K$4:$K$42) -> 39 | E28: =COUNTIF('Trade Suspension'!$K$4:$K$42,"Pass") -> 0 | F28: =COUNTIF('Trade Suspension'!$K$4:$K$42,"Fail") -> 0 | G28: =COUNTIF('Trade Suspension'!$K$4:$K$42,"Blocked") -> 0 | H28: =COUNTIF('Trade Suspension'!$K$4:$K$42,"Not Applicable") -> 0
A29: 7. Pricing & Quantity Bands | B29: 14 | C29: =COUNTA('Pricing & Quantity Bands'!$K$4:$K$77) -> 74 | D29: =COUNTIF('Pricing & Quantity Bands'!$K$4:$K$77,"Not Run")+COUNTBLANK('Pricing & Quantity Bands'!$K$4:$K$77) -> 74 | E29: =COUNTIF('Pricing & Quantity Bands'!$K$4:$K$77,"Pass") -> 0 | F29: =COUNTIF('Pricing & Quantity Bands'!$K$4:$K$77,"Fail") -> 0 | G29: =COUNTIF('Pricing & Quantity Bands'!$K$4:$K$77,"Blocked") -> 0 | H29: =COUNTIF('Pricing & Quantity Bands'!$K$4:$K$77,"Not Applicable") -> 0
A30: 8. Cart & Cart Repricing | B30: 11 | C30: =COUNTA('Cart & Cart Repricing'!$K$4:$K$61) -> 58 | D30: =COUNTIF('Cart & Cart Repricing'!$K$4:$K$61,"Not Run")+COUNTBLANK('Cart & Cart Repricing'!$K$4:$K$61) -> 58 | E30: =COUNTIF('Cart & Cart Repricing'!$K$4:$K$61,"Pass") -> 0 | F30: =COUNTIF('Cart & Cart Repricing'!$K$4:$K$61,"Fail") -> 0 | G30: =COUNTIF('Cart & Cart Repricing'!$K$4:$K$61,"Blocked") -> 0 | H30: =COUNTIF('Cart & Cart Repricing'!$K$4:$K$61,"Not Applicable") -> 0
A31: 9. VAT & Tax | B31: 9 | C31: =COUNTA('VAT & Tax'!$K$4:$K$49) -> 46 | D31: =COUNTIF('VAT & Tax'!$K$4:$K$49,"Not Run")+COUNTBLANK('VAT & Tax'!$K$4:$K$49) -> 46 | E31: =COUNTIF('VAT & Tax'!$K$4:$K$49,"Pass") -> 0 | F31: =COUNTIF('VAT & Tax'!$K$4:$K$49,"Fail") -> 0 | G31: =COUNTIF('VAT & Tax'!$K$4:$K$49,"Blocked") -> 0 | H31: =COUNTIF('VAT & Tax'!$K$4:$K$49,"Not Applicable") -> 0
A32: 10. Checkout | B32: 10 | C32: =COUNTA('Checkout'!$K$4:$K$61) -> 58 | D32: =COUNTIF('Checkout'!$K$4:$K$61,"Not Run")+COUNTBLANK('Checkout'!$K$4:$K$61) -> 58 | E32: =COUNTIF('Checkout'!$K$4:$K$61,"Pass") -> 0 | F32: =COUNTIF('Checkout'!$K$4:$K$61,"Fail") -> 0 | G32: =COUNTIF('Checkout'!$K$4:$K$61,"Blocked") -> 0 | H32: =COUNTIF('Checkout'!$K$4:$K$61,"Not Applicable") -> 0
A33: 11. Payment | B33: 9 | C33: =COUNTA('Payment'!$K$4:$K$48) -> 45 | D33: =COUNTIF('Payment'!$K$4:$K$48,"Not Run")+COUNTBLANK('Payment'!$K$4:$K$48) -> 45 | E33: =COUNTIF('Payment'!$K$4:$K$48,"Pass") -> 0 | F33: =COUNTIF('Payment'!$K$4:$K$48,"Fail") -> 0 | G33: =COUNTIF('Payment'!$K$4:$K$48,"Blocked") -> 0 | H33: =COUNTIF('Payment'!$K$4:$K$48,"Not Applicable") -> 0
A34: 12. Orders | B34: 7 | C34: =COUNTA('Orders'!$K$4:$K$48) -> 45 | D34: =COUNTIF('Orders'!$K$4:$K$48,"Not Run")+COUNTBLANK('Orders'!$K$4:$K$48) -> 45 | E34: =COUNTIF('Orders'!$K$4:$K$48,"Pass") -> 0 | F34: =COUNTIF('Orders'!$K$4:$K$48,"Fail") -> 0 | G34: =COUNTIF('Orders'!$K$4:$K$48,"Blocked") -> 0 | H34: =COUNTIF('Orders'!$K$4:$K$48,"Not Applicable") -> 0
A35: 13. Invoice | B35: 6 | C35: =COUNTA('Invoice'!$K$4:$K$40) -> 37 | D35: =COUNTIF('Invoice'!$K$4:$K$40,"Not Run")+COUNTBLANK('Invoice'!$K$4:$K$40) -> 37 | E35: =COUNTIF('Invoice'!$K$4:$K$40,"Pass") -> 0 | F35: =COUNTIF('Invoice'!$K$4:$K$40,"Fail") -> 0 | G35: =COUNTIF('Invoice'!$K$4:$K$40,"Blocked") -> 0 | H35: =COUNTIF('Invoice'!$K$4:$K$40,"Not Applicable") -> 0
A36: 14. Email Notifications | B36: 13 | C36: =COUNTA('Email Notifications'!$K$4:$K$68) -> 65 | D36: =COUNTIF('Email Notifications'!$K$4:$K$68,"Not Run")+COUNTBLANK('Email Notifications'!$K$4:$K$68) -> 65 | E36: =COUNTIF('Email Notifications'!$K$4:$K$68,"Pass") -> 0 | F36: =COUNTIF('Email Notifications'!$K$4:$K$68,"Fail") -> 0 | G36: =COUNTIF('Email Notifications'!$K$4:$K$68,"Blocked") -> 0 | H36: =COUNTIF('Email Notifications'!$K$4:$K$68,"Not Applicable") -> 0
A37: 15. Admin | B37: 8 | C37: =COUNTA('Admin'!$K$4:$K$55) -> 52 | D37: =COUNTIF('Admin'!$K$4:$K$55,"Not Run")+COUNTBLANK('Admin'!$K$4:$K$55) -> 52 | E37: =COUNTIF('Admin'!$K$4:$K$55,"Pass") -> 0 | F37: =COUNTIF('Admin'!$K$4:$K$55,"Fail") -> 0 | G37: =COUNTIF('Admin'!$K$4:$K$55,"Blocked") -> 0 | H37: =COUNTIF('Admin'!$K$4:$K$55,"Not Applicable") -> 0
A38: 16. Security & Authorization | B38: 9 | C38: =COUNTA('Security & Authorization'!$K$4:$K$55) -> 52 | D38: =COUNTIF('Security & Authorization'!$K$4:$K$55,"Not Run")+COUNTBLANK('Security & Authorization'!$K$4:$K$55) -> 52 | E38: =COUNTIF('Security & Authorization'!$K$4:$K$55,"Pass") -> 0 | F38: =COUNTIF('Security & Authorization'!$K$4:$K$55,"Fail") -> 0 | G38: =COUNTIF('Security & Authorization'!$K$4:$K$55,"Blocked") -> 0 | H38: =COUNTIF('Security & Authorization'!$K$4:$K$55,"Not Applicable") -> 0
A39: 17. Mobile & Responsive | B39: 8 | C39: =COUNTA('Mobile & Responsive'!$K$4:$K$48) -> 45 | D39: =COUNTIF('Mobile & Responsive'!$K$4:$K$48,"Not Run")+COUNTBLANK('Mobile & Responsive'!$K$4:$K$48) -> 45 | E39: =COUNTIF('Mobile & Responsive'!$K$4:$K$48,"Pass") -> 0 | F39: =COUNTIF('Mobile & Responsive'!$K$4:$K$48,"Fail") -> 0 | G39: =COUNTIF('Mobile & Responsive'!$K$4:$K$48,"Blocked") -> 0 | H39: =COUNTIF('Mobile & Responsive'!$K$4:$K$48,"Not Applicable") -> 0
A40: 18. Regression Testing | B40: 8 | C40: =COUNTA('Regression Testing'!$K$4:$K$47) -> 44 | D40: =COUNTIF('Regression Testing'!$K$4:$K$47,"Not Run")+COUNTBLANK('Regression Testing'!$K$4:$K$47) -> 44 | E40: =COUNTIF('Regression Testing'!$K$4:$K$47,"Pass") -> 0 | F40: =COUNTIF('Regression Testing'!$K$4:$K$47,"Fail") -> 0 | G40: =COUNTIF('Regression Testing'!$K$4:$K$47,"Blocked") -> 0 | H40: =COUNTIF('Regression Testing'!$K$4:$K$47,"Not Applicable") -> 0
A41: 19. End-to-End Scenarios | B41: 5 | C41: =COUNTA('End-to-End Scenarios'!$K$4:$K$80) -> 77 | D41: =COUNTIF('End-to-End Scenarios'!$K$4:$K$80,"Not Run")+COUNTBLANK('End-to-End Scenarios'!$K$4:$K$80) -> 77 | E41: =COUNTIF('End-to-End Scenarios'!$K$4:$K$80,"Pass") -> 0 | F41: =COUNTIF('End-to-End Scenarios'!$K$4:$K$80,"Fail") -> 0 | G41: =COUNTIF('End-to-End Scenarios'!$K$4:$K$80,"Blocked") -> 0 | H41: =COUNTIF('End-to-End Scenarios'!$K$4:$K$80,"Not Applicable") -> 0
A42: 20. Admin Customer Preview | B42: 24 | C42: =COUNTA('Admin Customer Preview'!$K$4:$K$162) -> 159 | D42: =COUNTIF('Admin Customer Preview'!$K$4:$K$162,"Not Run")+COUNTBLANK('Admin Customer Preview'!$K$4:$K$162) -> 159 | E42: =COUNTIF('Admin Customer Preview'!$K$4:$K$162,"Pass") -> 0 | F42: =COUNTIF('Admin Customer Preview'!$K$4:$K$162,"Fail") -> 0 | G42: =COUNTIF('Admin Customer Preview'!$K$4:$K$162,"Blocked") -> 0 | H42: =COUNTIF('Admin Customer Preview'!$K$4:$K$162,"Not Applicable") -> 0
A43: 21. Wizard Type Switching | B43: 11 | C43: =COUNTA('Wizard Type Switching'!$K$4:$K$97) -> 94 | D43: =COUNTIF('Wizard Type Switching'!$K$4:$K$97,"Not Run")+COUNTBLANK('Wizard Type Switching'!$K$4:$K$97) -> 94 | E43: =COUNTIF('Wizard Type Switching'!$K$4:$K$97,"Pass") -> 0 | F43: =COUNTIF('Wizard Type Switching'!$K$4:$K$97,"Fail") -> 0 | G43: =COUNTIF('Wizard Type Switching'!$K$4:$K$97,"Blocked") -> 0 | H43: =COUNTIF('Wizard Type Switching'!$K$4:$K$97,"Not Applicable") -> 0
A44: 22. Suspended Account Access | B44: 14 | C44: =COUNTA('Suspended Account Access'!$K$4:$K$91) -> 88 | D44: =COUNTIF('Suspended Account Access'!$K$4:$K$91,"Not Run")+COUNTBLANK('Suspended Account Access'!$K$4:$K$91) -> 88 | E44: =COUNTIF('Suspended Account Access'!$K$4:$K$91,"Pass") -> 0 | F44: =COUNTIF('Suspended Account Access'!$K$4:$K$91,"Fail") -> 0 | G44: =COUNTIF('Suspended Account Access'!$K$4:$K$91,"Blocked") -> 0 | H44: =COUNTIF('Suspended Account Access'!$K$4:$K$91,"Not Applicable") -> 0
A45: TOTAL | B45: =SUM(B23:B44) -> 231 | C45: =SUM(C23:C44) -> 1418 | D45: =SUM(D23:D44) -> 1418 | E45: =SUM(E23:E44) -> 0 | F45: =SUM(F23:F44) -> 0 | G45: =SUM(G23:G44) -> 0 | H45: =SUM(H23:H44) -> 0
A47: HOW TO USE THIS PACK
A48: 1. Read the Test Data sheet first. It carries the environment URLs, the account details to type, the real product and band prices to expect, and the list of features that are NOT implemented.
A49: 2. Work the sheets in the order of the breakdown above. Later sheets depend on accounts and approvals created by earlier ones.
A50: 3. Each row is ONE executable step. Do the step, compare what happened against Expected Result, then set Status on that row.
A51: 4. Record what you actually saw in Actual Result — always on a failure, and whenever the behaviour is surprising but arguably correct.
A52: 5. On a failure: set Status to Fail, set a Severity, raise a row in the Defect Log, and put its Bug ID in the Bug ID column.
A53: 6. Use Blocked when you could not run the step — environment down, test data missing, or an earlier failure stopped you. Blocked is not a Fail.
A54: 7. Use Not Applicable when the Expected Result says the feature is Not Available / Not Implemented. That is the documented state of this build, not a defect.
A55: 8. Do not assume a step passed because it looks like it should. Verify the actual value on screen, and in the database or admin panel where the step says to.
A56: 9. Prices: verify the figure charged, not only the figure displayed. Where a step tells you to re-check a total at the next screen, do it — the display and the charge are produced by different code.
A57: 10. Never run this pack against production data. All accounts and company details in this workbook are fictitious test data.

Sheet Test Data
A1: TEST DATA — Business & Trade Account Manual Testing
A2: *** ALL DATA ON THIS SHEET IS FICTITIOUS TEST DATA. It does not represent any real customer, company, VAT registration or bank detail. Use it only against a non-production test environment. ***
A3: Read this sheet before starting. The application collects a SINGLE "name" field, not separate first/last names, and a SINGLE free-text "billing address" field, not separate city/county/country/Eircode fields. The requested test data has been mapped onto the fields the application actually has. Rows shaded amber are places where the originally requested value would be REJECTED by the application and has been corrected.
A5: ENVIRONMENT UNDER TEST
A6: Field | B6: Value to enter | C6: Notes
A7: Storefront base URL | B7: http://127.0.0.1:8000 | C7: Laravel APP_URL from .env. Confirm with the dev team before starting; substitute your own environment URL throughout the pack.
A8: Registration page | B8: {storefront}/register | C8: Multi-step wizard. Steps are driven by a ?step= query parameter: type, details, verify, security, done.
A9: Customer dashboard | B9: {storefront}/user/dashboard | C9: Shows the account headline and trade status.
A10: Customer profile | B10: {storefront}/user/profile | C10: Edit name, phone, company details and PO preference.
A11: Customer orders | B11: {storefront}/user/orders | C11: Order history; carries the Invoice action.
A12: Checkout | B12: {storefront}/checkout | C12: Signed-in checkout.
A13: Guest checkout | B13: {storefront}/guest-checkout | C13: Guest flow (no account).
A14: Admin panel base URL | B14: http://127.0.0.1:3001/admin/ | C14: Nuxt admin panel. In this project the admin dev server runs on port 3001 under the /admin/ path. Confirm before starting.
A15: Admin — trade queue | B15: {admin}/trade-applications | C15: Review queue: approve / reject / suspend trade applications.
A16: Admin — customers | B16: {admin}/registered-users | C16: Customer list; open a customer to see account type, status and business profile.
A17: Admin — quantity bands | B17: {admin}/business-products | C17: Where business/trade quantity band prices are created and edited.
... A19: Email capture | B19: Mailtrap / MailHog / real inbox | C19: Confirm with the dev team how outbound mail is captured in this environment BEFORE running the notification tests. If mail is discarded, mark those cases Blocked, not Failed.
A21: BUSINESS CUSTOMER — primary test account (TD-BUS-01)
A22: Field | B22: Value to enter | C22: Notes
A23: Account type | B23: Business | C23: Chosen on step 1 (type) of the registration wizard.
A24: Name | B24: Daniel Murphy | C24: The application has ONE name field. "Daniel" and "Murphy" are entered together here.
A25: Email | B25: business.test01@example.com | C25: Must be unique among VERIFIED accounts.
A26: Phone | B26: +353871234567 | C26: Must be unique among VERIFIED accounts. Used for the emailed/texted verification code.
A27: Password | B27: Business@2026Test! | C27: Meets the rule: at least 10 characters, one capital, one digit.
A28: Confirm password | B28: Business@2026Test! | C28: Must match exactly.
A29: Company name | B29: Murphy IT Solutions Ltd | C29: Required for Business accounts.
A30: Sector | B30: Professional services / office | C30: REQUIRED dropdown. Valid options only: Professional services / office | School or college | Medical or dental practice | Hospitality or retail | Construction or trades | Charity or community group | Other.
A31: VAT number | B31: IE1234567A | C31: Optional for Business. Format check only — 6-18 letters/digits with at least 2 digits. Must be unique across verified accounts.
A32: Company registration no. | B32: 123456 | C32: DIGITS ONLY, 4-12 digits. The originally requested "IE123456" WILL BE REJECTED with "A company registration number is digits only."
A33: Billing address | B33: 25 Main Street, Dublin, Dublin, D02 X285, Ireland | C33: ONE free-text field. There are no separate City / County / Country / Eircode inputs, so the whole address is typed into this box.
... A36: Terms | B36: Ticked | C36: Required. Unticked gives "Tick the box to continue."
A38: TRADE CUSTOMER — primary test account (TD-TRD-01)
A39: Field | B39: Value to enter | C39: Notes
A40: Account type | B40: Trade | C40: Chosen on step 1 (type) of the registration wizard.
A41: Name | B41: James O'Brien | C41: Single name field. The apostrophe is deliberate — it doubles as an input-hygiene check.
A42: Email | B42: trade.test01@example.com | C42: Must be unique among verified accounts.
A43: Phone | B43: +353861234567 | C43: Must be unique among verified accounts.
A44: Password | B44: Trade@2026Test! | C44: At least 10 characters, one capital, one digit.
A45: Company name | B45: O'Brien Electrical Services Ltd | C45: Required for Trade accounts.
A46: Trade | B46: Field engineer / sole trader | C46: REQUIRED dropdown. "Electrical Contractor" is NOT an option. Valid options only: Computer / laptop repair shop | Phone and tablet repair | IT reseller or MSP | Games console repair | Electronics or appliance repair | Field engineer / sole trader | Other.
A47: VAT number | B47: IE7654321B | C47: REQUIRED for Trade accounts (unlike Business, where it is optional).
A48: Company registration no. | B48: 654321 | C48: DIGITS ONLY. The requested "IE654321" WILL BE REJECTED.
A49: Billing address | B49: 42 Industrial Estate, Cork, Cork, T12 AB12, Ireland | C49: Single free-text field.
A50: Expected monthly spend | B50: €2,000 – €5,000 | C50: REQUIRED dropdown. Valid options only: Under €500 | €500 – €2,000 | €2,000 – €5,000 | Over €5,000.
... A54: PO number (checkout) | B54: PO-2026-00125 | C54: Entered at CHECKOUT, not at registration. Max 64 characters.
A56: ADDITIONAL ACCOUNTS — create one per scenario
A57: Field | B57: Value to enter | C57: Notes
A58: Trade rejection account | B58: trade.reject01@example.com | C58: Phone +353861234568. Used by the Trade Rejection sheet.
A59: Trade suspension account | B59: trade.suspend01@example.com | C59: Phone +353861234569. Approved first, then suspended.
A60: Trade re-application account | B60: trade.reapply01@example.com | C60: Phone +353861234570. Rejected, then moved back to Pending, then Approved.
A61: Business duplicate-test account | B61: business.dup01@example.com | C61: Phone +353871234568. Used for duplicate email / duplicate VAT checks.
A62: Business second account | B62: business.test02@example.com | C62: Phone +353871234569. Used for cross-account security checks.
A63: Personal regression account | B63: personal.test01@example.com | C63: Phone +353871234570. Used by the Regression sheet.
A64: Password for all extras | B64: Test@2026Secure! | C64: Meets the strength rule.
A65: Every account must use an email address and a phone number not already on a VERIFIED account. If you re-run the pack, increment the numbers (business.test02, business.test03 ...) rather than reusing an address.
A67: PRODUCT AND PRICING DATA — read from the test database
A68: Field | B68: Value to enter | C68: Notes
A69: Test product | B69: testing product | C69: Product ID 99240288, slug "testing-product". Confirm it is still published before you start.
A70: Retail (ex VAT) price | B70: €505.00 | C70: The retail unit price all band prices are compared against.
A71: Tax rule | B71: VAT23 — 23% (percentage) | C71: Product has excludeVAT = 0, so it IS taxable, at tax rule 1 (VAT23, 23%).
A72: Retail (inc VAT) price | B72: €621.15 | C72: 505.00 x 1.23. Shown as the VAT-inclusive price.
A73: Band: quantity 5 to 10 | B73: €450.00 ex VAT | C73: Wholesale 500.00 less a fixed 50.00.
A74: Band: quantity 11 to 20 | B74: €430.00 ex VAT | C74: Wholesale 500.00 less a fixed 70.00.
A75: Band: quantity 21 to 30 | B75: €420.00 ex VAT | C75: Wholesale 500.00 less a fixed 80.00.
A76: Quantity 1 to 4 | B76: €505.00 ex VAT (RETAIL) | C76: IMPORTANT: there is NO band below quantity 5. An entitled account still pays retail at quantity 1-4. This is correct behaviour, not a defect.
A77: Quantity 31 and above | B77: €505.00 ex VAT (RETAIL) | C77: IMPORTANT: the top band STOPS at 30. Quantity 31+ falls back to retail. This is correct behaviour for this data set, not a defect.
A78: These band figures are the ones configured in the test database at the time this pack was written. Re-check them in Admin > business-products before you begin; if they have changed, update the expected values in the Pricing, Cart, VAT and Checkout sheets to match.
A80: EXPECTED PRICE CALCULATIONS — entitled account (Business, or Trade once Approved)
A81: Field | B81: Value to enter | C81: Notes
A82: Quantity | B82: Unit price ex VAT / Line ex VAT | C82: VAT at 23% / Line inc VAT
A83: Qty 1 | B83: €505.00 each / €505.00 ex VAT | C83: VAT €116.15 / €621.15 inc VAT
A84: Qty 4 | B84: €505.00 each / €2,020.00 ex VAT | C84: VAT €464.60 / €2,484.60 inc VAT
A85: Qty 5 | B85: €450.00 each / €2,250.00 ex VAT | C85: VAT €517.50 / €2,767.50 inc VAT
A86: Qty 10 | B86: €450.00 each / €4,500.00 ex VAT | C86: VAT €1,035.00 / €5,535.00 inc VAT
A87: Qty 11 | B87: €430.00 each / €4,730.00 ex VAT | C87: VAT €1,087.90 / €5,817.90 inc VAT
A88: Qty 20 | B88: €430.00 each / €8,600.00 ex VAT | C88: VAT €1,978.00 / €10,578.00 inc VAT
A89: Qty 21 | B89: €420.00 each / €8,820.00 ex VAT | C89: VAT €2,028.60 / €10,848.60 inc VAT
A90: Qty 25 | B90: €420.00 each / €10,500.00 ex VAT | C90: VAT €2,415.00 / €12,915.00 inc VAT
A91: Qty 30 | B91: €420.00 each / €12,600.00 ex VAT | C91: VAT €2,898.00 / €15,498.00 inc VAT
A92: Qty 31 | B92: €505.00 each / €15,655.00 ex VAT | C92: VAT €3,600.65 / €19,255.65 inc VAT
A93: VAT is charged on the BAND price, not on the retail price. A non-entitled account (personal, or trade still pending/rejected/suspended) pays €505.00 per unit at every quantity above.
A95: FEATURES NOT IMPLEMENTED — mark test cases "Not Applicable", do NOT raise defects
A96: Field | B96: Value to enter | C96: Notes
A97: Account type change | B97: NOT AVAILABLE / NOT IMPLEMENTED | C97: There is no self-serve or admin workflow to change an existing account from personal to business or trade. A different account type means a new registration.
A98: VAT number validation against VIES | B98: NOT AVAILABLE / NOT IMPLEMENTED | C98: The VAT check is a FORMAT check only (6-18 alphanumerics, 2+ digits). It does not verify the number exists or belongs to the company. A well-formed but fictitious number is ACCEPTED by design.
A99: Country-based VAT rules | B99: NOT AVAILABLE / NOT IMPLEMENTED | C99: VAT is decided per product (excludeVAT + tax rule), not by the customer country or by whether a VAT number was supplied. There is no reverse-charge / zero-rating for EU cross-border trade.
A100: Separate first/last name fields | B100: NOT AVAILABLE / NOT IMPLEMENTED | C100: One "name" field only.
A101: Structured address fields | B101: NOT AVAILABLE / NOT IMPLEMENTED | C101: One free-text billing address field. No separate city/county/country/Eircode inputs and no Eircode format validation.
A102: Years in business | B102: NOT AVAILABLE / NOT IMPLEMENTED | C102: Not collected at registration.
A103: Live admin updates | B103: NOT AVAILABLE / NOT IMPLEMENTED | C103: There is no WebSocket/push transport. Admin screens need a manual refresh to show a change made elsewhere.
A104: If you find any of the above DOES work, that is worth reporting as a documentation defect — but it is not a functional failure.

Sheet Business Registration
A1: Business Registration
A2: Registration is a multi-step wizard at {storefront}/register: Type > Details > Verify > Security > Done. The application collects ONE name field and ONE free-text billing address. A Business account opens ACTIVE and gets band pricing immediately once the email is confirmed - it does not wait for staff verification.
A3: Test Case ID | B3: Module | C3: Test Scenario | D3: Priority | E3: Preconditions | F3: Test Data | G3: Step No. | H3: Action / Steps | I3: Expected Result | J3: Actual Result | K3: Status | L3: Severity | M3: Bug ID | N3: Tester Comments
A4: BRG-001 | B4: Business Registration | C4: Open the registration page and confirm the account-type step | D4: High | E4: No user signed in. Browser cache cleared. | F4: URL: {storefront}/register | G4: 1 | H4: Open a browser and go to {storefront}/register. | I4: The registration page loads with no PHP error, no blank screen and no console error. The first step is the account-type chooser. | K4: Not Run
A5: BRG-001 | B5: Business Registration | C5: Open the registration page and confirm the account-type step | D5: High | G5: 2 | H5: Look at the step indicator at the top of the form. | I5: Four steps are shown in order: Type, Details, Verify, Security. "Type" is the current step. | K5: Not Run
A6: BRG-001 | B6: Business Registration | C6: Open the registration page and confirm the account-type step | D6: High | G6: 3 | H6: Read the account type options offered. | I6: Exactly three choices are offered: Personal, Business and Trade. Record the wording of each. | K6: Not Run
A7: BRG-001 | B7: Business Registration | C7: Open the registration page and confirm the account-type step | D7: High | G7: 4 | H7: Check the browser address bar. | I7: The URL is {storefront}/register. The wizard tracks its position with a ?step= query parameter as you move forward. | K7: Not Run
A8: BRG-002 | B8: Business Registration | C8: Select Business and confirm the Business detail fields appear | D8: Critical | E8: BRG-001 done. | F8: Account type: Business | G8: 1 | H8: Select the Business account option and continue to the Details step. | I8: The form advances to Details. The URL gains ?step=details. The heading and intro text describe a business account. | K8: Not Run
A9: BRG-002 | B9: Business Registration | C9: Select Business and confirm the Business detail fields appear | D9: Critical | G9: 2 | H9: List every field shown on the Details step. | I9: The form shows: Name, Email, Phone, Password (and confirm), Company name, Sector (dropdown), VAT number, Company registration number, Billing address, "requires PO number" checkbox, "credit account application" checkbox, marketing preference checkboxes and a Terms checkbox. | K9: Not Run
A10: BRG-002 | B10: Business Registration | C10: Select Business and confirm the Business detail fields appear | D10: Critical | G10: 3 | H10: Open the Sector dropdown and read the options. | I10: Exactly seven options: Professional services / office | School or college | Medical or dental practice | Hospitality or retail | Construction or trades | Charity or community group | Other. | K10: Not Run
A11: BRG-002 | B11: Business Registration | C11: Select Business and confirm the Business detail fields appear | D11: Critical | G11: 4 | H11: Confirm there is NO separate first name and last name field. | I11: Correct - there is ONE Name field. Separate first/last name fields are Not Available / Not Implemented. Mark this step Not Applicable if you were expecting two fields; it is not a defect. | K11: Not Run
A12: BRG-002 | B12: Business Registration | C12: Select Business and confirm the Business detail fields appear | D12: Critical | G12: 5 | H12: Confirm there is NO separate City, County, Country or Eircode field. | I12: Correct - there is ONE free-text Billing address field. Structured address fields are Not Available / Not Implemented. | K12: Not Run
A13: BRG-002 | B13: Business Registration | C13: Select Business and confirm the Business detail fields appear | D13: Critical | G13: 6 | H13: Confirm there is NO "years in business" field. | I13: Correct - Not Available / Not Implemented for all account types. | K13: Not Run
A14: BRG-003 | B14: Business Registration | C14: Complete a valid Business registration end to end | D14: Critical | E14: BRG-002 done. The email address and phone number are not already on a verified account. | F14: Name: Daniel Murphy | Email: business.test01@example.com | Phone: +353871234567 | Password: Business@2026Test! | Company: Murphy IT Solutions Ltd | Sector: Professional services / office | VAT: IE1234567A | Company reg no: 123456 | Billing address: 25 Main Street, Dublin, Dublin, D02 X285, Ireland | Requires PO: ticked | Credit application: ticked | G14: 1 | H14: Enter Name: Daniel Murphy | I14: The field accepts the value with no error. | K14: Not Run
A15: BRG-003 | B15: Business Registration | C15: Complete a valid Business registration end to end | D15: Critical | G15: 2 | H15: Enter Email: business.test01@example.com | I15: Accepted, no inline error. | K15: Not Run
A16: BRG-003 | B16: Business Registration | C16: Complete a valid Business registration end to end | D16: Critical | G16: 3 | H16: Enter Phone: +353871234567 | I16: Accepted. If the form shows a country/format hint, the number is recognised as valid. | K16: Not Run
A17: BRG-003 | B17: Business Registration | C17: Complete a valid Business registration end to end | D17: Critical | G17: 4 | H17: Enter Password: Business@2026Test! and repeat it in the confirm field. | I17: Both accepted and they match. Any strength indicator shows the rule is met (10+ characters, a capital and a digit). | K17: Not Run
A18: BRG-003 | B18: Business Registration | C18: Complete a valid Business registration end to end | D18: Critical | G18: 5 | H18: Enter Company name: Murphy IT Solutions Ltd | I18: Accepted. | K18: Not Run
A19: BRG-003 | B19: Business Registration | C19: Complete a valid Business registration end to end | D19: Critical | G19: 6 | H19: Choose Sector: Professional services / office | I19: Accepted. | K19: Not Run
A20: BRG-003 | B20: Business Registration | C20: Complete a valid Business registration end to end | D20: Critical | G20: 7 | H20: Enter VAT number: IE1234567A | I20: Accepted. VAT is OPTIONAL for a Business account. | K20: Not Run
A21: BRG-003 | B21: Business Registration | C21: Complete a valid Business registration end to end | D21: Critical | G21: 8 | H21: Enter Company registration number: 123456 | I21: Accepted. NOTE: this field is digits only - entering "IE123456" would be rejected. | K21: Not Run
A22: BRG-003 | B22: Business Registration | C22: Complete a valid Business registration end to end | D22: Critical | G22: 9 | H22: Enter Billing address: 25 Main Street, Dublin, Dublin, D02 X285, Ireland | I22: Accepted as a single free-text value. | K22: Not Run
A23: BRG-003 | B23: Business Registration | C23: Complete a valid Business registration end to end | D23: Critical | G23: 10 | H23: Tick "requires PO number" and "credit account application". | I23: Both tick. These are preferences - the credit tick records interest only and does not grant a credit account. | K23: Not Run
A24: BRG-003 | B24: Business Registration | C24: Complete a valid Business registration end to end | D24: Critical | G24: 11 | H24: Tick the Terms checkbox and submit the Details step. | I24: The form submits with no validation error and moves to the Verify step (?step=verify). | K24: Not Run
A25: BRG-003 | B25: Business Registration | C25: Complete a valid Business registration end to end | D25: Critical | G25: 12 | H25: Read the Verify step. | I25: It asks for a verification code and states where the code was sent. Retrieve the code from the configured mail capture tool. | K25: Not Run
A26: BRG-003 | B26: Business Registration | C26: Complete a valid Business registration end to end | D26: Critical | G26: 13 | H26: Enter the correct verification code and continue. | I26: The code is accepted and the wizard advances to the Security step (two-factor setup). | K26: Not Run
... A28: BRG-003 | B28: Business Registration | C28: Complete a valid Business registration end to end | D28: Critical | G28: 15 | H28: Read the confirmation on the Done step. | I28: It confirms the account is created. Record the exact wording in Actual Result. | K28: Not Run
A29: BRG-004 | B29: Business Registration | C29: Verify the Business account was created with the right state | D29: Critical | E29: BRG-003 completed successfully. | F29: Email: business.test01@example.com | G29: 1 | H29: Sign in to the storefront as business.test01@example.com. | I29: Sign-in succeeds and the customer dashboard loads. | K29: Not Run
A30: BRG-004 | B30: Business Registration | C30: Verify the Business account was created with the right state | D30: Critical | G30: 2 | H30: Open {storefront}/user/dashboard and read the account section. | I30: The account is shown as a Business account and as active. A one-line headline describes the account state. | K30: Not Run
A31: BRG-004 | B31: Business Registration | C31: Verify the Business account was created with the right state | D31: Critical | G31: 3 | H31: Confirm the dashboard does NOT show a trade application or a pending trade status. | I31: Correct - trade status belongs to Trade accounts only. A Business account has no trade application. | K31: Not Run
A32: BRG-004 | B32: Business Registration | C32: Verify the Business account was created with the right state | D32: Critical | G32: 4 | H32: In the admin panel open {admin}/registered-users and find business.test01@example.com. | I32: The customer is listed with account type Business. | K32: Not Run
A33: BRG-004 | B33: Business Registration | C33: Verify the Business account was created with the right state | D33: Critical | G33: 5 | H33: Open that customer record in admin. | I33: Account type = business; account status = active; verification status = pending (company details not yet checked by staff); trade status = empty/none. | K33: Not Run
A34: BRG-004 | B34: Business Registration | C34: Verify the Business account was created with the right state | D34: Critical | G34: 6 | H34: Confirm the business pricing entitlement on the admin record. | I34: The record shows the account IS entitled to business pricing. A Business account qualifies at signup - it does NOT have to wait for staff verification. Verification status and pricing entitlement are two separate facts. | K34: Not Run
A35: BRG-005 | B35: Business Registration | C35: Verify every value entered at registration was stored | D35: High | E35: BRG-004 done. | F35: All values from BRG-003. | G35: 1 | H35: In admin, open the customer record for business.test01@example.com and find the business profile section. | I35: A business profile exists for this customer. | K35: Not Run
A36: BRG-005 | B36: Business Registration | C36: Verify every value entered at registration was stored | D36: High | G36: 2 | H36: Compare Company name against what you typed. | I36: Shows exactly: Murphy IT Solutions Ltd | K36: Not Run
A37: BRG-005 | B37: Business Registration | C37: Verify every value entered at registration was stored | D37: High | G37: 3 | H37: Compare VAT number. | I37: Shows exactly: IE1234567A | K37: Not Run
A38: BRG-005 | B38: Business Registration | C38: Verify every value entered at registration was stored | D38: High | G38: 4 | H38: Compare Company registration number. | I38: Shows exactly: 123456 | K38: Not Run
A39: BRG-005 | B39: Business Registration | C39: Verify every value entered at registration was stored | D39: High | G39: 5 | H39: Compare Billing address. | I39: Shows the full address string exactly as typed, including the Eircode text. | K39: Not Run
A40: BRG-005 | B40: Business Registration | C40: Verify every value entered at registration was stored | D40: High | G40: 6 | H40: Compare Sector. | I40: Shows: Professional services / office | K40: Not Run
A41: BRG-005 | B41: Business Registration | C41: Verify every value entered at registration was stored | D41: High | G41: 7 | H41: Compare the PO requirement flag. | I41: Shows that this account requires a PO number. | K41: Not Run
A42: BRG-005 | B42: Business Registration | C42: Verify every value entered at registration was stored | D42: High | G42: 8 | H42: Compare the credit application flag. | I42: Shows that a credit account application was requested. | K42: Not Run
A43: BRG-005 | B43: Business Registration | C43: Verify every value entered at registration was stored | D43: High | G43: 9 | H43: Check whether any trade-only field was stored against this Business account. | I43: Trade-only fields (trade type, expected spend, website, resale confirmation) are empty for a Business account. They are deliberately not stored for this type. | K43: Not Run
A44: BRG-006 | B44: Business Registration | C44: Required-field validation on the Business Details step | D44: High | E44: At {storefront}/register, Business selected, Details step open. | F44: Leave fields empty as directed. | G44: 1 | H44: Leave every field empty and submit the Details step. | I44: The form does NOT submit. Validation errors are shown against the required fields. | K44: Not Run
A45: BRG-006 | B45: Business Registration | C45: Required-field validation on the Business Details step | D45: High | G45: 2 | H45: Clear only Company name and submit. | I45: Refused with the message: "Enter the company name." | K45: Not Run
A46: BRG-006 | B46: Business Registration | C46: Required-field validation on the Business Details step | D46: High | G46: 3 | H46: Restore Company name, clear Sector and submit. | I46: Refused with the message: "Choose what the business does." | K46: Not Run
A47: BRG-006 | B47: Business Registration | C47: Required-field validation on the Business Details step | D47: High | G47: 4 | H47: Restore Sector, clear Billing address and submit. | I47: Refused with the message: "We need a billing address for VAT invoices." | K47: Not Run
A48: BRG-006 | B48: Business Registration | C48: Required-field validation on the Business Details step | D48: High | G48: 5 | H48: Restore Billing address, clear Phone and submit. | I48: Refused with the message: "Enter a mobile number we can text." | K48: Not Run
A49: BRG-006 | B49: Business Registration | C49: Required-field validation on the Business Details step | D49: High | G49: 6 | H49: Restore Phone, untick Terms and submit. | I49: Refused with the message: "Tick the box to continue." | K49: Not Run
A50: BRG-006 | B50: Business Registration | C50: Required-field validation on the Business Details step | D50: High | G50: 7 | H50: Confirm no account was created by any of the refused attempts. | I50: In admin, no customer exists for this email address. A refused registration must not create a partial account. | K50: Not Run
A51: BRG-007 | B51: Business Registration | C51: Email validation on Business registration | D51: High | E51: Business Details step open, all other fields valid. | F51: Invalid: daniel.murphy | daniel@ | @example.com | daniel murphy@example.com Duplicate: business.test01@example.com | G51: 1 | H51: Enter email "daniel.murphy" and submit. | I51: Refused as not a valid email address. | K51: Not Run
A52: BRG-007 | B52: Business Registration | C52: Email validation on Business registration | D52: High | G52: 2 | H52: Enter email "daniel@" and submit. | I52: Refused as not a valid email address. | K52: Not Run
A53: BRG-007 | B53: Business Registration | C53: Email validation on Business registration | D53: High | G53: 3 | H53: Enter email "@example.com" and submit. | I53: Refused as not a valid email address. | K53: Not Run
A54: BRG-007 | B54: Business Registration | C54: Email validation on Business registration | D54: High | G54: 4 | H54: Enter email "daniel murphy@example.com" (with a space) and submit. | I54: Refused as not a valid email address. | K54: Not Run
A55: BRG-007 | B55: Business Registration | C55: Email validation on Business registration | D55: High | G55: 5 | H55: Enter business.test01@example.com - the address already registered and verified in BRG-003 - and submit. | I55: Refused with: "That email address already has an account. Sign in instead, or reset your password." | K55: Not Run
A56: BRG-007 | B56: Business Registration | C56: Email validation on Business registration | D56: High | G56: 6 | H56: Confirm the duplicate attempt did not alter the existing account. | I56: The original account is untouched: same company details, same status, still usable. | K56: Not Run
A57: BRG-008 | B57: Business Registration | C57: Phone validation and phone uniqueness | D57: Medium | E57: Business Details step open, all other fields valid, a fresh unused email in the email field. | F57: Duplicate phone: +353871234567 (already on business.test01@example.com) | G57: 1 | H57: Clear the phone field and submit. | I57: Refused with: "Enter a mobile number we can text." | K57: Not Run
A58: BRG-008 | B58: Business Registration | C58: Phone validation and phone uniqueness | D58: Medium | G58: 2 | H58: Enter obvious non-numeric text such as "not a phone" and submit. | I58: Refused. Record the exact message shown in Actual Result. | K58: Not Run
A59: BRG-008 | B59: Business Registration | C59: Phone validation and phone uniqueness | D59: Medium | G59: 3 | H59: Enter +353871234567, which is already on the verified account from BRG-003, with a DIFFERENT email address, and submit. | I59: Refused with: "That mobile number is already on another account. Use a different number." | K59: Not Run
A60: BRG-008 | B60: Business Registration | C60: Phone validation and phone uniqueness | D60: Medium | G60: 4 | H60: Enter an unused number such as +353871234599 and submit. | I60: Accepted - the registration proceeds past the phone check. | K60: Not Run
A61: BRG-009 | B61: Business Registration | C61: Password strength and confirmation validation | D61: Critical | E61: Business Details step open, all other fields valid. | F61: Weak: Test1 | abcdefghij1 | ABCDEFGHIJ | Password12 Valid: Business@2026Test! | G61: 1 | H61: Enter password "Test1" (too short) and submit. | I61: Refused with: "Use at least 10 characters, with a capital letter and a number." | K61: Not Run
A62: BRG-009 | B62: Business Registration | C62: Password strength and confirmation validation | D62: Critical | G62: 2 | H62: Enter "abcdefghij1" (10 chars, a digit, NO capital) and submit. | I62: Refused with the same message - a capital letter is required. | K62: Not Run
A63: BRG-009 | B63: Business Registration | C63: Password strength and confirmation validation | D63: Critical | G63: 3 | H63: Enter "ABCDEFGHIJ" (10 chars, a capital, NO digit) and submit. | I63: Refused with the same message - a digit is required. | K63: Not Run
A64: BRG-009 | B64: Business Registration | C64: Password strength and confirmation validation | D64: Critical | G64: 4 | H64: Enter "Password12" (10 chars, capital, digit) and submit. | I64: ACCEPTED - this meets the rule as implemented. Note there is no dictionary or common-password check; that is Not Available / Not Implemented. | K64: Not Run
A65: BRG-009 | B65: Business Registration | C65: Password strength and confirmation validation | D65: Critical | G65: 5 | H65: Enter Business@2026Test! in the password field and a DIFFERENT value in the confirm field, then submit. | I65: Refused - the form reports that the two passwords do not match, and does not submit. | K65: Not Run
A66: BRG-009 | B66: Business Registration | C66: Password strength and confirmation validation | D66: Critical | G66: 6 | H66: Make both fields Business@2026Test! and submit. | I66: Accepted and the form proceeds. | K66: Not Run
A67: BRG-010 | B67: Business Registration | C67: VAT number validation - the format check and its limits | D67: High | E67: Business Details step open, all other fields valid, fresh email and phone. | F67: Invalid: n/a | will send later | 12 | ???????? Valid: IE1234567A | IE 123 4567 A | G67: 1 | H67: Enter VAT number "n/a" and submit. | I67: Refused with: "That does not look like a VAT number. Enter it as it appears on your VAT certificate." | K67: Not Run
A68: BRG-010 | B68: Business Registration | C68: VAT number validation - the format check and its limits | D68: High | G68: 2 | H68: Enter VAT number "will send later" and submit. | I68: Refused with the same message. | K68: Not Run
A69: BRG-010 | B69: Business Registration | C69: VAT number validation - the format check and its limits | D69: High | G69: 3 | H69: Enter VAT number "12" (too short) and submit. | I69: Refused with the same message. | K69: Not Run
A70: BRG-010 | B70: Business Registration | C70: VAT number validation - the format check and its limits | D70: High | G70: 4 | H70: Enter VAT number "ABCDEFGH" (8 letters, no digits) and submit. | I70: Refused - the check requires at least two digits. | K70: Not Run
A71: BRG-010 | B71: Business Registration | C71: VAT number validation - the format check and its limits | D71: High | G71: 5 | H71: Enter VAT number "IE 123 4567 A" with spaces and submit. | I71: ACCEPTED - spaces, dots, hyphens and slashes are stripped before the check. | K71: Not Run
A72: BRG-010 | B72: Business Registration | C72: VAT number validation - the format check and its limits | D72: High | G72: 6 | H72: Enter VAT number "IE1234567A" and submit. | I72: Accepted. | K72: Not Run
A73: BRG-010 | B73: Business Registration | C73: VAT number validation - the format check and its limits | D73: High | G73: 7 | H73: Enter a well-formed but entirely fictitious VAT number such as "IE9999999Z" and submit. | I73: ACCEPTED. The check is FORMAT ONLY - it does not verify the number exists or belongs to the company. Validation against VIES is Not Available / Not Implemented. This is correct behaviour, not a defect. | K73: Not Run
A74: BRG-010 | B74: Business Registration | C74: VAT number validation - the format check and its limits | D74: High | G74: 8 | H74: Leave the VAT number blank entirely and submit. | I74: Accepted - VAT is OPTIONAL for a Business account (it is required only for Trade). | K74: Not Run
A75: BRG-011 | B75: Business Registration | C75: Company registration number validation | D75: Medium | E75: Business Details step open, all other fields valid, fresh email and phone. | F75: Invalid: IE123456 | ABC123 | 12 Valid: 123456 | 123-456 | G75: 1 | H75: Enter company registration number "IE123456" and submit. | I75: REFUSED with: "A company registration number is digits only." Letters are not accepted, so the value originally proposed for this test data cannot be used. | K75: Not Run
A76: BRG-011 | B76: Business Registration | C76: Company registration number validation | D76: Medium | G76: 2 | H76: Enter "ABC123" and submit. | I76: Refused with the same message. | K76: Not Run
A77: BRG-011 | B77: Business Registration | C77: Company registration number validation | D77: Medium | G77: 3 | H77: Enter "12" (too short) and submit. | I77: Refused - the value must be 4 to 12 digits. | K77: Not Run
A78: BRG-011 | B78: Business Registration | C78: Company registration number validation | D78: Medium | G78: 4 | H78: Enter "1234567890123" (13 digits, too long) and submit. | I78: Refused - more than 12 digits. | K78: Not Run
A79: BRG-011 | B79: Business Registration | C79: Company registration number validation | D79: Medium | G79: 5 | H79: Enter "123-456" and submit. | I79: ACCEPTED - separators are stripped before the digits are counted. | K79: Not Run
A80: BRG-011 | B80: Business Registration | C80: Company registration number validation | D80: Medium | G80: 6 | H80: Enter "123456" and submit. | I80: Accepted. | K80: Not Run
A81: BRG-011 | B81: Business Registration | C81: Company registration number validation | D81: Medium | G81: 7 | H81: Leave the field blank and submit. | I81: Accepted - the company registration number is optional. | K81: Not Run
A82: BRG-012 | B82: Business Registration | C82: Duplicate VAT number across accounts | D82: High | E82: The Business account from BRG-003 exists and is VERIFIED, holding VAT number IE1234567A. | F82: New account: business.dup01@example.com | Phone +353871234568 | VAT IE1234567A | G82: 1 | H82: Start a new Business registration with email business.dup01@example.com and phone +353871234568. | I82: The form accepts these as unused. | K82: Not Run
A83: BRG-012 | B83: Business Registration | C83: Duplicate VAT number across accounts | D83: High | G83: 2 | H83: Enter VAT number IE1234567A - the number already held by the verified account from BRG-003 - and submit. | I83: Refused with: "That VAT number is already registered to another account. Sign in instead, or contact us." | K83: Not Run
A84: BRG-012 | B84: Business Registration | C84: Duplicate VAT number across accounts | D84: High | G84: 3 | H84: Change the VAT number to IE2222222C and submit. | I84: Accepted - one VAT number, one account. | K84: Not Run
A85: BRG-012 | B85: Business Registration | C85: Duplicate VAT number across accounts | D85: High | G85: 4 | H85: Confirm the original account still holds IE1234567A. | I85: Unchanged in admin. | K85: Not Run
A86: BRG-013 | B86: Business Registration | C86: Website field validation (where shown) | D86: Low | E86: Business Details step open. NOTE: the website field is collected for TRADE accounts; if it is not present on the Business form, mark this case Not Applicable. | F86: Invalid: not a website Valid: example.com | https://example.com | G86: 1 | H86: If a Website field is shown, enter "not a website" and submit. | I86: Refused with: "Enter a valid website address, for example yourcompany.ie." | K86: Not Run
A87: BRG-013 | B87: Business Registration | C87: Website field validation (where shown) | D87: Low | G87: 2 | H87: Enter "example.com" and submit. | I87: Accepted - the scheme is optional. | K87: Not Run
A88: BRG-013 | B88: Business Registration | C88: Website field validation (where shown) | D88: Low | G88: 3 | H88: Enter "https://example.com" and submit. | I88: Accepted. | K88: Not Run
A89: BRG-013 | B89: Business Registration | C89: Website field validation (where shown) | D89: Low | G89: 4 | H89: If no Website field is shown on the Business form. | I89: Mark this case Not Applicable - the website field belongs to the Trade form. | K89: Not Run
A90: BRG-014 | B90: Business Registration | C90: Wizard navigation - back and forward between steps | D90: Medium | E90: A Business registration in progress with the Details step filled in but not submitted. | F90: Values from BRG-003. | G90: 1 | H90: Fill the Details step completely but do not submit. Use the wizard control to go back to the Type step. | I90: The wizard returns to the Type step without submitting anything. | K90: Not Run
A91: BRG-014 | B91: Business Registration | C91: Wizard navigation - back and forward between steps | D91: Medium | G91: 2 | H91: Move forward to the Details step again. | I91: Record in Actual Result whether the values you typed are still present or were cleared. Both are defensible; what matters is that the tester documents the real behaviour. | K91: Not Run
A92: BRG-014 | B92: Business Registration | C92: Wizard navigation - back and forward between steps | D92: Medium | G92: 3 | H92: Change the account type from Business to Personal, then back to Business. | I92: The form shows the correct field set for each type: Personal has no company fields; Business has company name, sector and billing address. | K92: Not Run
A93: BRG-014 | B93: Business Registration | C93: Wizard navigation - back and forward between steps | D93: Medium | G93: 4 | H93: Change the account type from Business to Trade. | I93: The field set changes to the Trade set: trade dropdown, expected spend, resale confirmation, and VAT becomes REQUIRED. | K93: Not Run
A94: BRG-015 | B94: Business Registration | C94: Browser refresh and browser back button during registration | D94: Medium | E94: A Business registration in progress, Details step filled but not submitted. | F94: Values from BRG-003. | G94: 1 | H94: With the Details step filled in but not submitted, press F5 to refresh. | I94: The page reloads without a script error. Record whether the entered values survive or are cleared. | K94: Not Run
A95: BRG-015 | B95: Business Registration | C95: Browser refresh and browser back button during registration | D95: Medium | G95: 2 | H95: Confirm no account was created by the refresh. | I95: No customer exists in admin for this email - an unsubmitted form must not create an account. | K95: Not Run
A96: BRG-015 | B96: Business Registration | C96: Browser refresh and browser back button during registration | D96: Medium | G96: 3 | H96: Submit the Details step to reach the Verify step, then press the browser Back button. | I96: The application returns to a previous step without crashing. Record the behaviour. | K96: Not Run
A97: BRG-015 | B97: Business Registration | C97: Browser refresh and browser back button during registration | D97: Medium | G97: 4 | H97: From there navigate forward again to the Verify step. | I97: The verification step is reachable and the code you were sent is still the one expected. If a new code is required, record that. | K97: Not Run
A98: BRG-015 | B98: Business Registration | C98: Browser refresh and browser back button during registration | D98: Medium | G98: 5 | H98: Complete verification and confirm only ONE account exists for this email. | I98: Exactly one customer record exists in admin. Refreshing and going back must not create duplicates. | K98: Not Run
A99: BRG-016 | B99: Business Registration | C99: Re-registering an email that was never verified | D99: Medium | E99: An earlier registration attempt reached the Verify step for an address but the code was never entered. | F99: Email: business.test02@example.com | Phone: +353871234569 | G99: 1 | H99: Register a Business account with business.test02@example.com but stop at the Verify step without entering the code. | I99: An unverified customer row exists. The account is not usable yet. | K99: Not Run
A100: BRG-016 | B100: Business Registration | C100: Re-registering an email that was never verified | D100: Medium | G100: 2 | H100: Start registration again with the SAME email address and a different company name. | I100: ACCEPTED - registering again over an unverified row is the supported way to start over if the code was lost. | K100: Not Run
A101: BRG-016 | B101: Business Registration | C101: Re-registering an email that was never verified | D101: Medium | G101: 3 | H101: Complete verification this time and check the stored company name. | I101: The company name from the SECOND attempt is stored - the pending row is overwritten wholesale. | K101: Not Run
...

Sheet Business Profile
A1: Business Profile
A2: The customer profile at {storefront}/user/profile. Name, phone and marketing preferences are the customer's own; company details are editable here too. Account TYPE is not editable by the customer - and there is no workflow anywhere to change it.
A3: Test Case ID | B3: Module | C3: Test Scenario | D3: Priority | E3: Preconditions | F3: Test Data | G3: Step No. | H3: Action / Steps | I3: Expected Result | J3: Actual Result | K3: Status | L3: Severity | M3: Bug ID | N3: Tester Comments
A4: BPR-001 | B4: Business Profile | C4: Open the Business profile and verify the registration data is all there | D4: Critical | E4: Signed in as business.test01@example.com. | F4: All values from BRG-003. | G4: 1 | H4: Sign in as business.test01@example.com and open {storefront}/user/profile. | I4: The profile page loads with no error. | K4: Not Run
A5: BPR-001 | B5: Business Profile | C5: Open the Business profile and verify the registration data is all there | D5: Critical | G5: 2 | H5: Compare the Name shown against what was registered. | I5: Shows: Daniel Murphy | K5: Not Run
A6: BPR-001 | B6: Business Profile | C6: Open the Business profile and verify the registration data is all there | D6: Critical | G6: 3 | H6: Compare the Email shown. | I6: Shows: business.test01@example.com | K6: Not Run
A7: BPR-001 | B7: Business Profile | C7: Open the Business profile and verify the registration data is all there | D7: Critical | G7: 4 | H7: Compare the Phone shown. | I7: Shows: +353871234567 | K7: Not Run
A8: BPR-001 | B8: Business Profile | C8: Open the Business profile and verify the registration data is all there | D8: Critical | G8: 5 | H8: Compare the Company name shown. | I8: Shows: Murphy IT Solutions Ltd | K8: Not Run
A9: BPR-001 | B9: Business Profile | C9: Open the Business profile and verify the registration data is all there | D9: Critical | G9: 6 | H9: Compare the VAT number shown. | I9: Shows: IE1234567A | K9: Not Run
A10: BPR-001 | B10: Business Profile | C10: Open the Business profile and verify the registration data is all there | D10: Critical | G10: 7 | H10: Compare the Company registration number shown. | I10: Shows: 123456 | K10: Not Run
A11: BPR-001 | B11: Business Profile | C11: Open the Business profile and verify the registration data is all there | D11: Critical | G11: 8 | H11: Compare the Billing address shown. | I11: Shows the full address as registered. | K11: Not Run
A12: BPR-001 | B12: Business Profile | C12: Open the Business profile and verify the registration data is all there | D12: Critical | G12: 9 | H12: Compare the Sector shown. | I12: Shows: Professional services / office | K12: Not Run
A13: BPR-001 | B13: Business Profile | C13: Open the Business profile and verify the registration data is all there | D13: Critical | G13: 10 | H13: Compare the PO requirement setting. | I13: Shows that a PO number is required for this account (it was ticked at registration). | K13: Not Run
A14: BPR-001 | B14: Business Profile | C14: Open the Business profile and verify the registration data is all there | D14: Critical | G14: 11 | H14: Confirm nothing entered at registration is missing from this screen. | I14: Every value entered during registration is either shown or accounted for. List anything missing in Actual Result - a value collected at registration but never shown back is a defect. | K14: Not Run
A15: BPR-002 | B15: Business Profile | C15: Edit the name and confirm it persists | D15: High | E15: Signed in as business.test01@example.com. | F15: New name: Daniel J Murphy | G15: 1 | H15: Change the Name field to "Daniel J Murphy" and save. | I15: Saved with a success confirmation. | K15: Not Run
A16: BPR-002 | B16: Business Profile | C16: Edit the name and confirm it persists | D16: High | G16: 2 | H16: Refresh the page. | I16: The name still shows Daniel J Murphy. | K16: Not Run
A17: BPR-002 | B17: Business Profile | C17: Edit the name and confirm it persists | D17: High | G17: 3 | H17: Sign out and sign back in, then reopen the profile. | I17: The name is still Daniel J Murphy. | K17: Not Run
A18: BPR-002 | B18: Business Profile | C18: Edit the name and confirm it persists | D18: High | G18: 4 | H18: Check the same customer in the admin panel. | I18: Admin shows the updated name. | K18: Not Run
A19: BPR-002 | B19: Business Profile | C19: Edit the name and confirm it persists | D19: High | G19: 5 | H19: Confirm the marketing preferences and company details were NOT wiped by saving the name alone. | I19: Company name, VAT number, billing address and the preference checkboxes are all unchanged. Saving one field must not blank the others. | K19: Not Run
A20: BPR-003 | B20: Business Profile | C20: Edit the phone number and confirm it is treated as unproved | D20: High | E20: Signed in as business.test01@example.com. | F20: New phone: +353871234571 | G20: 1 | H20: Change the Phone to +353871234571 and save. | I20: Saved. | K20: Not Run
A21: BPR-003 | B21: Business Profile | C21: Edit the phone number and confirm it is treated as unproved | D21: High | G21: 2 | H21: Refresh and confirm the new number is shown. | I21: Shows +353871234571. | K21: Not Run
A22: BPR-003 | B22: Business Profile | C22: Edit the phone number and confirm it is treated as unproved | D22: High | G22: 3 | H22: Check whether the account still claims the phone number is verified. | I22: The new number is NOT treated as verified - changing the number clears any previous phone verification. A number that has never been texted must not be shown as proved. | K22: Not Run
A23: BPR-003 | B23: Business Profile | C23: Edit the phone number and confirm it is treated as unproved | D23: High | G23: 4 | H23: If two-factor by SMS was enabled, check what happened to it. | I23: Record the behaviour. The second factor must not silently point at an unproved number. | K23: Not Run
A24: BPR-003 | B24: Business Profile | C24: Edit the phone number and confirm it is treated as unproved | D24: High | G24: 5 | H24: Change the phone back to +353871234567. | I24: Saved, and again treated as unverified until proved. | K24: Not Run
A25: BPR-004 | B25: Business Profile | C25: Edit the billing address and company details | D25: High | E25: Signed in as business.test01@example.com. | F25: New address: 26 Main Street, Dublin, Dublin, D02 X286, Ireland | New company: Murphy IT Solutions Limited | G25: 1 | H25: Change the Billing address to "26 Main Street, Dublin, Dublin, D02 X286, Ireland" and save. | I25: Saved with a confirmation. | K25: Not Run
A26: BPR-004 | B26: Business Profile | C26: Edit the billing address and company details | D26: High | G26: 2 | H26: Refresh, then sign out and back in. | I26: The new address persists. | K26: Not Run
A27: BPR-004 | B27: Business Profile | C27: Edit the billing address and company details | D27: High | G27: 3 | H27: Change the Company name to "Murphy IT Solutions Limited" and save. | I27: Saved. | K27: Not Run
A28: BPR-004 | B28: Business Profile | C28: Edit the billing address and company details | D28: High | G28: 4 | H28: Confirm in the admin customer record. | I28: Admin shows the updated company name and address. | K28: Not Run
A29: BPR-004 | B29: Business Profile | C29: Edit the billing address and company details | D29: High | G29: 5 | H29: Clear the Billing address entirely and save. | I29: Record the behaviour. If the field is required here it should be refused with a clear message; if it is allowed to be emptied, note that a VAT invoice would then have no address. | K29: Not Run
A30: BPR-005 | B30: Business Profile | C30: Edit the VAT number from the profile | D30: High | E30: Signed in as business.test01@example.com. A second verified account exists holding VAT IE2222222C. | F30: Valid: IE1234567B | Invalid: n/a | Taken: IE2222222C | G30: 1 | H30: Change the VAT number to "n/a" and save. | I30: Refused with: "That does not look like a VAT number. Enter it as it appears on your VAT certificate." | K30: Not Run
A31: BPR-005 | B31: Business Profile | C31: Edit the VAT number from the profile | D31: High | G31: 2 | H31: Change the VAT number to IE2222222C, which belongs to another verified account, and save. | I31: REFUSED - another company's VAT number cannot be edited in from the profile. Record the exact message. | K31: Not Run
A32: BPR-005 | B32: Business Profile | C32: Edit the VAT number from the profile | D32: High | G32: 3 | H32: Change the VAT number to IE1234567B and save. | I32: Accepted and saved. | K32: Not Run
A33: BPR-005 | B33: Business Profile | C33: Edit the VAT number from the profile | D33: High | G33: 4 | H33: Refresh and confirm. | I33: Shows IE1234567B. | K33: Not Run
A34: BPR-005 | B34: Business Profile | C34: Edit the VAT number from the profile | D34: High | G34: 5 | H34: Set the VAT number back to IE1234567A for the rest of the pack. | I34: Saved. | K34: Not Run
A35: BPR-006 | B35: Business Profile | C35: Change the PO requirement and confirm it gates checkout | D35: Critical | E35: Signed in as business.test01@example.com. | F35: PO toggle on the profile; PO-2026-00125 at checkout. | G35: 1 | H35: On the profile, UNTICK "requires PO number" and save. | I35: Saved. | K35: Not Run
A36: BPR-006 | B36: Business Profile | C36: Change the PO requirement and confirm it gates checkout | D36: Critical | G36: 2 | H36: Add 'testing product' (product ID 99240288, slug testing-product, retail EUR 505.00 ex VAT) to the basket and go to checkout. Leave the PO field empty. | I36: Checkout is allowed to proceed without a PO number. | K36: Not Run
A37: BPR-006 | B37: Business Profile | C37: Change the PO requirement and confirm it gates checkout | D37: Critical | G37: 3 | H37: Return to the profile, TICK "requires PO number" and save. | I37: Saved. | K37: Not Run
A38: BPR-006 | B38: Business Profile | C38: Change the PO requirement and confirm it gates checkout | D38: Critical | G38: 4 | H38: Go to checkout again and leave the PO number empty, then try to place the order. | I38: REFUSED with: "Enter the purchase order number for this order." | K38: Not Run
A39: BPR-006 | B39: Business Profile | C39: Change the PO requirement and confirm it gates checkout | D39: Critical | G39: 5 | H39: Enter PO-2026-00125 and place the order. | I39: Accepted. The preference set on the profile is what gates checkout. | K39: Not Run
A40: BPR-007 | B40: Business Profile | C40: The account type cannot be changed by the customer | D40: Critical | E40: Signed in as business.test01@example.com. | F40: Attempt to set account_type to trade. | G40: 1 | H40: Look on the profile page for any control to change the account type from Business to Trade or Personal. | I40: There is NO such control. An account-type change workflow is Not Available / Not Implemented - a different type means a new registration. Mark Not Applicable, not Fail. | K40: Not Run
A41: BPR-007 | B41: Business Profile | C41: The account type cannot be changed by the customer | D41: Critical | G41: 2 | H41: Open developer tools and submit a profile save with "account_type": "trade" added to the request payload. | I41: The account type is UNCHANGED - it is still business. The server ignores a customer-supplied account type. | K41: Not Run
A42: BPR-007 | B42: Business Profile | C42: The account type cannot be changed by the customer | D42: Critical | G42: 3 | H42: Reload the dashboard and the admin customer record. | I42: Both still show Business. | K42: Not Run
A43: BPR-007 | B43: Business Profile | C43: The account type cannot be changed by the customer | D43: Critical | G43: 4 | H43: Submit a profile save with "trade_status": "approved" added. | I43: Ignored - the account still has no approved trade status, and band entitlement is unchanged. | K43: Not Run
A44: BPR-008 | B44: Business Profile | C44: A customer cannot lift their own suspension through the profile | D44: Critical | E44: The Business account has been suspended by an admin. | F44: Attempt to set status to active. | G44: 1 | H44: In admin, suspend business.test01@example.com. | I44: Account status is suspended. | K44: Not Run
A45: BPR-008 | B45: Business Profile | C45: A customer cannot lift their own suspension through the profile | D45: Critical | G45: 2 | H45: Sign in as that customer and open the profile. | I45: Sign-in still works - a suspended customer can sign in and view history, but cannot place new orders. | K45: Not Run
A46: BPR-008 | B46: Business Profile | C46: A customer cannot lift their own suspension through the profile | D46: Critical | G46: 3 | H46: Submit a profile save with "status": "active" added to the payload. | I46: IGNORED - the account is still suspended in admin. | K46: Not Run
A47: BPR-008 | B47: Business Profile | C47: A customer cannot lift their own suspension through the profile | D47: Critical | G47: 4 | H47: Confirm the dashboard headline still says the account is suspended. | I47: The suspension message is still shown and no new order can be placed. | K47: Not Run
A48: BPR-008 | B48: Business Profile | C48: A customer cannot lift their own suspension through the profile | D48: Critical | G48: 5 | H48: Submit a profile save with "status_note" set to a value of your choosing. | I48: Ignored - the status note is staff-owned. | K48: Not Run
A49: BPR-008 | B49: Business Profile | C49: A customer cannot lift their own suspension through the profile | D49: Critical | G49: 6 | H49: In admin, return the account to active. | I49: Account is active again. | K49: Not Run
A50: BPR-009 | B50: Business Profile | C50: One customer cannot read or edit another customer's profile | D50: Critical | E50: Two accounts exist: business.test01@example.com and business.test02@example.com. | F50: Swap the customer id in the request. | G50: 1 | H50: Sign in as business.test01@example.com. In developer tools, note the profile request and the customer id it returns. | I50: You can see your own profile data. | K50: Not Run
A51: BPR-009 | B51: Business Profile | C51: One customer cannot read or edit another customer's profile | D51: Critical | G51: 2 | H51: Replay the profile READ request with the other customer's id substituted. | I51: You receive your OWN profile or an authorisation error - never the other customer's data. The signed-in identity, not the id in the request, decides whose profile is returned. | K51: Not Run
A52: BPR-009 | B52: Business Profile | C52: One customer cannot read or edit another customer's profile | D52: Critical | G52: 3 | H52: Replay the profile SAVE request with the other customer's id substituted and a changed company name. | I52: The other account is UNCHANGED. Verify in admin. | K52: Not Run
A53: BPR-009 | B53: Business Profile | C53: One customer cannot read or edit another customer's profile | D53: Critical | G53: 4 | H53: Sign in as the other customer and confirm their data. | I53: Company name and all details are as they were. | K53: Not Run
A54: BPR-010 | B54: Business Profile | C54: An older account that predates the company columns still works | D54: Medium | E54: Access to an account created before business/trade fields existed, or one with NULL status and verification columns. Ask the dev team to identify one; if none exists, mark Not Applicable. | F54: A legacy customer account. | G54: 1 | H54: Sign in as the legacy account. | I54: Sign-in succeeds with no error. | K54: Not Run
A55: BPR-010 | B55: Business Profile | C55: An older account that predates the company columns still works | D55: Medium | G55: 2 | H55: Open the dashboard. | I55: The account is treated as ACTIVE - a missing/NULL status is read as active, not as suspended. | K55: Not Run
A56: BPR-010 | B56: Business Profile | C56: An older account that predates the company columns still works | D56: Medium | G56: 3 | H56: Open the profile. | I56: The page renders. Company fields are empty rather than causing an error. | K56: Not Run
A57: BPR-010 | B57: Business Profile | C57: An older account that predates the company columns still works | D57: Medium | G57: 4 | H57: Add a product to the basket and view the price. | I57: Retail pricing applies. A legacy personal account gets no band pricing. | K57: Not Run

Sheet Trade Registration
A1: Trade Registration
A2: A Trade account opens ACTIVE but with trade status PENDING, and buys at RETAIL until staff approve it. VAT number, trade type, expected spend and the resale confirmation are all REQUIRED for Trade - unlike Business, where VAT is optional.
A3: Test Case ID | B3: Module | C3: Test Scenario | D3: Priority | E3: Preconditions | F3: Test Data | G3: Step No. | H3: Action / Steps | I3: Expected Result | J3: Actual Result | K3: Status | L3: Severity | M3: Bug ID | N3: Tester Comments
A4: TRG-001 | B4: Trade Registration | C4: Select Trade and confirm the Trade detail fields | D4: Critical | E4: No user signed in. | F4: URL: {storefront}/register | G4: 1 | H4: Open {storefront}/register and choose the Trade account type, then continue. | I4: The Details step opens with Trade-specific text explaining that the account works at retail prices immediately and trade pricing switches on after approval. | K4: Not Run
A5: TRG-001 | B5: Trade Registration | C5: Select Trade and confirm the Trade detail fields | D5: Critical | G5: 2 | H5: List every field on the Trade Details step. | I5: Name, Email, Phone, Password + confirm, Company name, Trade (dropdown), VAT number, Company registration number, Billing address, Expected monthly spend (dropdown), Website, resale confirmation checkbox, marketing preferences, Terms. | K5: Not Run
A6: TRG-001 | B6: Trade Registration | C6: Select Trade and confirm the Trade detail fields | D6: Critical | G6: 3 | H6: Open the Trade dropdown and read the options. | I6: Exactly seven: Computer / laptop repair shop | Phone and tablet repair | IT reseller or MSP | Games console repair | Electronics or appliance repair | Field engineer / sole trader | Other. NOTE "Electrical Contractor" is NOT an option - use "Field engineer / sole trader" or "Other". | K6: Not Run
A7: TRG-001 | B7: Trade Registration | C7: Select Trade and confirm the Trade detail fields | D7: Critical | G7: 4 | H7: Open the Expected monthly spend dropdown. | I7: Exactly four: Under EUR 500 | EUR 500 - 2,000 | EUR 2,000 - 5,000 | Over EUR 5,000. | K7: Not Run
A8: TRG-001 | B8: Trade Registration | C8: Select Trade and confirm the Trade detail fields | D8: Critical | G8: 5 | H8: Confirm there is NO "sector" field on the Trade form. | I8: Correct - sector belongs to Business; trade type is the Trade equivalent. | K8: Not Run
A9: TRG-001 | B9: Trade Registration | C9: Select Trade and confirm the Trade detail fields | D9: Critical | G9: 6 | H9: Confirm there is NO "requires PO" or "credit application" checkbox on the Trade form. | I9: Correct - those are collected for Business accounts at registration. Record whether the PO preference can be set later from the Trade profile. | K9: Not Run
A10: TRG-002 | B10: Trade Registration | C10: Complete a valid Trade registration end to end | D10: Critical | E10: TRG-001 done. Email and phone unused. | F10: Name: James O'Brien | Email: trade.test01@example.com | Phone: +353861234567 | Password: Trade@2026Test! | Company: O'Brien Electrical Services Ltd | Trade: Field engineer / sole trader | VAT: IE7654321B | Company reg no: 654321 | Billing address: 42 Industrial Estate, Cork, Cork, T12 AB12, Ireland | Expected spend: EUR 2,000 - 5,000 | Website: https://example.com | Resale: ticked | G10: 1 | H10: Enter Name: James O'Brien | I10: Accepted, apostrophe intact. | K10: Not Run
A11: TRG-002 | B11: Trade Registration | C11: Complete a valid Trade registration end to end | D11: Critical | G11: 2 | H11: Enter Email: trade.test01@example.com | I11: Accepted. | K11: Not Run
A12: TRG-002 | B12: Trade Registration | C12: Complete a valid Trade registration end to end | D12: Critical | G12: 3 | H12: Enter Phone: +353861234567 | I12: Accepted. | K12: Not Run
A13: TRG-002 | B13: Trade Registration | C13: Complete a valid Trade registration end to end | D13: Critical | G13: 4 | H13: Enter Password: Trade@2026Test! twice. | I13: Accepted and matching. | K13: Not Run
A14: TRG-002 | B14: Trade Registration | C14: Complete a valid Trade registration end to end | D14: Critical | G14: 5 | H14: Enter Company name: O'Brien Electrical Services Ltd | I14: Accepted. | K14: Not Run
A15: TRG-002 | B15: Trade Registration | C15: Complete a valid Trade registration end to end | D15: Critical | G15: 6 | H15: Choose Trade: Field engineer / sole trader | I15: Accepted. | K15: Not Run
A16: TRG-002 | B16: Trade Registration | C16: Complete a valid Trade registration end to end | D16: Critical | G16: 7 | H16: Enter VAT number: IE7654321B | I16: Accepted. VAT is REQUIRED for Trade. | K16: Not Run
A17: TRG-002 | B17: Trade Registration | C17: Complete a valid Trade registration end to end | D17: Critical | G17: 8 | H17: Enter Company registration number: 654321 | I17: Accepted (digits only). | K17: Not Run
A18: TRG-002 | B18: Trade Registration | C18: Complete a valid Trade registration end to end | D18: Critical | G18: 9 | H18: Enter Billing address: 42 Industrial Estate, Cork, Cork, T12 AB12, Ireland | I18: Accepted. | K18: Not Run
A19: TRG-002 | B19: Trade Registration | C19: Complete a valid Trade registration end to end | D19: Critical | G19: 10 | H19: Choose Expected monthly spend: EUR 2,000 - 5,000 | I19: Accepted. | K19: Not Run
A20: TRG-002 | B20: Trade Registration | C20: Complete a valid Trade registration end to end | D20: Critical | G20: 11 | H20: Enter Website: https://example.com | I20: Accepted. | K20: Not Run
A21: TRG-002 | B21: Trade Registration | C21: Complete a valid Trade registration end to end | D21: Critical | G21: 12 | H21: Tick the resale confirmation and the Terms box, then submit. | I21: Submits with no validation error and advances to the Verify step. | K21: Not Run
A22: TRG-002 | B22: Trade Registration | C22: Complete a valid Trade registration end to end | D22: Critical | G22: 13 | H22: Enter the verification code from the mail capture tool. | I22: Accepted; the wizard advances to the Security step. | K22: Not Run
... A24: TRG-002 | B24: Trade Registration | C24: Complete a valid Trade registration end to end | D24: Critical | G24: 15 | H24: Read the closing message carefully. | I24: It should say the account is ready at RETAIL prices and that an email will follow once the trade application is approved. Record the exact wording. | K24: Not Run
A25: TRG-003 | B25: Trade Registration | C25: Verify the Trade application was created and is Pending | D25: Critical | E25: TRG-002 complete. | F25: Email: trade.test01@example.com | G25: 1 | H25: Sign in as trade.test01@example.com and open the dashboard. | I25: The dashboard loads and identifies the account as a Trade account. | K25: Not Run
A26: TRG-003 | B26: Trade Registration | C26: Verify the Trade application was created and is Pending | D26: Critical | G26: 2 | H26: Read the account headline on the dashboard. | I26: It states the trade application is being reviewed / is pending. A trade customer waiting on approval can tell that something is happening. Record the exact wording. | K26: Not Run
A27: TRG-003 | B27: Trade Registration | C27: Verify the Trade application was created and is Pending | D27: Critical | G27: 3 | H27: Confirm the dashboard does NOT claim trade pricing is active. | I27: No claim of trade or band pricing while the application is pending. | K27: Not Run
A28: TRG-003 | B28: Trade Registration | C28: Verify the Trade application was created and is Pending | D28: Critical | G28: 4 | H28: In admin open {admin}/trade-applications. | I28: The application for trade.test01@example.com appears in the queue with status Pending. | K28: Not Run
A29: TRG-003 | B29: Trade Registration | C29: Verify the Trade application was created and is Pending | D29: Critical | G29: 5 | H29: Open the application in admin. | I29: It shows the company name, VAT number, company registration number, trade type, expected spend, website and billing address exactly as submitted. | K29: Not Run
A30: TRG-003 | B30: Trade Registration | C30: Verify the Trade application was created and is Pending | D30: Critical | G30: 6 | H30: Check the admin customer record for this account. | I30: Account type = trade; account status = active; trade status = pending; verification status = pending. | K30: Not Run
A31: TRG-004 | B31: Trade Registration | C31: A pending Trade account must NOT get trade pricing | D31: Critical | E31: TRG-003 complete - application still Pending. | F31: 'testing product' (product ID 99240288, slug testing-product, retail EUR 505.00 ex VAT) | G31: 1 | H31: Signed in as trade.test01@example.com, open the product page for 'testing product' (product ID 99240288, slug testing-product, retail EUR 505.00 ex VAT). | I31: The product page shows the RETAIL price of EUR 505.00 ex VAT. | K31: Not Run
A32: TRG-004 | B32: Trade Registration | C32: A pending Trade account must NOT get trade pricing | D32: Critical | G32: 2 | H32: Confirm no quantity band table or trade price is advertised on the page. | I32: NO bands are offered. Advertising a band price the till will not honour is a critical defect. | K32: Not Run
A33: TRG-004 | B33: Trade Registration | C33: A pending Trade account must NOT get trade pricing | D33: Critical | G33: 3 | H33: Add 10 units to the basket and open the basket. | I33: The basket unit price is EUR 505.00 ex VAT, not the band price of EUR 450.00. Line total EUR 5,050.00 ex VAT. | K33: Not Run
A34: TRG-004 | B34: Trade Registration | C34: A pending Trade account must NOT get trade pricing | D34: Critical | G34: 4 | H34: Proceed to checkout and read the unit price and totals. | I34: Checkout also shows EUR 505.00 per unit. The basket, the product page and checkout all agree. | K34: Not Run
A35: TRG-004 | B35: Trade Registration | C35: A pending Trade account must NOT get trade pricing | D35: Critical | G35: 5 | H35: Search for the product from the site search and read the price in the results. | I35: Retail EUR 505.00. No trade price leaks into search results. | K35: Not Run
A36: TRG-004 | B36: Trade Registration | C36: A pending Trade account must NOT get trade pricing | D36: Critical | G36: 6 | H36: Open the category / listing page containing the product. | I36: Retail EUR 505.00 in the listing too. | K36: Not Run
A37: TRG-004 | B37: Trade Registration | C37: A pending Trade account must NOT get trade pricing | D37: Critical | G37: 7 | H37: Empty the basket before continuing. | I37: Basket is empty, ready for the approval tests. | K37: Not Run
A38: TRG-005 | B38: Trade Registration | C38: Required-field validation on the Trade form | D38: High | E38: Trade Details step open with otherwise valid values, fresh email and phone. | F38: Remove one required field at a time. | G38: 1 | H38: Clear Company name and submit. | I38: Refused: "Enter the company name." | K38: Not Run
A39: TRG-005 | B39: Trade Registration | C39: Required-field validation on the Trade form | D39: High | G39: 2 | H39: Restore it, clear the Trade dropdown and submit. | I39: Refused: "Choose the trade that best describes your work." | K39: Not Run
A40: TRG-005 | B40: Trade Registration | C40: Required-field validation on the Trade form | D40: High | G40: 3 | H40: Restore it, clear the VAT number and submit. | I40: Refused: "Enter your VAT number." VAT is REQUIRED for Trade, unlike Business. | K40: Not Run
A41: TRG-005 | B41: Trade Registration | C41: Required-field validation on the Trade form | D41: High | G41: 4 | H41: Restore it, clear the Billing address and submit. | I41: Refused: "We need a billing address for VAT invoices." | K41: Not Run
A42: TRG-005 | B42: Trade Registration | C42: Required-field validation on the Trade form | D42: High | G42: 5 | H42: Restore it, clear Expected monthly spend and submit. | I42: Refused: "Choose your expected monthly spend." | K42: Not Run
A43: TRG-005 | B43: Trade Registration | C43: Required-field validation on the Trade form | D43: High | G43: 6 | H43: Restore it, UNTICK the resale confirmation and submit. | I43: Refused: "Trade accounts need this confirmation." | K43: Not Run
A44: TRG-005 | B44: Trade Registration | C44: Required-field validation on the Trade form | D44: High | G44: 7 | H44: Restore everything, untick Terms and submit. | I44: Refused: "Tick the box to continue." | K44: Not Run
A45: TRG-005 | B45: Trade Registration | C45: Required-field validation on the Trade form | D45: High | G45: 8 | H45: Confirm no account or application was created by any refused attempt. | I45: Nothing in the admin trade queue for this email. A refused submission must not create a pending application. | K45: Not Run
A46: TRG-006 | B46: Trade Registration | C46: Trade VAT and company number validation | D46: High | E46: Trade Details step open, fresh email and phone. | F46: Invalid VAT: n/a | 12 Invalid CRO: IE654321 Taken VAT: IE7654321B | G46: 1 | H46: Enter VAT "n/a" and submit. | I46: Refused: "That does not look like a VAT number. Enter it as it appears on your VAT certificate." | K46: Not Run
A47: TRG-006 | B47: Trade Registration | C47: Trade VAT and company number validation | D47: High | G47: 2 | H47: Enter VAT "12" and submit. | I47: Refused with the same message. | K47: Not Run
A48: TRG-006 | B48: Trade Registration | C48: Trade VAT and company number validation | D48: High | G48: 3 | H48: Enter company registration number "IE654321" and submit. | I48: REFUSED: "A company registration number is digits only." | K48: Not Run
A49: TRG-006 | B49: Trade Registration | C49: Trade VAT and company number validation | D49: High | G49: 4 | H49: Enter company registration number "654321" and submit. | I49: Accepted. | K49: Not Run
A50: TRG-006 | B50: Trade Registration | C50: Trade VAT and company number validation | D50: High | G50: 5 | H50: Enter VAT IE7654321B, already held by the verified account from TRG-002, and submit. | I50: Refused: "That VAT number is already registered to another account. Sign in instead, or contact us." | K50: Not Run
A51: TRG-006 | B51: Trade Registration | C51: Trade VAT and company number validation | D51: High | G51: 6 | H51: Enter a well-formed fictitious VAT such as IE8888888X and submit. | I51: ACCEPTED - format check only. VIES validation is Not Available / Not Implemented. | K51: Not Run
A52: TRG-007 | B52: Trade Registration | C52: Duplicate email on Trade registration | D52: High | E52: The verified Trade account from TRG-002 exists. | F52: Email: trade.test01@example.com | G52: 1 | H52: Start a Trade registration using trade.test01@example.com and submit the Details step. | I52: Refused: "That email address already has an account. Sign in instead, or reset your password." | K52: Not Run
A53: TRG-007 | B53: Trade Registration | C53: Duplicate email on Trade registration | D53: High | G53: 2 | H53: Confirm the existing account and its application were not altered. | I53: In admin, the original application is still Pending with its original details and there is exactly one account for this email. | K53: Not Run
A54: TRG-007 | B54: Trade Registration | C54: Duplicate email on Trade registration | D54: High | G54: 3 | H54: Use trade.test02@example.com with phone +353861234599 instead. | I54: Accepted - the registration proceeds. | K54: Not Run
A55: TRG-008 | B55: Trade Registration | C55: An incomplete Trade application cannot be approved into existence | D55: High | E55: A Trade registration abandoned at the Verify step (code never entered). | F55: Email: trade.incomplete01@example.com | Phone: +353861234571 | G55: 1 | H55: Register a Trade account with trade.incomplete01@example.com and stop at the Verify step. | I55: An unverified customer row exists. | K55: Not Run
A56: TRG-008 | B56: Trade Registration | C56: An incomplete Trade application cannot be approved into existence | D56: High | G56: 2 | H56: Open {admin}/trade-applications and look for this applicant. | I56: Record whether an unverified applicant appears in the review queue. Note the finding either way - approving an applicant who never confirmed their email address would be worth raising. | K56: Not Run
A57: TRG-008 | B57: Trade Registration | C57: An incomplete Trade application cannot be approved into existence | D57: High | G57: 3 | H57: If the applicant is listed, attempt to approve them. | I57: Record the outcome in Actual Result and discuss with the dev team whether it is intended. | K57: Not Run
A58: TRG-008 | B58: Trade Registration | C58: An incomplete Trade application cannot be approved into existence | D58: High | G58: 4 | H58: Confirm the account still cannot sign in without verification. | I58: Sign-in is refused or forces verification until the emailed code is entered. | K58: Not Run
A59: TRG-009 | B59: Trade Registration | C59: Browser refresh and navigation during Trade registration | D59: Medium | E59: A Trade registration in progress. | F59: Values from TRG-002 with a fresh email. | G59: 1 | H59: Fill the Trade Details step and refresh with F5 before submitting. | I59: The page reloads without a script error. Record whether values survive. | K59: Not Run
A60: TRG-009 | B60: Trade Registration | C60: Browser refresh and navigation during Trade registration | D60: Medium | G60: 2 | H60: Confirm no trade application was created by the refresh. | I60: Nothing in the admin queue for that email. | K60: Not Run
A61: TRG-009 | B61: Trade Registration | C61: Browser refresh and navigation during Trade registration | D61: Medium | G61: 3 | H61: Submit to reach the Verify step, then press the browser Back button. | I61: The application returns to an earlier step without crashing. | K61: Not Run
A62: TRG-009 | B62: Trade Registration | C62: Browser refresh and navigation during Trade registration | D62: Medium | G62: 4 | H62: Navigate forward again and complete verification. | I62: Exactly ONE account and ONE trade application exist for that email - not two. | K62: Not Run
A63: TRG-009 | B63: Trade Registration | C63: Browser refresh and navigation during Trade registration | D63: Medium | G63: 5 | H63: Change the account type from Trade to Business mid-way and complete a Business registration instead. | I63: The stored account is BUSINESS, with no trade application and no trade-only fields. Switching type must not leave trade data behind. | K63: Not Run
A64: TRG-010 | B64: Trade Registration | C64: Session behaviour during a long registration | D64: Low | E64: A Trade registration in progress. | F64: Leave the form idle. | G64: 1 | H64: Fill the Trade Details step, then leave the browser idle for 30 minutes without submitting. | I64: Record what happens on submit: either it succeeds, or a clear message asks you to start again. A silent failure or a raw error page is a defect. | K64: Not Run
A65: TRG-010 | B65: Trade Registration | C65: Session behaviour during a long registration | D65: Low | G65: 2 | H65: Complete a registration to the Verify step, then wait more than the code lifetime before entering the code. | I65: The code is REFUSED as expired and a new one can be requested. Verification codes expire by design. | K65: Not Run
A66: TRG-010 | B66: Trade Registration | C66: Session behaviour during a long registration | D66: Low | G66: 3 | H66: Request a fresh code and enter it. | I66: Accepted, and the account is verified. | K66: Not Run
A67: TRG-010 | B67: Trade Registration | C67: Session behaviour during a long registration | D67: Low | G67: 4 | H67: Enter a wrong code several times in a row. | I67: After the attempt limit the code is burned and must be re-requested. Brute-forcing the code must not be possible. | K67: Not Run

Sheet Trade Approval
A1: Trade Approval
A2: Approval is the moment trade pricing switches on. It also marks the company details verified, so the two cannot drift apart. Approval is done from {admin}/trade-applications. There is no live push to the customer - the customer sees the change on their next page load.
A3: Test Case ID | B3: Module | C3: Test Scenario | D3: Priority | E3: Preconditions | F3: Test Data | G3: Step No. | H3: Action / Steps | I3: Expected Result | J3: Actual Result | K3: Status | L3: Severity | M3: Bug ID | N3: Tester Comments
A4: TAP-001 | B4: Trade Approval | C4: Admin can open the trade review queue | D4: Critical | E4: An admin account with the trade permission. A pending application exists for trade.test01@example.com. | F4: URL: {admin}/trade-applications | G4: 1 | H4: Sign in to the admin panel. | I4: Admin dashboard loads. | K4: Not Run
A5: TAP-001 | B5: Trade Approval | C5: Admin can open the trade review queue | D5: Critical | G5: 2 | H5: Open {admin}/trade-applications. | I5: The review queue loads and lists trade applicants. | K5: Not Run
A6: TAP-001 | B6: Trade Approval | C6: Admin can open the trade review queue | D6: Critical | G6: 3 | H6: Find the application for trade.test01@example.com. | I6: It is listed, showing the company name and a status of Pending. | K6: Not Run
A7: TAP-001 | B7: Trade Approval | C7: Admin can open the trade review queue | D7: Critical | G7: 4 | H7: Use the status filter to show only Pending applications. | I7: Only pending applications are listed and this one is among them. | K7: Not Run
A8: TAP-001 | B8: Trade Approval | C8: Admin can open the trade review queue | D8: Critical | G8: 5 | H8: Filter by each of the other statuses in turn (Approved, Rejected, Suspended). | I8: Each filter returns only applications in that state. Record any filter that returns the wrong set. | K8: Not Run
A9: TAP-001 | B9: Trade Approval | C9: Admin can open the trade review queue | D9: Critical | G9: 6 | H9: Search the queue by the customer email address. | I9: The search finds the application. | K9: Not Run
A10: TAP-002 | B10: Trade Approval | C10: Review the submitted application before deciding | D10: High | E10: TAP-001 done. | F10: Application for trade.test01@example.com | G10: 1 | H10: Open the application for trade.test01@example.com. | I10: The detail view opens. | K10: Not Run
A11: TAP-002 | B11: Trade Approval | C11: Review the submitted application before deciding | D11: High | G11: 2 | H11: Check the company name. | I11: Shows: O'Brien Electrical Services Ltd | K11: Not Run
A12: TAP-002 | B12: Trade Approval | C12: Review the submitted application before deciding | D12: High | G12: 3 | H12: Check the VAT number. | I12: Shows: IE7654321B | K12: Not Run
A13: TAP-002 | B13: Trade Approval | C13: Review the submitted application before deciding | D13: High | G13: 4 | H13: Check the company registration number. | I13: Shows: 654321 | K13: Not Run
A14: TAP-002 | B14: Trade Approval | C14: Review the submitted application before deciding | D14: High | G14: 5 | H14: Check the trade type and expected monthly spend. | I14: Shows: Field engineer / sole trader, and EUR 2,000 - 5,000. | K14: Not Run
A15: TAP-002 | B15: Trade Approval | C15: Review the submitted application before deciding | D15: High | G15: 6 | H15: Check the billing address and website. | I15: Shows the Cork address as entered, and https://example.com | K15: Not Run
A16: TAP-002 | B16: Trade Approval | C16: Review the submitted application before deciding | D16: High | G16: 7 | H16: Confirm the screen shows the current account state as well as the application. | I16: Account type, account status, trade status and verification status are all visible, so a decision can be made from this one screen. | K16: Not Run
A17: TAP-002 | B17: Trade Approval | C17: Review the submitted application before deciding | D17: High | G17: 8 | H17: Confirm that merely opening and reading the application changes nothing. | I17: The status is still Pending and NO email has been sent. Reading the queue must never notify the customer. | K17: Not Run
A18: TAP-003 | B18: Trade Approval | C18: Approve the application and confirm the state change | D18: Critical | E18: TAP-002 done. Mail capture open so the email can be inspected. | F18: Decision: Approved | Reviewer note: Verified against CRO listing. | G18: 1 | H18: Enter the reviewer note "Verified against CRO listing." and approve the application. | I18: The action succeeds and reports success. | K18: Not Run
A19: TAP-003 | B19: Trade Approval | C19: Approve the application and confirm the state change | D19: Critical | G19: 2 | H19: Read the response / confirmation shown to the admin. | I19: It reports that the transition happened and whether the customer was told. Record the wording. | K19: Not Run
A20: TAP-003 | B20: Trade Approval | C20: Approve the application and confirm the state change | D20: Critical | G20: 3 | H20: Refresh the admin page. | I20: The application now shows status Approved. The status survives a refresh - it was really persisted. | K20: Not Run
A21: TAP-003 | B21: Trade Approval | C21: Approve the application and confirm the state change | D21: Critical | G21: 4 | H21: Check the trade status on the admin customer record. | I21: Trade status = approved. | K21: Not Run
A22: TAP-003 | B22: Trade Approval | C22: Approve the application and confirm the state change | D22: Critical | G22: 5 | H22: Check the VERIFICATION status on the same record. | I22: Verification status = VERIFIED. Approving a trade application is also what marks the company details checked - the two cannot drift apart. | K22: Not Run
A23: TAP-003 | B23: Trade Approval | C23: Approve the application and confirm the state change | D23: Critical | G23: 6 | H23: Check the account status. | I23: Still active - account status and trade status are separate ladders and approval does not touch the account status. | K23: Not Run
A24: TAP-003 | B24: Trade Approval | C24: Approve the application and confirm the state change | D24: Critical | G24: 7 | H24: Confirm the pricing entitlement now shows as granted. | I24: The record shows the account IS entitled to business/band pricing. | K24: Not Run
A25: TAP-004 | B25: Trade Approval | C25: The customer sees the approval and gets trade pricing | D25: Critical | E25: TAP-003 done. | F25: 'testing product' (product ID 99240288, slug testing-product, retail EUR 505.00 ex VAT) | G25: 1 | H25: Sign in to the storefront as trade.test01@example.com. | I25: Sign-in succeeds. | K25: Not Run
A26: TAP-004 | B26: Trade Approval | C26: The customer sees the approval and gets trade pricing | D26: Critical | G26: 2 | H26: Open the dashboard and read the account headline. | I26: It now states the trade account is approved. It no longer says the application is under review. | K26: Not Run
A27: TAP-004 | B27: Trade Approval | C27: The customer sees the approval and gets trade pricing | D27: Critical | G27: 3 | H27: Open the product page for 'testing product' (product ID 99240288, slug testing-product, retail EUR 505.00 ex VAT). | I27: Quantity bands are now advertised. The band table shows 5-10 at EUR 450.00, 11-20 at EUR 430.00 and 21-30 at EUR 420.00 ex VAT. | K27: Not Run
A28: TAP-004 | B28: Trade Approval | C28: The customer sees the approval and gets trade pricing | D28: Critical | G28: 4 | H28: Set the quantity to 1 and read the price. | I28: EUR 505.00 ex VAT - there is NO band below quantity 5, so retail applies. This is correct, not a defect. | K28: Not Run
A29: TAP-004 | B29: Trade Approval | C29: The customer sees the approval and gets trade pricing | D29: Critical | G29: 5 | H29: Set the quantity to 10 and read the price. | I29: EUR 450.00 ex VAT per unit. | K29: Not Run
A30: TAP-004 | B30: Trade Approval | C30: The customer sees the approval and gets trade pricing | D30: Critical | G30: 6 | H30: Add 10 units to the basket and open the basket. | I30: Unit price EUR 450.00 ex VAT; line total EUR 4,500.00 ex VAT. | K30: Not Run
A31: TAP-004 | B31: Trade Approval | C31: The customer sees the approval and gets trade pricing | D31: Critical | G31: 7 | H31: Proceed to checkout and read the unit price and totals. | I31: Checkout shows EUR 450.00 per unit and EUR 4,500.00 ex VAT. Product page, basket and checkout all agree. | K31: Not Run
A32: TAP-004 | B32: Trade Approval | C32: The customer sees the approval and gets trade pricing | D32: Critical | G32: 8 | H32: Check VAT at checkout. | I32: VAT is 23% of the BAND price: EUR 1,035.00 on a EUR 4,500.00 line, giving EUR 5,535.00 inc VAT. VAT must be charged on the band price, not on retail. | K32: Not Run
A33: TAP-004 | B33: Trade Approval | C33: The customer sees the approval and gets trade pricing | D33: Critical | G33: 9 | H33: Search for the product and open the category listing. | I33: Both show the entitled price, with the retail price struck through where a band undercuts it. | K33: Not Run
A34: TAP-005 | B34: Trade Approval | C34: Approval persists across sign-out and sign-in | D34: High | E34: TAP-004 done. | F34: Account: trade.test01@example.com | G34: 1 | H34: Sign out of the storefront. | I34: Signed out. | K34: Not Run
A35: TAP-005 | B35: Trade Approval | C35: Approval persists across sign-out and sign-in | D35: High | G35: 2 | H35: Sign back in as trade.test01@example.com. | I35: Sign-in succeeds. | K35: Not Run
A36: TAP-005 | B36: Trade Approval | C36: Approval persists across sign-out and sign-in | D36: High | G36: 3 | H36: Open the dashboard. | I36: Still shows the trade account as approved. | K36: Not Run
A37: TAP-005 | B37: Trade Approval | C37: Approval persists across sign-out and sign-in | D37: High | G37: 4 | H37: Open the product page at quantity 10. | I37: Still EUR 450.00 ex VAT. Entitlement is not lost at sign-out. | K37: Not Run
A38: TAP-005 | B38: Trade Approval | C38: Approval persists across sign-out and sign-in | D38: High | G38: 5 | H38: Open the same account in a different browser or a private window and sign in. | I38: Same approved state and same band pricing - the entitlement lives on the account, not in one browser session. | K38: Not Run
A39: TAP-006 | B39: Trade Approval | C39: Approving the same application twice | D39: High | E39: The application for trade.test01@example.com is already Approved. Mail capture cleared. | F39: Decision: Approved (again) | G39: 1 | H39: Clear the mail capture inbox. | I39: Inbox empty. | K39: Not Run
A40: TAP-006 | B40: Trade Approval | C40: Approving the same application twice | D40: High | G40: 2 | H40: In admin, approve the already-approved application a second time. | I40: The action is accepted without error, OR is reported as no transition. Record which. The status remains Approved either way. | K40: Not Run
A41: TAP-006 | B41: Trade Approval | C41: Approving the same application twice | D41: High | G41: 3 | H41: Check the mail capture inbox. | I41: NO second approval email was sent. An action that changes nothing must not re-notify the customer. | K41: Not Run
A42: TAP-006 | B42: Trade Approval | C42: Approving the same application twice | D42: High | G42: 4 | H42: Edit the reviewer note on the approved application and save. | I42: The note is updated and again NO email is sent. Editing the note after the decision must not re-notify. | K42: Not Run
A43: TAP-006 | B43: Trade Approval | C43: Approving the same application twice | D43: High | G43: 5 | H43: Confirm the customer still has trade pricing. | I43: Unchanged - EUR 450.00 at quantity 10. | K43: Not Run
A44: TAP-007 | B44: Trade Approval | C44: Invalid and unauthorised approval attempts | D44: Critical | E44: A pending application exists. A customer account is available to attempt the action with. | F44: POST {storefront}/api/admin/trade-application/action/{customerId} | G44: 1 | H44: In admin, attempt to set the trade status to an unknown value such as "platinum". | I44: REFUSED. The status is unchanged and no email is sent. | K44: Not Run
A45: TAP-007 | B45: Trade Approval | C45: Invalid and unauthorised approval attempts | D45: Critical | G45: 2 | H45: Attempt to SUSPEND an application that is still Pending. | I45: REFUSED - pending is not a state that can be suspended. Only an approved application can be suspended. | K45: Not Run
A46: TAP-007 | B46: Trade Approval | C46: Invalid and unauthorised approval attempts | D46: Critical | G46: 3 | H46: Attempt a decision against a customer id that does not exist (for example 99999999). | I46: Refused cleanly with an error. No email is sent and no record is created. | K46: Not Run
A47: TAP-007 | B47: Trade Approval | C47: Invalid and unauthorised approval attempts | D47: Critical | G47: 4 | H47: Sign out of admin entirely. Send the approval request with no authorisation. | I47: REFUSED as unauthenticated. NOTE: this API answers HTTP 201 with the refusal carried in the response BODY - check the body says "Unauthenticated.", do not judge by the HTTP status code alone. | K47: Not Run
A48: TAP-007 | B48: Trade Approval | C48: Invalid and unauthorised approval attempts | D48: Critical | G48: 5 | H48: Sign in as the TRADE CUSTOMER and send the approval request for their own account. | I48: REFUSED. The customer cannot approve themselves. Verify in admin that the trade status is unchanged. | K48: Not Run
A49: TAP-007 | B49: Trade Approval | C49: Invalid and unauthorised approval attempts | D49: Critical | G49: 6 | H49: Sign in as a different CUSTOMER and send the approval request for the trade applicant. | I49: Refused. Verify the trade status is unchanged. | K49: Not Run
A50: TAP-007 | B50: Trade Approval | C50: Invalid and unauthorised approval attempts | D50: Critical | G50: 7 | H50: Confirm no email was sent by any refused attempt. | I50: Mail capture is empty. A refused transition must notify nobody. | K50: Not Run
A51: TAP-008 | B51: Trade Approval | C51: Approval when the application is missing information | D51: Medium | E51: A trade applicant registered with only the minimum required fields (no company registration number, no website). | F51: Email: trade.minimal01@example.com | Phone: +353861234572 | G51: 1 | H51: Register a Trade account with only the required fields - leave company registration number and website empty. | I51: Registration succeeds; those fields are optional. | K51: Not Run
A52: TAP-008 | B52: Trade Approval | C52: Approval when the application is missing information | D52: Medium | G52: 2 | H52: Open the application in the admin queue. | I52: The empty fields are shown as blank rather than causing an error or showing "null". | K52: Not Run
A53: TAP-008 | B53: Trade Approval | C53: Approval when the application is missing information | D53: Medium | G53: 3 | H53: Approve the application. | I53: Approval succeeds - the optional fields do not block a decision. | K53: Not Run
A54: TAP-008 | B54: Trade Approval | C54: Approval when the application is missing information | D54: Medium | G54: 4 | H54: Confirm the customer now gets band pricing. | I54: EUR 450.00 at quantity 10. | K54: Not Run
A55: TAP-008 | B55: Trade Approval | C55: Approval when the application is missing information | D55: Medium | G55: 5 | H55: Check the approval email for the missing values. | I55: The email reads sensibly and does not print "null" or an empty placeholder where the optional data would be. | K55: Not Run
A56: TAP-009 | B56: Trade Approval | C56: An application with no recorded trade status can still be decided | D56: Medium | E56: A trade account whose trade status is empty/NULL - ask the dev team to provide one, or mark Not Applicable. | F56: A legacy trade account. | G56: 1 | H56: Open the admin customer record for the account with no trade status. | I56: The record opens. An absent trade status is treated as pending. | K56: Not Run
A57: TAP-009 | B57: Trade Approval | C57: An application with no recorded trade status can still be decided | D57: Medium | G57: 2 | H57: Approve the application. | I57: Approval succeeds and the trade status becomes approved. | K57: Not Run
A58: TAP-009 | B58: Trade Approval | C58: An application with no recorded trade status can still be decided | D58: Medium | G58: 3 | H58: Confirm the customer gets band pricing. | I58: EUR 450.00 at quantity 10. | K58: Not Run
A59: TAP-009 | B59: Trade Approval | C59: An application with no recorded trade status can still be decided | D59: Medium | G59: 4 | H59: Confirm the approval email was sent. | I59: One approval email in the mail capture inbox. | K59: Not Run
A60: TAP-010 | B60: Trade Approval | C60: Two admins deciding the same application at once | D60: Medium | E60: A pending application. Two admin sessions in different browsers. | F60: Both approve simultaneously. | G60: 1 | H60: Open the same pending application in two separate admin sessions. | I60: Both show it as Pending. | K60: Not Run
A61: TAP-010 | B61: Trade Approval | C61: Two admins deciding the same application at once | D61: Medium | G61: 2 | H61: Approve from the first session. | I61: Succeeds and reports the transition. One approval email is sent. | K61: Not Run
A62: TAP-010 | B62: Trade Approval | C62: Two admins deciding the same application at once | D62: Medium | G62: 3 | H62: Without refreshing, approve from the second session. | I62: The second request reports NO transition (the status was already approved). The application remains Approved. | K62: Not Run
A63: TAP-010 | B63: Trade Approval | C63: Two admins deciding the same application at once | D63: Medium | G63: 4 | H63: Check the mail capture inbox. | I63: Exactly ONE approval email in total. The losing request must not send a second one. | K63: Not Run
A64: TAP-010 | B64: Trade Approval | C64: Two admins deciding the same application at once | D64: Medium | G64: 5 | H64: Refresh both admin sessions. | I64: Both now show Approved. | K64: Not Run

Sheet Trade Rejection
A1: Trade Rejection
A2: Rejecting an application leaves the ACCOUNT open and usable at retail prices - rejection is terminal for the application, not for the customer. The reviewer note is internal; check carefully that it does not reach the customer.
A3: Test Case ID | B3: Module | C3: Test Scenario | D3: Priority | E3: Preconditions | F3: Test Data | G3: Step No. | H3: Action / Steps | I3: Expected Result | J3: Actual Result | K3: Status | L3: Severity | M3: Bug ID | N3: Tester Comments
A4: TRJ-001 | B4: Trade Rejection | C4: Create a Trade application to reject | D4: High | E4: No account exists for trade.reject01@example.com. | F4: Email: trade.reject01@example.com | Phone: +353861234568 | Company: Reject Test Trading Ltd | Trade: Other | VAT: IE5555555R | Expected spend: Under EUR 500 | Password: Test@2026Secure! | G4: 1 | H4: Register a Trade account with the data above and complete email verification. | I4: Account created. | K4: Not Run
A5: TRJ-001 | B5: Trade Rejection | C5: Create a Trade application to reject | D5: High | G5: 2 | H5: Sign in and confirm the dashboard says the application is pending. | I5: Pending status shown. | K5: Not Run
A6: TRJ-001 | B6: Trade Rejection | C6: Create a Trade application to reject | D6: High | G6: 3 | H6: Confirm the account gets NO band pricing while pending. | I6: Product page shows retail EUR 505.00 at every quantity, including quantity 10. | K6: Not Run
A7: TRJ-001 | B7: Trade Rejection | C7: Create a Trade application to reject | D7: High | G7: 4 | H7: Confirm the application appears in the admin queue as Pending. | I7: Listed as Pending. | K7: Not Run
A8: TRJ-002 | B8: Trade Rejection | C8: Reject the application and verify the state | D8: Critical | E8: TRJ-001 done. Mail capture cleared. | F8: Decision: Rejected | Reviewer note: Could not verify the company at the address given. | G8: 1 | H8: Clear the mail capture inbox. | I8: Empty. | K8: Not Run
A9: TRJ-002 | B9: Trade Rejection | C9: Reject the application and verify the state | D9: Critical | G9: 2 | H9: In admin, open the application and reject it with the note "Could not verify the company at the address given." | I9: The action succeeds and reports the transition. | K9: Not Run
A10: TRJ-002 | B10: Trade Rejection | C10: Reject the application and verify the state | D10: Critical | G10: 3 | H10: Refresh the admin page. | I10: Status is Rejected and survives the refresh. | K10: Not Run
A11: TRJ-002 | B11: Trade Rejection | C11: Reject the application and verify the state | D11: Critical | G11: 4 | H11: Check the trade status on the admin customer record. | I11: Trade status = rejected. | K11: Not Run
A12: TRJ-002 | B12: Trade Rejection | C12: Reject the application and verify the state | D12: Critical | G12: 5 | H12: Check the ACCOUNT status on the same record. | I12: Account status is still ACTIVE. Rejecting the trade application must not suspend or close the customer account. | K12: Not Run
A13: TRJ-002 | B13: Trade Rejection | C13: Reject the application and verify the state | D13: Critical | G13: 6 | H13: Check the verification status. | I13: Record the value. Rejection does not mark the company details verified. | K13: Not Run
A14: TRJ-002 | B14: Trade Rejection | C14: Reject the application and verify the state | D14: Critical | G14: 7 | H14: Confirm the pricing entitlement is NOT granted. | I14: The record shows no business/band pricing entitlement. | K14: Not Run
A15: TRJ-003 | B15: Trade Rejection | C15: The rejected customer can still shop at retail | D15: Critical | E15: TRJ-002 done. | F15: 'testing product' (product ID 99240288, slug testing-product, retail EUR 505.00 ex VAT) | G15: 1 | H15: Sign in to the storefront as trade.reject01@example.com. | I15: Sign-in SUCCEEDS - the account is still open. | K15: Not Run
A16: TRJ-003 | B16: Trade Rejection | C16: The rejected customer can still shop at retail | D16: Critical | G16: 2 | H16: Open the dashboard and read the headline. | I16: It states the trade application was not approved. Record the exact wording - it should be clear and should offer a way to get in touch. | K16: Not Run
A17: TRJ-003 | B17: Trade Rejection | C17: The rejected customer can still shop at retail | D17: Critical | G17: 3 | H17: Confirm the dashboard does NOT show the internal reviewer note. | I17: The internal note "Could not verify the company at the address given." must NOT appear verbatim on the customer dashboard unless it was explicitly written as a customer-facing reason. Record what is shown. | K17: Not Run
A18: TRJ-003 | B18: Trade Rejection | C18: The rejected customer can still shop at retail | D18: Critical | G18: 4 | H18: Open the product page at quantity 1, 5, 10 and 25. | I18: EVERY quantity shows retail EUR 505.00 ex VAT. No bands are advertised. | K18: Not Run
A19: TRJ-003 | B19: Trade Rejection | C19: The rejected customer can still shop at retail | D19: Critical | G19: 5 | H19: Add 10 units to the basket. | I19: Basket shows EUR 505.00 per unit, EUR 5,050.00 ex VAT. | K19: Not Run
A20: TRJ-003 | B20: Trade Rejection | C20: The rejected customer can still shop at retail | D20: Critical | G20: 6 | H20: Proceed to checkout. | I20: Checkout shows EUR 505.00 per unit. Retail pricing is consistent across product page, basket and checkout. | K20: Not Run
A21: TRJ-003 | B21: Trade Rejection | C21: The rejected customer can still shop at retail | D21: Critical | G21: 7 | H21: Place a retail order to confirm the account still transacts. | I21: The order is accepted. A rejected trade application does not stop the customer buying at retail. | K21: Not Run
A22: TRJ-004 | B22: Trade Rejection | C22: Rejecting the same application twice | D22: High | E22: The application is already Rejected. Mail capture cleared. | F22: Decision: Rejected (again) | G22: 1 | H22: Clear the mail capture inbox. | I22: Empty. | K22: Not Run
A23: TRJ-004 | B23: Trade Rejection | C23: Rejecting the same application twice | D23: High | G23: 2 | H23: Reject the already-rejected application again. | I23: Accepted without error, or reported as no transition. Status remains Rejected. | K23: Not Run
A24: TRJ-004 | B24: Trade Rejection | C24: Rejecting the same application twice | D24: High | G24: 3 | H24: Check the mail capture inbox. | I24: NO second rejection email. A repeated identical action must not re-notify. | K24: Not Run
A25: TRJ-004 | B25: Trade Rejection | C25: Rejecting the same application twice | D25: High | G25: 4 | H25: Edit the reviewer note and save. | I25: Note updated, and still NO email sent. | K25: Not Run
A26: TRJ-005 | B26: Trade Rejection | C26: Unauthorised rejection attempts | D26: Critical | E26: A pending application exists. | F26: POST {storefront}/api/admin/trade-application/action/{customerId} | G26: 1 | H26: Sign out of admin and send a rejection request with no authorisation. | I26: REFUSED - the response body reports "Unauthenticated." (the HTTP code is 201; judge by the body). | K26: Not Run
A27: TRJ-005 | B27: Trade Rejection | C27: Unauthorised rejection attempts | D27: Critical | G27: 2 | H27: Sign in as a customer and send a rejection request for another customer. | I27: Refused. The trade status is unchanged. | K27: Not Run
A28: TRJ-005 | B28: Trade Rejection | C28: Unauthorised rejection attempts | D28: Critical | G28: 3 | H28: Sign in as the applicant themselves and send a rejection for their own account. | I28: Refused. Status unchanged. | K28: Not Run
A29: TRJ-005 | B29: Trade Rejection | C29: Unauthorised rejection attempts | D29: Critical | G29: 4 | H29: Confirm no email was sent by any of these attempts. | I29: Mail capture empty. | K29: Not Run
A30: TRJ-006 | B30: Trade Rejection | C30: Rejection with no reason, and with an over-long reason | D30: Medium | E30: Two pending applications available (register more accounts if needed). | F30: Note: empty | Note: a single space | Note: 2000 characters of text | G30: 1 | H30: Reject an application with the note field left completely EMPTY. | I30: The rejection succeeds. An email is still sent and reads sensibly with no dangling "Reason:" label and no "null". | K30: Not Run
A31: TRJ-006 | B31: Trade Rejection | C31: Rejection with no reason, and with an over-long reason | D31: Medium | G31: 2 | H31: Reject another application with a note consisting only of a single SPACE. | I31: Treated as NO note at all - the email must not contain a blank reason block. | K31: Not Run
A32: TRJ-006 | B32: Trade Rejection | C32: Rejection with no reason, and with an over-long reason | D32: Medium | G32: 3 | H32: Reject another with a 2000-character note. | I32: Accepted. The note is SHORTENED rather than sent whole. Check the email is not broken by the length. | K32: Not Run
A33: TRJ-006 | B33: Trade Rejection | C33: Rejection with no reason, and with an over-long reason | D33: Medium | G33: 4 | H33: Read the shortened note in the email. | I33: It is truncated cleanly and remains readable. | K33: Not Run
A34: TRJ-007 | B34: Trade Rejection | C34: Internal detail must not reach the customer | D34: Critical | E34: A pending application. Mail capture open. | F34: Note: INTERNAL - credit check failed, see ticket #4471, do not tell customer | G34: 1 | H34: Reject an application with the note "INTERNAL - credit check failed, see ticket #4471, do not tell customer". | I34: The rejection succeeds. | K34: Not Run
A35: TRJ-007 | B35: Trade Rejection | C35: Internal detail must not reach the customer | D35: Critical | G35: 2 | H35: Open the rejection email and read it in full, including the plain-text part. | I35: Record exactly whether the note text appears. Anything that exposes an internal ticket reference or an internal instruction to the customer is a CRITICAL defect - raise it. | K35: Not Run
A36: TRJ-007 | B36: Trade Rejection | C36: Internal detail must not reach the customer | D36: Critical | G36: 3 | H36: Check the customer dashboard for the same text. | I36: Record whether it is shown. | K36: Not Run
A37: TRJ-007 | B37: Trade Rejection | C37: Internal detail must not reach the customer | D37: Critical | G37: 4 | H37: Check the email for any other internal detail. | I37: The email must not contain database ids, stack traces, internal URLs, admin names or system paths. | K37: Not Run
A38: TRJ-007 | B38: Trade Rejection | C38: Internal detail must not reach the customer | D38: Critical | G38: 5 | H38: Trigger an internal error during a decision if you can (ask the dev team). | I38: Any error shown to the customer is a generic message, never a stack trace or a database error. | K38: Not Run
A39: TRJ-008 | B39: Trade Rejection | C39: Rejected then back to Pending then Approved | D39: High | E39: The application for trade.reject01@example.com is Rejected. Mail capture cleared. | F39: Transitions: Rejected > Pending > Approved | G39: 1 | H39: Clear the mail capture inbox. | I39: Empty. | K39: Not Run
A40: TRJ-008 | B40: Trade Rejection | C40: Rejected then back to Pending then Approved | D40: High | G40: 2 | H40: In admin, move the rejected application back to Pending. | I40: ACCEPTED - rejection is NOT terminal for a trade application; a customer can be reconsidered. (Contrast with a rejected ACCOUNT, which is terminal.) | K40: Not Run
A41: TRJ-008 | B41: Trade Rejection | C41: Rejected then back to Pending then Approved | D41: High | G41: 3 | H41: Check the mail capture inbox after moving to Pending. | I41: Record whether an email was sent for the move back to pending. Note the finding. | K41: Not Run
A42: TRJ-008 | B42: Trade Rejection | C42: Rejected then back to Pending then Approved | D42: High | G42: 4 | H42: Confirm the customer still has no band pricing while Pending. | I42: Retail EUR 505.00 at quantity 10. | K42: Not Run
A43: TRJ-008 | B43: Trade Rejection | C43: Rejected then back to Pending then Approved | D43: High | G43: 5 | H43: Now approve the application. | I43: Approval succeeds. | K43: Not Run
A44: TRJ-008 | B44: Trade Rejection | C44: Rejected then back to Pending then Approved | D44: High | G44: 6 | H44: Check the mail capture inbox. | I44: A NEW approval email is sent. A genuine new transition must notify the customer even though they were notified of the earlier rejection. | K44: Not Run
A45: TRJ-008 | B45: Trade Rejection | C45: Rejected then back to Pending then Approved | D45: High | G45: 7 | H45: Sign in as the customer and check pricing at quantity 10. | I45: EUR 450.00 ex VAT - trade pricing is now active. | K45: Not Run
A46: TRJ-008 | B46: Trade Rejection | C46: Rejected then back to Pending then Approved | D46: High | G46: 8 | H46: Confirm the dashboard headline now says approved. | I46: No trace of the earlier rejection in the current status. | K46: Not Run

Sheet Trade Suspension
A1: Trade Suspension
A2: There are TWO separate ways pricing can be withdrawn: suspending the ACCOUNT (status), and suspending the TRADE STATUS. They are different ladders with different effects - the account suspension also stops the customer ordering at all. Test both.
A3: Test Case ID | B3: Module | C3: Test Scenario | D3: Priority | E3: Preconditions | F3: Test Data | G3: Step No. | H3: Action / Steps | I3: Expected Result | J3: Actual Result | K3: Status | L3: Severity | M3: Bug ID | N3: Tester Comments
A4: TSU-001 | B4: Trade Suspension | C4: Prepare an approved Trade account to suspend | D4: High | E4: No account for trade.suspend01@example.com. | F4: Email: trade.suspend01@example.com | Phone: +353861234569 | Company: Suspend Test Ltd | Trade: IT reseller or MSP | VAT: IE6666666S | Expected spend: Over EUR 5,000 | Password: Test@2026Secure! | G4: 1 | H4: Register the Trade account above and complete email verification. | I4: Account created, application Pending. | K4: Not Run
A5: TSU-001 | B5: Trade Suspension | C5: Prepare an approved Trade account to suspend | D5: High | G5: 2 | H5: In admin, approve the application. | I5: Trade status = approved. | K5: Not Run
A6: TSU-001 | B6: Trade Suspension | C6: Prepare an approved Trade account to suspend | D6: High | G6: 3 | H6: Sign in as the customer and confirm band pricing at quantity 10. | I6: EUR 450.00 ex VAT. | K6: Not Run
A7: TSU-001 | B7: Trade Suspension | C7: Prepare an approved Trade account to suspend | D7: High | G7: 4 | H7: Leave 10 units of 'testing product' (product ID 99240288, slug testing-product, retail EUR 505.00 ex VAT) in the basket and sign out. | I7: Basket holds 10 units priced at the band rate. | K7: Not Run
A8: TSU-002 | B8: Trade Suspension | C8: Suspend the TRADE STATUS and verify pricing is withdrawn | D8: Critical | E8: TSU-001 done. | F8: Trade status: Suspended | G8: 1 | H8: In admin, set the TRADE STATUS of the account to Suspended. | I8: Accepted - an approved application can be suspended. | K8: Not Run
A9: TSU-002 | B9: Trade Suspension | C9: Suspend the TRADE STATUS and verify pricing is withdrawn | D9: Critical | G9: 2 | H9: Refresh admin and confirm the state. | I9: Trade status = suspended. ACCOUNT status is still active. | K9: Not Run
A10: TSU-002 | B10: Trade Suspension | C10: Suspend the TRADE STATUS and verify pricing is withdrawn | D10: Critical | G10: 3 | H10: Confirm the pricing entitlement is withdrawn on the admin record. | I10: No business/band pricing entitlement. | K10: Not Run
A11: TSU-002 | B11: Trade Suspension | C11: Suspend the TRADE STATUS and verify pricing is withdrawn | D11: Critical | G11: 4 | H11: Sign in as the customer and open the product page at quantity 10. | I11: Back to RETAIL EUR 505.00 ex VAT. No bands advertised. | K11: Not Run
A12: TSU-002 | B12: Trade Suspension | C12: Suspend the TRADE STATUS and verify pricing is withdrawn | D12: Critical | G12: 5 | H12: Open the basket that still holds 10 units. | I12: The basket has RE-PRICED to EUR 505.00 per unit, EUR 5,050.00 ex VAT. A basket priced while the entitlement stood must not keep the old rate. | K12: Not Run
A13: TSU-002 | B13: Trade Suspension | C13: Suspend the TRADE STATUS and verify pricing is withdrawn | D13: Critical | G13: 6 | H13: Proceed to checkout. | I13: Checkout also shows EUR 505.00. Basket and checkout agree. | K13: Not Run
A14: TSU-002 | B14: Trade Suspension | C14: Suspend the TRADE STATUS and verify pricing is withdrawn | D14: Critical | G14: 7 | H14: Search for the product and open the category listing. | I14: Both show retail EUR 505.00 with no struck-through band price. | K14: Not Run
A15: TSU-002 | B15: Trade Suspension | C15: Suspend the TRADE STATUS and verify pricing is withdrawn | D15: Critical | G15: 8 | H15: Confirm the customer can STILL place an order. | I15: Ordering works at retail - suspending trade status withdraws pricing only, it does not stop the customer buying. | K15: Not Run
A16: TSU-003 | B16: Trade Suspension | C16: Reinstate the trade status | D16: High | E16: TSU-002 done. | F16: Trade status: Approved | G16: 1 | H16: In admin, set the trade status back to Approved. | I16: Accepted - a suspended application can be reinstated. | K16: Not Run
A17: TSU-003 | B17: Trade Suspension | C17: Reinstate the trade status | D17: High | G17: 2 | H17: Sign in as the customer and open the product page at quantity 10. | I17: Band pricing is back: EUR 450.00 ex VAT. | K17: Not Run
A18: TSU-003 | B18: Trade Suspension | C18: Reinstate the trade status | D18: High | G18: 3 | H18: Open the basket. | I18: The basket has re-priced to EUR 450.00 per unit. | K18: Not Run
A19: TSU-003 | B19: Trade Suspension | C19: Reinstate the trade status | D19: High | G19: 4 | H19: Check the mail capture inbox. | I19: Record whether suspending or reinstating the trade status sends the customer an email. Note the finding - the approval/rejection emails are the documented ones. | K19: Not Run
A20: TSU-004 | B20: Trade Suspension | C20: Suspend the ACCOUNT and verify it stops ordering | D20: Critical | E20: TSU-003 done - the account is approved with band pricing and holds 10 units in the basket. | F20: Account status: Suspended | Note: Payment dispute under review | G20: 1 | H20: In admin, set the ACCOUNT STATUS to Suspended with the note "Payment dispute under review". | I20: Accepted - an active account can be suspended. | K20: Not Run
A21: TSU-004 | B21: Trade Suspension | C21: Suspend the ACCOUNT and verify it stops ordering | D21: Critical | G21: 2 | H21: Refresh admin and confirm the state. | I21: Account status = suspended. TRADE status is still approved - suspending the account does not touch the application. | K21: Not Run
A22: TSU-004 | B22: Trade Suspension | C22: Suspend the ACCOUNT and verify it stops ordering | D22: Critical | G22: 3 | H22: Confirm the pricing entitlement is withdrawn. | I22: No entitlement - a suspended account gets no band pricing even though its trade application is still approved. | K22: Not Run
A23: TSU-004 | B23: Trade Suspension | C23: Suspend the ACCOUNT and verify it stops ordering | D23: Critical | G23: 4 | H23: While the customer is still signed in in another browser, have them load any account page. | I23: They are signed out automatically and sent to the sign-in page with the message "Your account has been suspended. Please contact support for assistance." Suspension ends every open session; it does not wait for the next sign-in. | K23: Not Run
A24: TSU-004 | B24: Trade Suspension | C24: Suspend the ACCOUNT and verify it stops ordering | D24: Critical | G24: 5 | H24: Attempt to sign in as the customer. | I24: REFUSED with "Your account has been suspended. Please contact support for assistance." No session is created and the customer does not reach the dashboard. | K24: Not Run
A25: TSU-004 | B25: Trade Suspension | C25: Suspend the ACCOUNT and verify it stops ordering | D25: Critical | G25: 6 | H25: Confirm the refusal does not repeat the internal note. | I25: The words "Payment dispute under review" appear nowhere - that note is a staff remark. | K25: Not Run
A26: TSU-004 | B26: Trade Suspension | C26: Suspend the ACCOUNT and verify it stops ordering | D26: Critical | G26: 7 | H26: Signed out, open the product page at quantity 10. | I26: The shop front still works and shows RETAIL EUR 505.00. Suspension blocks the account, not browsing. | K26: Not Run
A27: TSU-004 | B27: Trade Suspension | C27: Suspend the ACCOUNT and verify it stops ordering | D27: Critical | G27: 8 | H27: Attempt to reach the account pages directly by URL while signed out. | I27: Refused / redirected to sign-in. See the Suspended Account Access sheet for the full set. | K27: Not Run
A28: TSU-005 | B28: Trade Suspension | C28: Suspension persists and is reversible | D28: High | E28: TSU-004 done. | F28: Account status: Suspended, then Active | G28: 1 | H28: Attempt to sign in again as the suspended customer. | I28: Still refused with the same suspension message. | K28: Not Run
A29: TSU-005 | B29: Trade Suspension | C29: Suspension persists and is reversible | D29: High | G29: 2 | H29: Attempt to sign in from a different browser. | I29: Also refused. The block lives on the account, not on one session. | K29: Not Run
A30: TSU-005 | B30: Trade Suspension | C30: Suspension persists and is reversible | D30: High | G30: 3 | H30: In admin, return the account status to Active. | I30: Accepted - a suspended account can be brought back. | K30: Not Run
A31: TSU-005 | B31: Trade Suspension | C31: Suspension persists and is reversible | D31: High | G31: 4 | H31: Sign in as the customer and read the dashboard. | I31: The suspension message is gone. | K31: Not Run
A32: TSU-005 | B32: Trade Suspension | C32: Suspension persists and is reversible | D32: High | G32: 5 | H32: Open the product page at quantity 10. | I32: Band pricing is back at EUR 450.00 - because the trade status was still approved underneath, reactivating restores the entitlement immediately. | K32: Not Run
A33: TSU-005 | B33: Trade Suspension | C33: Suspension persists and is reversible | D33: High | G33: 6 | H33: Place an order. | I33: Accepted. | K33: Not Run
A34: TSU-006 | B34: Trade Suspension | C34: Invalid account-status transitions are refused | D34: High | E34: An active account and a rejected account are available. | F34: Transitions to attempt. | G34: 1 | H34: In admin, attempt to move an ACTIVE account straight to Rejected. | I34: REFUSED - an active account cannot jump straight to rejected. Record the message. | K34: Not Run
A35: TSU-006 | B35: Trade Suspension | C35: Invalid account-status transitions are refused | D35: High | G35: 2 | H35: Attempt to set an account status to an unknown value such as "frozen". | I35: REFUSED. Status unchanged. | K35: Not Run
A36: TSU-006 | B36: Trade Suspension | C36: Invalid account-status transitions are refused | D36: High | G36: 3 | H36: Move an account to the status it ALREADY has (active to active). | I36: Allowed - a no-op transition is permitted and changes nothing. | K36: Not Run
A37: TSU-006 | B37: Trade Suspension | C37: Invalid account-status transitions are refused | D37: High | G37: 4 | H37: Ask the dev team to put an account into Rejected, then attempt to reactivate it. | I37: REFUSED - rejected is TERMINAL for an ACCOUNT. (Note the contrast: rejected is NOT terminal for a trade APPLICATION - see TRJ-008.) | K37: Not Run
A38: TSU-007 | B38: Trade Suspension | C38: Withdrawing trade status does not disturb the account, and vice versa | D38: High | E38: An approved trade account that is active. | F38: Change one axis at a time. | G38: 1 | H38: Note the current account status and trade status. | I38: Account active, trade approved. | K38: Not Run
A39: TSU-007 | B39: Trade Suspension | C39: Withdrawing trade status does not disturb the account, and vice versa | D39: High | G39: 2 | H39: Suspend the TRADE status only. | I39: Trade suspended; ACCOUNT still active; the customer can still order, at retail. | K39: Not Run
A40: TSU-007 | B40: Trade Suspension | C40: Withdrawing trade status does not disturb the account, and vice versa | D40: High | G40: 3 | H40: Return trade status to approved, then suspend the ACCOUNT only. | I40: Account suspended; TRADE status still approved; the customer cannot order at all. | K40: Not Run
A41: TSU-007 | B41: Trade Suspension | C41: Withdrawing trade status does not disturb the account, and vice versa | D41: High | G41: 4 | H41: Return the account to active. | I41: Both axes back to their original values; band pricing restored. | K41: Not Run
A42: TSU-007 | B42: Trade Suspension | C42: Withdrawing trade status does not disturb the account, and vice versa | D42: High | G42: 5 | H42: Confirm the two were never changed together by a single action. | I42: Account status and trade status are independent. An action on one must not silently move the other. The one documented exception is that APPROVING a trade application also marks verification verified. | K42: Not Run

Sheet Pricing & Quantity Bands
A1: Pricing & Quantity Bands
A2: Band prices for 'testing product' (product ID 99240288, slug testing-product, retail EUR 505.00 ex VAT): quantity 5-10 = EUR 450.00, 11-20 = EUR 430.00, 21-30 = EUR 420.00 (all ex VAT). There is NO band below 5 and NO band above 30 - those quantities pay retail EUR 505.00. A band NEVER charges above the retail price. Verify the band figures in {admin}/business-products before starting.
A3: Test Case ID | B3: Module | C3: Test Scenario | D3: Priority | E3: Preconditions | F3: Test Data | G3: Step No. | H3: Action / Steps | I3: Expected Result | J3: Actual Result | K3: Status | L3: Severity | M3: Bug ID | N3: Tester Comments
A4: PQB-001 | B4: Pricing & Quantity Bands | C4: Confirm the band configuration in admin before testing | D4: Critical | E4: Admin access. | F4: URL: {admin}/business-products | G4: 1 | H4: Open {admin}/business-products. | I4: The list loads, showing one row per product that has bands, with a count of bands. | K4: Not Run
A5: PQB-001 | B5: Pricing & Quantity Bands | C5: Confirm the band configuration in admin before testing | D5: Critical | G5: 2 | H5: Find 'testing product' (product ID 99240288, slug testing-product, retail EUR 505.00 ex VAT) and note the number of bands. | I5: The product is listed with 3 bands. | K5: Not Run
A6: PQB-001 | B6: Pricing & Quantity Bands | C6: Confirm the band configuration in admin before testing | D6: Critical | G6: 3 | H6: Open the product's band ladder. | I6: Three bands, in quantity order: 5-10, 11-20, 21-30. | K6: Not Run
A7: PQB-001 | B7: Pricing & Quantity Bands | C7: Confirm the band configuration in admin before testing | D7: Critical | G7: 4 | H7: Record the final price of each band. | I7: EUR 450.00, EUR 430.00 and EUR 420.00 respectively. If these differ, update the expected values throughout this sheet and the Cart, VAT and Checkout sheets before continuing. | K7: Not Run
A8: PQB-001 | B8: Pricing & Quantity Bands | C8: Confirm the band configuration in admin before testing | D8: Critical | G8: 5 | H8: Confirm the retail selling price of the product. | I8: EUR 505.00 ex VAT. | K8: Not Run
A9: PQB-001 | B9: Pricing & Quantity Bands | C9: Confirm the band configuration in admin before testing | D9: Critical | G9: 6 | H9: Confirm there is no band covering quantity 1-4 or 31+. | I9: Correct - those quantities fall back to retail. This is the configured data, not a defect. | K9: Not Run
A10: PQB-002 | B10: Pricing & Quantity Bands | C10: Quantity 1 - below the first band | D10: Critical | E10: Signed in as the approved Trade account trade.test01@example.com (or the Business account). | F10: Quantity: 1 | G10: 1 | H10: Open the product page and set quantity to 1. | I10: Unit price EUR 505.00 ex VAT - retail, because no band covers quantity 1. | K10: Not Run
A11: PQB-002 | B11: Pricing & Quantity Bands | C11: Quantity 1 - below the first band | D11: Critical | G11: 2 | H11: Add 1 unit to the basket and open the basket. | I11: EUR 505.00 ex VAT, line total EUR 505.00. | K11: Not Run
A12: PQB-002 | B12: Pricing & Quantity Bands | C12: Quantity 1 - below the first band | D12: Critical | G12: 3 | H12: Open checkout. | I12: EUR 505.00 ex VAT, VAT EUR 116.15, total EUR 621.15 inc VAT. | K12: Not Run
A13: PQB-002 | B13: Pricing & Quantity Bands | C13: Quantity 1 - below the first band | D13: Critical | G13: 4 | H13: Check the price in the search results and the category listing. | I13: Both show a price consistent with the product page for a single unit. | K13: Not Run
A14: PQB-003 | B14: Pricing & Quantity Bands | C14: Quantity 5 - the first band boundary | D14: Critical | E14: Signed in as an entitled account. | F14: Quantity: 5 | G14: 1 | H14: Set the product quantity to 4. | I14: EUR 505.00 ex VAT - still below the band. | K14: Not Run
A15: PQB-003 | B15: Pricing & Quantity Bands | C15: Quantity 5 - the first band boundary | D15: Critical | G15: 2 | H15: Set the quantity to 5. | I15: Drops to EUR 450.00 ex VAT - the 5-10 band begins exactly at 5. | K15: Not Run
A16: PQB-003 | B16: Pricing & Quantity Bands | C16: Quantity 5 - the first band boundary | D16: Critical | G16: 3 | H16: Add 5 units to the basket. | I16: Unit EUR 450.00, line total EUR 2,250.00 ex VAT. | K16: Not Run
A17: PQB-003 | B17: Pricing & Quantity Bands | C17: Quantity 5 - the first band boundary | D17: Critical | G17: 4 | H17: Open checkout. | I17: EUR 2,250.00 ex VAT, VAT EUR 517.50, total EUR 2,767.50 inc VAT. | K17: Not Run
A18: PQB-004 | B18: Pricing & Quantity Bands | C18: Quantity 10 - inside the first band | D18: Critical | E18: Signed in as an entitled account. | F18: Quantity: 10 | G18: 1 | H18: Set the quantity to 10. | I18: EUR 450.00 ex VAT per unit - still the 5-10 band. | K18: Not Run
A19: PQB-004 | B19: Pricing & Quantity Bands | C19: Quantity 10 - inside the first band | D19: Critical | G19: 2 | H19: Add 10 to the basket. | I19: Line total EUR 4,500.00 ex VAT. | K19: Not Run
A20: PQB-004 | B20: Pricing & Quantity Bands | C20: Quantity 10 - inside the first band | D20: Critical | G20: 3 | H20: Open checkout. | I20: EUR 4,500.00 ex VAT, VAT EUR 1,035.00, total EUR 5,535.00 inc VAT. | K20: Not Run
A21: PQB-004 | B21: Pricing & Quantity Bands | C21: Quantity 10 - inside the first band | D21: Critical | G21: 4 | H21: Set the quantity to 11 in the basket. | I21: Unit price drops to EUR 430.00 - crossing into the 11-20 band. Line total EUR 4,730.00 ex VAT. | K21: Not Run
A22: PQB-005 | B22: Pricing & Quantity Bands | C22: Quantity 25 - the third band | D22: Critical | E22: Signed in as an entitled account. | F22: Quantity: 25 | G22: 1 | H22: Set the quantity to 20. | I22: EUR 430.00 ex VAT per unit - top of the 11-20 band. | K22: Not Run
A23: PQB-005 | B23: Pricing & Quantity Bands | C23: Quantity 25 - the third band | D23: Critical | G23: 2 | H23: Set the quantity to 21. | I23: EUR 420.00 ex VAT - the 21-30 band begins. | K23: Not Run
A24: PQB-005 | B24: Pricing & Quantity Bands | C24: Quantity 25 - the third band | D24: Critical | G24: 3 | H24: Set the quantity to 25. | I24: EUR 420.00 ex VAT per unit, line total EUR 10,500.00 ex VAT. | K24: Not Run
A25: PQB-005 | B25: Pricing & Quantity Bands | C25: Quantity 25 - the third band | D25: Critical | G25: 4 | H25: Open checkout. | I25: EUR 10,500.00 ex VAT, VAT EUR 2,415.00, total EUR 12,915.00 inc VAT. | K25: Not Run
A26: PQB-005 | B26: Pricing & Quantity Bands | C26: Quantity 25 - the third band | D26: Critical | G26: 5 | H26: Set the quantity to 30. | I26: EUR 420.00 ex VAT - top of the last band. | K26: Not Run
A27: PQB-006 | B27: Pricing & Quantity Bands | C27: Quantity 31 - above the top band | D27: High | E27: Signed in as an entitled account. | F27: Quantity: 31 | G27: 1 | H27: Set the quantity to 31. | I27: Unit price returns to RETAIL EUR 505.00 ex VAT. The top band stops at 30 and there is no open-ended band above it. | K27: Not Run
A28: PQB-006 | B28: Pricing & Quantity Bands | C28: Quantity 31 - above the top band | D28: High | G28: 2 | H28: Check the basket at quantity 31. | I28: EUR 505.00 per unit, line total EUR 15,655.00 ex VAT. | K28: Not Run
A29: PQB-006 | B29: Pricing & Quantity Bands | C29: Quantity 31 - above the top band | D29: High | G29: 3 | H29: Confirm this is the configured behaviour and not a bug. | I29: Correct for this data set - the ladder simply ends at 30. Record it as an observation for the business (buying 31 costs more than buying 30), but do NOT raise it as a functional defect. | K29: Not Run
A30: PQB-006 | B30: Pricing & Quantity Bands | C30: Quantity 31 - above the top band | D30: High | G30: 4 | H30: Compare the cost of 30 units against 31 units. | I30: 30 units = EUR 12,600.00 ex VAT; 31 units = EUR 15,655.00 ex VAT. Note this in Tester Comments for the product owner. | K30: Not Run
A31: PQB-007 | B31: Pricing & Quantity Bands | C31: Crossing a threshold up and back down | D31: High | E31: Signed in as an entitled account. Basket empty. | F31: Quantities 4 > 5 > 4 > 11 > 10 | G31: 1 | H31: Add 4 units to the basket. | I31: EUR 505.00 per unit. | K31: Not Run
A32: PQB-007 | B32: Pricing & Quantity Bands | C32: Crossing a threshold up and back down | D32: High | G32: 2 | H32: Increase the basket quantity to 5. | I32: Re-prices to EUR 450.00 per unit immediately. | K32: Not Run
A33: PQB-007 | B33: Pricing & Quantity Bands | C33: Crossing a threshold up and back down | D33: High | G33: 3 | H33: Decrease it back to 4. | I33: Returns to EUR 505.00 per unit. Coming back below the threshold must lose the band price. | K33: Not Run
A34: PQB-007 | B34: Pricing & Quantity Bands | C34: Crossing a threshold up and back down | D34: High | G34: 4 | H34: Increase to 11. | I34: EUR 430.00 per unit. | K34: Not Run
A35: PQB-007 | B35: Pricing & Quantity Bands | C35: Crossing a threshold up and back down | D35: High | G35: 5 | H35: Decrease to 10. | I35: Returns to EUR 450.00 per unit. | K35: Not Run
A36: PQB-007 | B36: Pricing & Quantity Bands | C36: Crossing a threshold up and back down | D36: High | G36: 6 | H36: Refresh the basket page. | I36: The price still matches the current quantity - the displayed price is derived, not a stale stored value. | K36: Not Run
A37: PQB-008 | B37: Pricing & Quantity Bands | C37: A band never charges above the retail price | D37: Critical | E37: Admin access to edit bands. Use a DIFFERENT product from the main one so the pack's figures stay intact, or restore the bands afterwards. | F37: Band wholesale price set deliberately ABOVE retail. | G37: 1 | H37: In {admin}/business-products, pick a test product and note its retail price. | I37: Retail price recorded. | K37: Not Run
A38: PQB-008 | B38: Pricing & Quantity Bands | C38: A band never charges above the retail price | D38: Critical | G38: 2 | H38: Create a band for quantity 1 and upwards with a wholesale price HIGHER than the retail price (for example retail + 200). | I38: The band saves. | K38: Not Run
A39: PQB-008 | B39: Pricing & Quantity Bands | C39: A band never charges above the retail price | D39: Critical | G39: 3 | H39: Sign in as an entitled account and open that product at quantity 1. | I39: The price shown is the RETAIL price, NOT the higher band price. A band can only ever reduce a price, never raise it. | K39: Not Run
A40: PQB-008 | B40: Pricing & Quantity Bands | C40: A band never charges above the retail price | D40: Critical | G40: 4 | H40: Add it to the basket and check the basket and checkout price. | I40: Retail price in both. The cap holds everywhere, not just on the product page. | K40: Not Run
A41: PQB-008 | B41: Pricing & Quantity Bands | C41: A band never charges above the retail price | D41: Critical | G41: 5 | H41: Delete the test band afterwards. | I41: Band removed; the product is back to retail-only. | K41: Not Run
A42: PQB-009 | B42: Pricing & Quantity Bands | C42: Who is and is not offered bands | D42: Critical | E42: Accounts available: guest (signed out), personal, business, trade pending, trade approved, trade rejected, trade suspended, suspended account. | F42: 'testing product' (product ID 99240288, slug testing-product, retail EUR 505.00 ex VAT) at quantity 10 | G42: 1 | H42: Signed OUT (guest), open the product page at quantity 10. | I42: NO bands advertised. Retail EUR 505.00. | K42: Not Run
A43: PQB-009 | B43: Pricing & Quantity Bands | C43: Who is and is not offered bands | D43: Critical | G43: 2 | H43: Sign in as a PERSONAL account and check quantity 10. | I43: NO bands. Retail EUR 505.00. | K43: Not Run
A44: PQB-009 | B44: Pricing & Quantity Bands | C44: Who is and is not offered bands | D44: Critical | G44: 3 | H44: Sign in as the BUSINESS account and check quantity 10. | I44: Bands ARE offered. EUR 450.00. A business account qualifies from signup. | K44: Not Run
A45: PQB-009 | B45: Pricing & Quantity Bands | C45: Who is and is not offered bands | D45: Critical | G45: 4 | H45: Sign in as a trade account with a PENDING application. | I45: NO bands. Retail EUR 505.00. | K45: Not Run
A46: PQB-009 | B46: Pricing & Quantity Bands | C46: Who is and is not offered bands | D46: Critical | G46: 5 | H46: Sign in as a trade account that was REJECTED. | I46: NO bands. Retail EUR 505.00. | K46: Not Run
A47: PQB-009 | B47: Pricing & Quantity Bands | C47: Who is and is not offered bands | D47: Critical | G47: 6 | H47: Sign in as a trade account that is APPROVED. | I47: Bands offered. EUR 450.00. | K47: Not Run
A48: PQB-009 | B48: Pricing & Quantity Bands | C48: Who is and is not offered bands | D48: Critical | G48: 7 | H48: Sign in as an approved trade account whose TRADE STATUS is suspended. | I48: NO bands. Retail EUR 505.00. | K48: Not Run
A49: PQB-009 | B49: Pricing & Quantity Bands | C49: Who is and is not offered bands | D49: Critical | G49: 8 | H49: Sign in as an approved trade account whose ACCOUNT is suspended. | I49: NO bands. Retail EUR 505.00. | K49: Not Run
A50: PQB-010 | B50: Pricing & Quantity Bands | C50: The advertised band price is the price actually charged | D50: Critical | E50: Signed in as an entitled account. | F50: Quantity 10 - advertised EUR 450.00 | G50: 1 | H50: Read the band price advertised on the product page at quantity 10. | I50: EUR 450.00 ex VAT. | K50: Not Run
A51: PQB-010 | B51: Pricing & Quantity Bands | C51: The advertised band price is the price actually charged | D51: Critical | G51: 2 | H51: Add 10 to the basket and read the basket unit price. | I51: EUR 450.00 - identical to the advertised figure. | K51: Not Run
A52: PQB-010 | B52: Pricing & Quantity Bands | C52: The advertised band price is the price actually charged | D52: Critical | G52: 3 | H52: Open checkout and read the unit price. | I52: EUR 450.00. | K52: Not Run
A53: PQB-010 | B53: Pricing & Quantity Bands | C53: The advertised band price is the price actually charged | D53: Critical | G53: 4 | H53: Place the order and open the order confirmation. | I53: EUR 450.00 per unit, EUR 4,500.00 ex VAT. | K53: Not Run
A54: PQB-010 | B54: Pricing & Quantity Bands | C54: The advertised band price is the price actually charged | D54: Critical | G54: 5 | H54: Open the order in admin. | I54: EUR 450.00 per unit. | K54: Not Run
A55: PQB-010 | B55: Pricing & Quantity Bands | C55: The advertised band price is the price actually charged | D55: Critical | G55: 6 | H55: Open the invoice. | I55: EUR 450.00 per unit. The advertised price, the basket, checkout, the order and the invoice must all be the same figure - the store must never advertise a rate the till will not honour. | K55: Not Run
A56: PQB-011 | B56: Pricing & Quantity Bands | C56: Admin band editing - validation | D56: High | E56: Admin access. Use a scratch product so the main test data is untouched. | F56: Overlapping and invalid bands. | G56: 1 | H56: In {admin}/business-products, create bands 1-10 and 5-20 on a scratch product and save. | I56: REFUSED - the ranges overlap. The message names the row that overlaps. Nothing is saved. | K56: Not Run
A57: PQB-011 | B57: Pricing & Quantity Bands | C57: Admin band editing - validation | D57: High | G57: 2 | H57: Create two open-ended bands (10 upwards and 20 upwards) and save. | I57: REFUSED - two open-ended bands overlap each other. | K57: Not Run
A58: PQB-011 | B58: Pricing & Quantity Bands | C58: Admin band editing - validation | D58: High | G58: 3 | H58: Create touching bands 1-9 and 10 upwards and save. | I58: ACCEPTED - touching ranges do not overlap. | K58: Not Run
A59: PQB-011 | B59: Pricing & Quantity Bands | C59: Admin band editing - validation | D59: High | G59: 4 | H59: Create a band with a minimum quantity of 0 and save. | I59: REFUSED - the minimum quantity must be at least 1. | K59: Not Run
A60: PQB-011 | B60: Pricing & Quantity Bands | C60: Admin band editing - validation | D60: High | G60: 5 | H60: Create a band with maximum 5 and minimum 10 and save. | I60: REFUSED - the maximum is below the minimum. | K60: Not Run
A61: PQB-011 | B61: Pricing & Quantity Bands | C61: Admin band editing - validation | D61: High | G61: 6 | H61: Create a band with a negative wholesale price and save. | I61: REFUSED - prices and discounts cannot be negative. | K61: Not Run
A62: PQB-011 | B62: Pricing & Quantity Bands | C62: Admin band editing - validation | D62: High | G62: 7 | H62: Create a percentage-discount band of 120% and save. | I62: REFUSED - a percentage discount cannot exceed 100. | K62: Not Run
A63: PQB-011 | B63: Pricing & Quantity Bands | C63: Admin band editing - validation | D63: High | G63: 8 | H63: After a refused save, re-open the product's band ladder. | I63: The PREVIOUSLY SAVED bands are still intact. A refused save must not wipe the existing ladder. | K63: Not Run
A64: PQB-012 | B64: Pricing & Quantity Bands | C64: Admin band editing - the price is derived, not taken from the browser | D64: Critical | E64: Admin access, developer tools available. | F64: Send a forged final_price in the save request. | G64: 1 | H64: Create a band on a scratch product with wholesale 100 and a fixed discount of 25, and save. | I64: Saved. The stored final price is EUR 75.00 - derived from the inputs. | K64: Not Run
A65: PQB-012 | B65: Pricing & Quantity Bands | C65: Admin band editing - the price is derived, not taken from the browser | D65: Critical | G65: 2 | H65: Create a band with wholesale 200 and a 10% discount. | I65: Stored final price is EUR 180.00. | K65: Not Run
A66: PQB-012 | B66: Pricing & Quantity Bands | C66: Admin band editing - the price is derived, not taken from the browser | D66: Critical | G66: 3 | H66: Create a band with wholesale 10 and a fixed discount of 40. | I66: Stored final price is EUR 0.00 - floored at zero, never negative. | K66: Not Run
A67: PQB-012 | B67: Pricing & Quantity Bands | C67: Admin band editing - the price is derived, not taken from the browser | D67: Critical | G67: 4 | H67: Using developer tools, resend the band save request with "final_price": 1 injected alongside wholesale 100 and discount 25. | I67: The stored final price is still EUR 75.00. The browser's figure is IGNORED - it is what the customer pays, so the server derives it. | K67: Not Run
A68: PQB-012 | B68: Pricing & Quantity Bands | C68: Admin band editing - the price is derived, not taken from the browser | D68: Critical | G68: 5 | H68: Confirm the customer-facing price matches. | I68: An entitled customer is quoted EUR 75.00, not EUR 1.00. | K68: Not Run
A69: PQB-013 | B69: Pricing & Quantity Bands | C69: Replacing and deleting a band ladder | D69: Medium | E69: Admin access, scratch product with 3 bands. | F69: Save a shorter ladder; delete the ladder. | G69: 1 | H69: On a scratch product with three bands, save a ladder containing only ONE band. | I69: The product now has exactly ONE band - the ladder is replaced wholesale, not appended to. | K69: Not Run
A70: PQB-013 | B70: Pricing & Quantity Bands | C70: Replacing and deleting a band ladder | D70: Medium | G70: 2 | H70: Save an EMPTY ladder. | I70: The product has no bands at all and reverts to retail for everyone. | K70: Not Run
A71: PQB-013 | B71: Pricing & Quantity Bands | C71: Replacing and deleting a band ladder | D71: Medium | G71: 3 | H71: Recreate a band, then use the delete action on the product. | I71: All bands for that product are removed. | K71: Not Run
A72: PQB-013 | B72: Pricing & Quantity Bands | C72: Replacing and deleting a band ladder | D72: Medium | G72: 4 | H72: Confirm an entitled customer now sees retail for that product. | I72: Retail price, no bands advertised. | K72: Not Run
A73: PQB-014 | B73: Pricing & Quantity Bands | C73: Band pricing interaction with a flash sale or promotion | D73: Medium | E73: Ask the dev team to put the test product into an active flash sale, or use a product already in one. If no promotion mechanism is configured, mark Not Applicable. | F73: Flash sale price vs band price. | G73: 1 | H73: Note the flash-sale price and the band price for the product. | I73: Both recorded. | K73: Not Run
A74: PQB-014 | B74: Pricing & Quantity Bands | C74: Band pricing interaction with a flash sale or promotion | D74: Medium | G74: 2 | H74: Sign in as an entitled account and open the product at quantity 10. | I74: Record which price wins. The rule implemented is that a band never charges above the prevailing retail ladder, and the flash price is part of that ladder - so the charged price should be the LOWER of the two. | K74: Not Run
A75: PQB-014 | B75: Pricing & Quantity Bands | C75: Band pricing interaction with a flash sale or promotion | D75: Medium | G75: 3 | H75: Add to the basket and check the basket and checkout price. | I75: The same figure as the product page. Whatever the rule, it must be applied consistently across all three. | K75: Not Run
A76: PQB-014 | B76: Pricing & Quantity Bands | C76: Band pricing interaction with a flash sale or promotion | D76: Medium | G76: 4 | H76: Place an order and check the order and invoice. | I76: Same figure again. | K76: Not Run
A77: PQB-014 | B77: Pricing & Quantity Bands | C77: Band pricing interaction with a flash sale or promotion | D77: Medium | G77: 5 | H77: Record the outcome clearly in Actual Result. | I77: If product page and checkout disagree, that is a defect regardless of which rule is correct. | K77: Not Run

Sheet Cart & Cart Repricing
A1: Cart & Cart Repricing
A2: The basket price is derived on read, not stored and trusted. That means an entitlement change must re-price a basket that already exists. The tester must also prove that editing prices in the browser cannot change what is charged.
A3: Test Case ID | B3: Module | C3: Test Scenario | D3: Priority | E3: Preconditions | F3: Test Data | G3: Step No. | H3: Action / Steps | I3: Expected Result | J3: Actual Result | K3: Status | L3: Severity | M3: Bug ID | N3: Tester Comments
A4: CRP-001 | B4: Cart & Cart Repricing | C4: Build a basket before trade approval | D4: Critical | E4: A Trade account with a PENDING application (register trade.cart01@example.com if needed). | F4: Email: trade.cart01@example.com | Phone: +353861234573 | 10 units of the test product | G4: 1 | H4: Register a Trade account, verify the email, and leave the application Pending. | I4: Account active, trade status pending. | K4: Not Run
A5: CRP-001 | B5: Cart & Cart Repricing | C5: Build a basket before trade approval | D5: Critical | G5: 2 | H5: Sign in and add 10 units of 'testing product' (product ID 99240288, slug testing-product, retail EUR 505.00 ex VAT) to the basket. | I5: Added. | K5: Not Run
A6: CRP-001 | B6: Cart & Cart Repricing | C6: Build a basket before trade approval | D6: Critical | G6: 3 | H6: Open the basket and record the unit price and line total. | I6: EUR 505.00 per unit, EUR 5,050.00 ex VAT - retail, because the application is still pending. | K6: Not Run
A7: CRP-001 | B7: Cart & Cart Repricing | C7: Build a basket before trade approval | D7: Critical | G7: 4 | H7: Leave the basket as it is and sign out. | I7: Basket is retained against the account. | K7: Not Run
A8: CRP-002 | B8: Cart & Cart Repricing | C8: Approve the trade account and re-price the existing basket | D8: Critical | E8: CRP-001 done. | F8: Approve in admin, then refresh the basket. | G8: 1 | H8: In admin, approve the trade application for trade.cart01@example.com. | I8: Trade status = approved. | K8: Not Run
A9: CRP-002 | B9: Cart & Cart Repricing | C9: Approve the trade account and re-price the existing basket | D9: Critical | G9: 2 | H9: Sign in as the customer and open the basket WITHOUT removing or re-adding anything. | I9: The basket has RE-PRICED to EUR 450.00 per unit, EUR 4,500.00 ex VAT. The existing basket picks up the new entitlement on read - the customer should not have to empty and rebuild it. | K9: Not Run
A10: CRP-002 | B10: Cart & Cart Repricing | C10: Approve the trade account and re-price the existing basket | D10: Critical | G10: 3 | H10: Refresh the basket page. | I10: Still EUR 450.00. | K10: Not Run
A11: CRP-002 | B11: Cart & Cart Repricing | C11: Approve the trade account and re-price the existing basket | D11: Critical | G11: 4 | H11: Proceed to checkout. | I11: EUR 450.00 per unit, EUR 4,500.00 ex VAT, VAT EUR 1,035.00, total EUR 5,535.00 inc VAT. | K11: Not Run
A12: CRP-002 | B12: Cart & Cart Repricing | C12: Approve the trade account and re-price the existing basket | D12: Critical | G12: 5 | H12: Return to the basket and change the quantity to 25. | I12: Re-prices to EUR 420.00 per unit, EUR 10,500.00 ex VAT. | K12: Not Run
A13: CRP-002 | B13: Cart & Cart Repricing | C13: Approve the trade account and re-price the existing basket | D13: Critical | G13: 6 | H13: Set the quantity back to 10. | I13: Returns to EUR 450.00 per unit. | K13: Not Run
A14: CRP-003 | B14: Cart & Cart Repricing | C14: Suspend the account and re-price the existing basket | D14: Critical | E14: CRP-002 done - basket holds 10 units at the band price. | F14: Suspend the account, then refresh the basket. | G14: 1 | H14: In admin, suspend the ACCOUNT for trade.cart01@example.com. | I14: Account status = suspended. | K14: Not Run
A15: CRP-003 | B15: Cart & Cart Repricing | C15: Suspend the account and re-price the existing basket | D15: Critical | G15: 2 | H15: As the customer, refresh the basket. | I15: RE-PRICED to EUR 505.00 per unit, EUR 5,050.00 ex VAT. Trade pricing is withdrawn from the existing basket. | K15: Not Run
A16: CRP-003 | B16: Cart & Cart Repricing | C16: Suspend the account and re-price the existing basket | D16: Critical | G16: 3 | H16: Attempt to check out. | I16: Refused - a suspended account cannot place an order. | K16: Not Run
A17: CRP-003 | B17: Cart & Cart Repricing | C17: Suspend the account and re-price the existing basket | D17: Critical | G17: 4 | H17: In admin, return the account to Active. | I17: Account active again. | K17: Not Run
A18: CRP-003 | B18: Cart & Cart Repricing | C18: Suspend the account and re-price the existing basket | D18: Critical | G18: 5 | H18: Refresh the basket. | I18: Back to EUR 450.00 per unit. | K18: Not Run
A19: CRP-003 | B19: Cart & Cart Repricing | C19: Suspend the account and re-price the existing basket | D19: Critical | G19: 6 | H19: Now suspend the TRADE STATUS instead (leaving the account active) and refresh the basket. | I19: Re-priced to EUR 505.00 per unit, but checkout IS allowed - at retail. | K19: Not Run
A20: CRP-003 | B20: Cart & Cart Repricing | C20: Suspend the account and re-price the existing basket | D20: Critical | G20: 7 | H20: Restore the trade status to approved. | I20: Basket returns to EUR 450.00. | K20: Not Run
A21: CRP-004 | B21: Cart & Cart Repricing | C21: The basket price survives sign-out, sign-in and another browser | D21: High | E21: CRP-003 done - approved, basket holds 10 units at EUR 450.00. | F21: Same account in a second browser. | G21: 1 | H21: Sign out and sign back in, then open the basket. | I21: Still 10 units at EUR 450.00 per unit. | K21: Not Run
A22: CRP-004 | B22: Cart & Cart Repricing | C22: The basket price survives sign-out, sign-in and another browser | D22: High | G22: 2 | H22: Open a different browser (or a private window), sign in as the same customer and open the basket. | I22: The same 10 units at EUR 450.00. The basket belongs to the account, not to one browser. | K22: Not Run
A23: CRP-004 | B23: Cart & Cart Repricing | C23: The basket price survives sign-out, sign-in and another browser | D23: High | G23: 3 | H23: Change the quantity to 15 in the second browser. | I23: EUR 430.00 per unit there. | K23: Not Run
A24: CRP-004 | B24: Cart & Cart Repricing | C24: The basket price survives sign-out, sign-in and another browser | D24: High | G24: 4 | H24: Return to the first browser and refresh the basket. | I24: Shows 15 units at EUR 430.00 - the change made elsewhere is reflected on refresh. | K24: Not Run
A25: CRP-004 | B25: Cart & Cart Repricing | C25: The basket price survives sign-out, sign-in and another browser | D25: High | G25: 5 | H25: Set the quantity back to 10. | I25: EUR 450.00 per unit. | K25: Not Run
A26: CRP-005 | B26: Cart & Cart Repricing | C26: Remove and re-add a product | D26: Medium | E26: Basket holds 10 units at the band price. | F26: Remove, then re-add 10 units. | G26: 1 | H26: Remove the product from the basket. | I26: Basket is empty and the total is zero. | K26: Not Run
A27: CRP-005 | B27: Cart & Cart Repricing | C27: Remove and re-add a product | D27: Medium | G27: 2 | H27: Re-add 10 units of the same product. | I27: EUR 450.00 per unit again - the same figure as before removal. | K27: Not Run
A28: CRP-005 | B28: Cart & Cart Repricing | C28: Remove and re-add a product | D28: Medium | G28: 3 | H28: Add a SECOND, different product to the basket alongside it. | I28: The second product is priced by its OWN rules. If it has no bands, it is at retail even for an entitled account. Record both lines. | K28: Not Run
A29: CRP-005 | B29: Cart & Cart Repricing | C29: Remove and re-add a product | D29: Medium | G29: 4 | H29: Check the basket subtotal. | I29: The subtotal is the sum of the two correctly-priced lines. | K29: Not Run
A30: CRP-005 | B30: Cart & Cart Repricing | C30: Remove and re-add a product | D30: Medium | G30: 5 | H30: Remove the second product. | I30: Only the first line remains, still at EUR 450.00 per unit. | K30: Not Run
A31: CRP-006 | B31: Cart & Cart Repricing | C31: A price sent with an add-to-basket request is ignored | D31: Critical | E31: Signed in as an entitled account. Developer tools available. | F31: POST {storefront}/api/v1/cart/action with a forged price | G31: 1 | H31: Open developer tools, network tab. Add a product to the basket and find the request. | I31: The add-to-basket request is visible. | K31: Not Run
A32: CRP-006 | B32: Cart & Cart Repricing | C32: A price sent with an add-to-basket request is ignored | D32: Critical | G32: 2 | H32: Resend the request with a "price" field of 1.00 injected into the payload. | I32: The basket line is priced by the SERVER at the correct figure - EUR 450.00 at quantity 10, or EUR 505.00 at quantity 1. The injected price is ignored. | K32: Not Run
A33: CRP-006 | B33: Cart & Cart Repricing | C33: A price sent with an add-to-basket request is ignored | D33: Critical | G33: 3 | H33: Open the basket and read the unit price. | I33: The correct server price, not EUR 1.00. | K33: Not Run
A34: CRP-006 | B34: Cart & Cart Repricing | C34: A price sent with an add-to-basket request is ignored | D34: Critical | G34: 4 | H34: Proceed to checkout. | I34: The correct figure again. | K34: Not Run
A35: CRP-006 | B35: Cart & Cart Repricing | C35: A price sent with an add-to-basket request is ignored | D35: Critical | G35: 5 | H35: Try the same with "final_price", "wholesale_price" and "discount" field names. | I35: All ignored. The basket price is never taken from the browser. | K35: Not Run
A36: CRP-007 | B36: Cart & Cart Repricing | C36: A tampered basket row is re-priced on read | D36: Critical | E36: Signed in as an entitled account with a basket. Ask the dev team to edit the stored basket row price directly in the database, or use an API call that attempts it. | F36: Stored basket price altered to 1.00 | G36: 1 | H36: Note the current basket line price. | I36: EUR 450.00 per unit at quantity 10. | K36: Not Run
A37: CRP-007 | B37: Cart & Cart Repricing | C37: A tampered basket row is re-priced on read | D37: Critical | G37: 2 | H37: Have the stored basket row price changed directly to 1.00 in the database. | I37: The stored value is now wrong. | K37: Not Run
A38: CRP-007 | B38: Cart & Cart Repricing | C38: A tampered basket row is re-priced on read | D38: Critical | G38: 3 | H38: As the customer, refresh the basket. | I38: The basket shows EUR 450.00 - the price is RE-DERIVED on read, so a tampered stored value does not survive. | K38: Not Run
A39: CRP-007 | B39: Cart & Cart Repricing | C39: A tampered basket row is re-priced on read | D39: Critical | G39: 4 | H39: Proceed to checkout. | I39: EUR 450.00 per unit, EUR 4,500.00 ex VAT. | K39: Not Run
A40: CRP-007 | B40: Cart & Cart Repricing | C40: A tampered basket row is re-priced on read | D40: Critical | G40: 5 | H40: Place the order and check the order total. | I40: EUR 4,500.00 ex VAT. The customer is charged the correct amount, not the tampered one. | K40: Not Run
A41: CRP-008 | B41: Cart & Cart Repricing | C41: Editing the price in the browser does not change what is charged | D41: Critical | E41: Signed in as an entitled account with 10 units in the basket. | F41: Edit the displayed price in dev tools. | G41: 1 | H41: Open the basket. In developer tools, use Edit as HTML to change the displayed unit price from EUR 450.00 to EUR 1.00. | I41: The page now DISPLAYS EUR 1.00 - this only changes your own screen. | K41: Not Run
A42: CRP-008 | B42: Cart & Cart Repricing | C42: Editing the price in the browser does not change what is charged | D42: Critical | G42: 2 | H42: Click through to checkout WITHOUT refreshing. | I42: Checkout shows the real figure of EUR 450.00 per unit, EUR 4,500.00 ex VAT. The server recalculates. | K42: Not Run
A43: CRP-008 | B43: Cart & Cart Repricing | C43: Editing the price in the browser does not change what is charged | D43: Critical | G43: 3 | H43: Place the order. | I43: The order total is the real EUR 4,500.00 ex VAT plus VAT. Verify the amount in admin. | K43: Not Run
A44: CRP-008 | B44: Cart & Cart Repricing | C44: Editing the price in the browser does not change what is charged | D44: Critical | G44: 4 | H44: Repeat, editing the QUANTITY in the DOM rather than the price. | I44: The quantity charged is the quantity the server has, and the price matches that quantity's band. | K44: Not Run
A45: CRP-008 | B45: Cart & Cart Repricing | C45: Editing the price in the browser does not change what is charged | D45: Critical | G45: 5 | H45: Repeat, editing the displayed VAT figure. | I45: The VAT charged is recalculated by the server, not taken from the page. | K45: Not Run
A46: CRP-009 | B46: Cart & Cart Repricing | C46: Quantity validation in the basket | D46: High | E46: Signed in with a basket. | F46: Quantities: 0 | -5 | 1.5 | 999999 | abc | G46: 1 | H46: Set the basket quantity to 0. | I46: Either the line is removed or the change is refused with a clear message. It must not result in a zero-priced line that can be ordered. | K46: Not Run
A47: CRP-009 | B47: Cart & Cart Repricing | C47: Quantity validation in the basket | D47: High | G47: 2 | H47: Set the quantity to -5. | I47: REFUSED. A negative quantity must never produce a negative line total or a credit. | K47: Not Run
A48: CRP-009 | B48: Cart & Cart Repricing | C48: Quantity validation in the basket | D48: High | G48: 3 | H48: Set the quantity to 1.5. | I48: Refused, or rounded to a whole number. Record which. | K48: Not Run
A49: CRP-009 | B49: Cart & Cart Repricing | C49: Quantity validation in the basket | D49: High | G49: 4 | H49: Set the quantity to 999999. | I49: Either refused as beyond a sane limit, or accepted subject to stock. It must not cause a server error or an arithmetic overflow. | K49: Not Run
A50: CRP-009 | B50: Cart & Cart Repricing | C50: Quantity validation in the basket | D50: High | G50: 5 | H50: Type "abc" into the quantity field. | I50: Refused with a clear message; no server error. | K50: Not Run
A51: CRP-009 | B51: Cart & Cart Repricing | C51: Quantity validation in the basket | D51: High | G51: 6 | H51: Set the quantity back to 10. | I51: EUR 450.00 per unit. | K51: Not Run
A52: CRP-010 | B52: Cart & Cart Repricing | C52: A guest basket that lands on an entitled account re-prices | D52: High | E52: Signed out. An entitled Business account available to sign in to. | F52: Guest basket then sign in. | G52: 1 | H52: Signed out, add 10 units of 'testing product' (product ID 99240288, slug testing-product, retail EUR 505.00 ex VAT) to the basket as a guest. | I52: Added at RETAIL EUR 505.00 per unit - a guest gets no bands. | K52: Not Run
A53: CRP-010 | B53: Cart & Cart Repricing | C53: A guest basket that lands on an entitled account re-prices | D53: High | G53: 2 | H53: Confirm the guest basket total. | I53: EUR 5,050.00 ex VAT. | K53: Not Run
A54: CRP-010 | B54: Cart & Cart Repricing | C54: A guest basket that lands on an entitled account re-prices | D54: High | G54: 3 | H54: Now sign in as the BUSINESS account business.test01@example.com. | I54: Sign-in succeeds and the guest basket is carried onto the account. | K54: Not Run
A55: CRP-010 | B55: Cart & Cart Repricing | C55: A guest basket that lands on an entitled account re-prices | D55: High | G55: 4 | H55: Open the basket. | I55: RE-PRICED to EUR 450.00 per unit, EUR 4,500.00 ex VAT - the account's entitlement now applies. | K55: Not Run
A56: CRP-010 | B56: Cart & Cart Repricing | C56: A guest basket that lands on an entitled account re-prices | D56: High | G56: 5 | H56: Sign out, build a guest basket again, then sign in as a PERSONAL account. | I56: The basket stays at retail EUR 505.00 - a personal account earns no band. | K56: Not Run
A57: CRP-011 | B57: Cart & Cart Repricing | C57: The basket reacts to a product price change | D57: Medium | E57: Admin access to change a product price. Basket holds the product. | F57: Change the retail price in admin. | G57: 1 | H57: With 10 units in an entitled customer's basket at EUR 450.00, note the total. | I57: EUR 4,500.00 ex VAT. | K57: Not Run
A58: CRP-011 | B58: Cart & Cart Repricing | C58: The basket reacts to a product price change | D58: Medium | G58: 2 | H58: In admin, reduce the product RETAIL price to EUR 400.00 (below the band price) and save. | I58: Saved. | K58: Not Run
A59: CRP-011 | B59: Cart & Cart Repricing | C59: The basket reacts to a product price change | D59: Medium | G59: 3 | H59: As the customer, refresh the basket. | I59: The unit price is now EUR 400.00, NOT EUR 450.00 - a band never charges above the prevailing retail price, so the cap now binds. | K59: Not Run
A60: CRP-011 | B60: Cart & Cart Repricing | C60: The basket reacts to a product price change | D60: Medium | G60: 4 | H60: Restore the retail price to EUR 505.00. | I60: Saved. | K60: Not Run
A61: CRP-011 | B61: Cart & Cart Repricing | C61: The basket reacts to a product price change | D61: Medium | G61: 5 | H61: Refresh the basket. | I61: Back to EUR 450.00 per unit. | K61: Not Run

Sheet VAT & Tax
A1: VAT & Tax
A2: VAT in this application is decided PER PRODUCT (an excludeVAT flag plus a tax rule), NOT by the customer country and NOT by whether a VAT number was supplied. There is no reverse-charge or zero-rating logic. The test product uses tax rule VAT23 at 23%.
A3: Test Case ID | B3: Module | C3: Test Scenario | D3: Priority | E3: Preconditions | F3: Test Data | G3: Step No. | H3: Action / Steps | I3: Expected Result | J3: Actual Result | K3: Status | L3: Severity | M3: Bug ID | N3: Tester Comments
A4: VAT-001 | B4: VAT & Tax | C4: Confirm the tax configuration before testing | D4: High | E4: Admin access. | F4: Tax rules: VAT23 = 23% percentage; VAT Margin = 0%. | G4: 1 | H4: In admin, open the tax rules configuration. | I4: At least two rules exist: VAT23 at 23% (percentage) and VAT Margin at 0%. | K4: Not Run
A5: VAT-001 | B5: VAT & Tax | C5: Confirm the tax configuration before testing | D5: High | G5: 2 | H5: Open 'testing product' (product ID 99240288, slug testing-product, retail EUR 505.00 ex VAT) in admin and check its tax settings. | I5: The product is taxable (VAT is not excluded) and uses tax rule VAT23. | K5: Not Run
A6: VAT-001 | B6: VAT & Tax | C6: Confirm the tax configuration before testing | D6: High | G6: 3 | H6: Find a SECOND product that uses a different tax rule, or is VAT-excluded. | I6: Record its id, name, price and rule - it is needed for the mixed-basket case. If no such product exists, ask the dev team to configure one or mark the mixed cases Not Applicable. | K6: Not Run
A7: VAT-001 | B7: VAT & Tax | C7: Confirm the tax configuration before testing | D7: High | G7: 4 | H7: Confirm the VAT rate is NOT hardcoded at 23% for every product. | I7: Different products can carry different rules. Do not assume one rate applies everywhere. | K7: Not Run
A8: VAT-002 | B8: VAT & Tax | C8: VAT on the retail price for a non-entitled account | D8: Critical | E8: Signed in as a PERSONAL account, or signed out as a guest. | F8: Quantity 1 and 10 of the test product. | G8: 1 | H8: Add 1 unit to the basket and read the ex-VAT price, the VAT and the inc-VAT total. | I8: EUR 505.00 ex VAT, VAT EUR 116.15, EUR 621.15 inc VAT. | K8: Not Run
A9: VAT-002 | B9: VAT & Tax | C9: VAT on the retail price for a non-entitled account | D9: Critical | G9: 2 | H9: Change the quantity to 10. | I9: EUR 5,050.00 ex VAT, VAT EUR 1,161.50, EUR 6,211.50 inc VAT. | K9: Not Run
A10: VAT-002 | B10: VAT & Tax | C10: VAT on the retail price for a non-entitled account | D10: Critical | G10: 3 | H10: Verify the VAT arithmetic yourself. | I10: 5,050.00 x 0.23 = 1,161.50. The displayed VAT matches. | K10: Not Run
A11: VAT-002 | B11: VAT & Tax | C11: VAT on the retail price for a non-entitled account | D11: Critical | G11: 4 | H11: Open checkout. | I11: The same three figures as the basket. | K11: Not Run
A12: VAT-003 | B12: VAT & Tax | C12: VAT is charged on the BAND price, not the retail price | D12: Critical | E12: Signed in as an entitled account (business, or approved trade). | F12: Quantity 10 - band price EUR 450.00 | G12: 1 | H12: Add 10 units to the basket. | I12: EUR 450.00 per unit, EUR 4,500.00 ex VAT. | K12: Not Run
A13: VAT-003 | B13: VAT & Tax | C13: VAT is charged on the BAND price, not the retail price | D13: Critical | G13: 2 | H13: Read the VAT figure in the basket. | I13: EUR 1,035.00 - that is 23% of EUR 4,500.00, the BAND price. It must NOT be EUR 1,161.50 (23% of retail). | K13: Not Run
A14: VAT-003 | B14: VAT & Tax | C14: VAT is charged on the BAND price, not the retail price | D14: Critical | G14: 3 | H14: Read the inc-VAT total. | I14: EUR 5,535.00. | K14: Not Run
A15: VAT-003 | B15: VAT & Tax | C15: VAT is charged on the BAND price, not the retail price | D15: Critical | G15: 4 | H15: Open checkout and compare all three figures. | I15: Identical: EUR 4,500.00 ex VAT, EUR 1,035.00 VAT, EUR 5,535.00 inc VAT. | K15: Not Run
A16: VAT-003 | B16: VAT & Tax | C16: VAT is charged on the BAND price, not the retail price | D16: Critical | G16: 5 | H16: Change the quantity to 25. | I16: EUR 10,500.00 ex VAT, VAT EUR 2,415.00, EUR 12,915.00 inc VAT. | K16: Not Run
A17: VAT-003 | B17: VAT & Tax | C17: VAT is charged on the BAND price, not the retail price | D17: Critical | G17: 6 | H17: Verify the arithmetic. | I17: 10,500.00 x 0.23 = 2,415.00. Charging VAT on the retail figure would overcharge the customer - a critical defect if seen. | K17: Not Run
A18: VAT-004 | B18: VAT & Tax | C18: A basket with products on different tax rules | D18: High | E18: VAT-001 identified a second product with a different rule. If none exists, mark Not Applicable. | F18: Test product (VAT23) + second product (different rule). | G18: 1 | H18: Add 10 units of the test product and 1 of the second product to the basket. | I18: Both lines are shown. | K18: Not Run
A19: VAT-004 | B19: VAT & Tax | C19: A basket with products on different tax rules | D19: High | G19: 2 | H19: Read the VAT attributed to each line. | I19: Each line is taxed by ITS OWN rule. The test product line is taxed at 23%; the second at its own rate. | K19: Not Run
A20: VAT-004 | B20: VAT & Tax | C20: A basket with products on different tax rules | D20: High | G20: 3 | H20: Read the basket VAT total. | I20: It is the SUM of the per-line VAT figures, not a single 23% applied to the whole subtotal. | K20: Not Run
A21: VAT-004 | B21: VAT & Tax | C21: A basket with products on different tax rules | D21: High | G21: 4 | H21: Verify the arithmetic line by line. | I21: Each line total matches its own rule. A single blanket rate across a mixed basket is a defect. | K21: Not Run
A22: VAT-004 | B22: VAT & Tax | C22: A basket with products on different tax rules | D22: High | G22: 5 | H22: Open checkout and compare. | I22: The same per-line and total VAT figures. | K22: Not Run
A23: VAT-005 | B23: VAT & Tax | C23: A VAT-excluded product is not taxed | D23: High | E23: A product flagged to exclude VAT. If none exists, ask the dev team to flag one or mark Not Applicable. | F23: VAT-excluded product. | G23: 1 | H23: Add the VAT-excluded product to the basket on its own. | I23: The line shows NO VAT. | K23: Not Run
A24: VAT-005 | B24: VAT & Tax | C24: A VAT-excluded product is not taxed | D24: High | G24: 2 | H24: Read the basket total. | I24: The inc-VAT total equals the ex-VAT total for this line - nothing is added. | K24: Not Run
A25: VAT-005 | B25: VAT & Tax | C25: A VAT-excluded product is not taxed | D25: High | G25: 3 | H25: Add the VAT23 test product alongside it. | I25: Only the taxable line attracts VAT. The excluded line still shows none. | K25: Not Run
A26: VAT-005 | B26: VAT & Tax | C26: A VAT-excluded product is not taxed | D26: High | G26: 4 | H26: Check this holds for an ENTITLED account with a band price too. | I26: A band price on a VAT-excluded product is still untaxed. The band and the VAT flag are independent. | K26: Not Run
A27: VAT-005 | B27: VAT & Tax | C27: A VAT-excluded product is not taxed | D27: High | G27: 5 | H27: Open checkout. | I27: Same treatment. | K27: Not Run
A28: VAT-006 | B28: VAT & Tax | C28: VAT carries correctly through order and invoice | D28: Critical | E28: Signed in as an entitled account. | F28: Quantity 10, PO-2026-00125 | G28: 1 | H28: Add 10 units, go to checkout and record the ex-VAT, VAT and inc-VAT figures. | I28: EUR 4,500.00 / EUR 1,035.00 / EUR 5,535.00. | K28: Not Run
A29: VAT-006 | B29: VAT & Tax | C29: VAT carries correctly through order and invoice | D29: Critical | G29: 2 | H29: Place the order and read the order confirmation. | I29: The same three figures. | K29: Not Run
A30: VAT-006 | B30: VAT & Tax | C30: VAT carries correctly through order and invoice | D30: Critical | G30: 3 | H30: Open the order in the customer order history. | I30: The same three figures. | K30: Not Run
A31: VAT-006 | B31: VAT & Tax | C31: VAT carries correctly through order and invoice | D31: Critical | G31: 4 | H31: Open the order in admin. | I31: The same three figures. | K31: Not Run
A32: VAT-006 | B32: VAT & Tax | C32: VAT carries correctly through order and invoice | D32: Critical | G32: 5 | H32: Open the invoice. | I32: The same three figures. Any disagreement between checkout, order and invoice is a critical defect. | K32: Not Run
A33: VAT-006 | B33: VAT & Tax | C33: VAT carries correctly through order and invoice | D33: Critical | G33: 6 | H33: Check the VAT number printed on the invoice. | I33: The customer's own VAT number is shown - IE1234567A for the business account, IE7654321B for the trade account. | K33: Not Run
A34: VAT-007 | B34: VAT & Tax | C34: VAT is not changed by the customer's VAT number or country | D34: High | E34: Two entitled accounts: one with a VAT number, one without (edit the profile to clear it if needed). | F34: Same product and quantity for both. | G34: 1 | H34: As an entitled account WITH a VAT number, add 10 units and record the VAT charged. | I34: EUR 1,035.00. | K34: Not Run
A35: VAT-007 | B35: VAT & Tax | C35: VAT is not changed by the customer's VAT number or country | D35: High | G35: 2 | H35: As an entitled account WITHOUT a VAT number, add 10 units and record the VAT charged. | I35: EUR 1,035.00 - the SAME. VAT is decided per product, not by whether the customer supplied a VAT number. | K35: Not Run
A36: VAT-007 | B36: VAT & Tax | C36: VAT is not changed by the customer's VAT number or country | D36: High | G36: 3 | H36: Change a billing address to a non-Irish country and re-check the VAT. | I36: UNCHANGED. Country-based VAT and EU reverse-charge are Not Available / Not Implemented. Mark this step Not Applicable rather than Fail. | K36: Not Run
A37: VAT-007 | B37: VAT & Tax | C37: VAT is not changed by the customer's VAT number or country | D37: High | G37: 4 | H37: Record the finding for the business. | I37: Note in Tester Comments that cross-border VAT treatment is not implemented, so it cannot be relied on. | K37: Not Run
A38: VAT-008 | B38: VAT & Tax | C38: VAT with a discount or voucher applied | D38: High | E38: A working voucher or discount code. If none is configured, mark Not Applicable. | F38: Voucher applied to an entitled basket. | G38: 1 | H38: Build a basket of 10 units at the band price and note the figures. | I38: EUR 4,500.00 ex VAT, VAT EUR 1,035.00. | K38: Not Run
