Workbook

Sheet Cover
B2: FixMyPC - Master Test Case Suite
B4: Laravel 8 API + Nuxt admin panel and storefront - multi-vendor e-commerce platform
B6: Document | C6: Master Test Case Suite
B7: Version | C7: 1
B8: Prepared | C8: 09 Sep 2026
B9: Total test cases | C9: 642
B10: Application under test | C10: FixMyPC (Laravel 8 REST API, Nuxt admin-panel, Nuxt frontend-panel)
B11: Scope | C11: Authentication, RBAC, catalogue, inventory, pricing and promotions, vouchers, cart, checkout, payments, orders, wallet and loyalty, storefront, search, reviews, vendor and procurement, POS, CMS, settings, customer account, security, API, performance, responsive, accessibility, compatibility, localisation, database, error handling, installation and end-to-end journeys.
B12: Out of scope | C12: Third-party gateway internals, ISP and DNS infrastructure, and any module explicitly deferred by the release plan.
B14: HOW TO USE THIS WORKBOOK
B15: Test Cases | C15: The master sheet. One row per test case. Filters are on and the header row is frozen. Fill in Actual Result and Status as you execute; everything else is pre-written.
B16: Status values | C16: Not Executed / Pass / Fail / Blocked / Deferred / N-A. Pick from the dropdown - the Dashboard counts depend on these exact values.
B17: Priority | C17: High / Medium / Low - execution order. Run every High case before any Medium.
B18: Severity | C18: Blocker / Critical / Major / Minor - the business impact if the case fails. Any Blocker failure stops the release.
B19: Dashboard | C19: Live counts by status, priority, severity and module. It reads the Test Cases sheet directly, so it updates as you fill Status in.
B20: Defect Log | C20: Raise one row per failure. Reference the Test Case ID so a defect always traces back to a case.
B21: Test Data | C21: Shared accounts, cards, and reference values used across the suite. Set these up before the first cycle.
B22: Environments | C22: The browser, device and environment matrix the Environment column refers to.
B23: Traceability | C23: Module-level coverage summary - which areas are covered, by how many cases, and at what risk weighting.
B25: NOTE ON RISK-WEIGHTED CASES
B26: Cases whose Remarks cite a QA audit reference (for example ORD-01, PRC-03, PAY-01, SEC-03, STK-02) are regression checks against findings recorded in reference/qa/qa-audit-2026-09-09.html. They target known weak points in pricing reconciliation, payment verification, stock handling, order lifecycle and access control, and should be executed first in every cycle regardless of module order.

Sheet Test Cases
A1: Test Case ID | B1: Module | C1: Feature / Functionality | D1: Test Scenario | E1: Preconditions | F1: Test Steps | G1: Test Data | H1: Expected Result | I1: Actual Result | J1: Priority | K1: Severity | L1: Test Type | M1: Environment | N1: Status | O1: Remarks
A2: AUTH-001 | B2: Authentication | C2: Personal account registration | D2: Register a new Personal account with all valid details | E2: Storefront reachable; email not already in the users table | F2: 1. Open /register 2. Choose account type "Personal" 3. Enter name, email, phone and password 4. Tick the terms checkbox 5. Click Register | G2: name=John Tester; email=qa.personal01@example.com; phone=+447700900001; password=Passw0rdTest1 | H2: HTTP 200; account created; verification code emailed; user advanced to the verify step; users row stores a bcrypt hash, never plain text | J2: High | K2: Critical | L2: Functional / Positive | M2: Staging - Chrome 126 (Win 11) | N2: Not Executed
A3: AUTH-002 | B3: Authentication | C3: Business account registration | D3: Register a Business account supplying the company block | E3: Email not registered | F3: 1. Open /register 2. Choose "Business" 3. Fill the base fields 4. Fill company_name, sector, billing_address 5. Submit | G3: company_name=Acme Ltd; sector=Retail; billing_address=1 High St, London, E1 6AN | H3: Account created with account_type=business and the user_business_profiles row persisted | J3: High | K3: Major | L3: Functional / Positive | M3: Staging - Chrome 126 (Win 11) | N3: Not Executed
A4: AUTH-003 | B4: Authentication | C4: Trade account registration | D4: Register a Trade account supplying the full trade block | E4: Email not registered | F4: 1. Open /register 2. Choose "Trade" 3. Fill base plus company_name, trade, vat_number, billing_address, expected_spend 4. Tick the resale confirmation 5. Submit | G4: vat_number=GB123456789; trade=IT Services; expected_spend=25000 | H4: Trade application created in pending state; account_type=trade; the record appears under Admin > Trade Applications | J4: High | K4: Major | L4: Functional / Positive | M4: Staging - Chrome 126 (Win 11) | N4: Not Executed
A5: AUTH-004 | B5: Authentication | C5: Registration - required fields | D5: Submit the registration form completely blank | E5: On /register | F5: 1. Open /register 2. Click Register without entering anything | G5: all fields empty | H5: Inline errors on name, email, phone, account_type, password and terms; no user row is created | J5: High | K5: Major | L5: Validation / Negative | M5: Staging - Chrome 126 (Win 11) | N5: Not Executed
A6: AUTH-005 | B6: Authentication | C6: Registration - email format | D6: Reject malformed email addresses | E6: On /register | F6: 1. Enter each malformed value in the email field 2. Submit | G6: plainaddress | qa@ | @example.com | qa@@example.com | qa me@example.com | qa@example | H6: "Enter a valid email" is shown for every value; no account is created | J6: High | K6: Major | L6: Validation / Negative | M6: Staging - Chrome 126 (Win 11) | N6: Not Executed
A7: AUTH-006 | B7: Authentication | C7: Registration - password strength | D7: Password must be at least 10 chars with a capital and a digit | E7: On /register | F7: 1. Try each password value in turn 2. Submit | G7: Short1 | alllowercase1 | ALLUPPERCASE1 | NoDigitsHere | Passw0rdTest1 | H7: The first four are rejected with "Use at least 10 characters, with a capital letter and a number."; the last is accepted | J7: High | K7: Major | L7: Validation / Negative | M7: Staging - Chrome 126 (Win 11) | N7: Not Executed
A8: AUTH-007 | B8: Authentication | C8: Registration - password boundary | D8: Exactly 9 / 10 / 11 characters with capital plus digit | E8: On /register | F8: 1. Submit each password value in turn | G8: Passwor1A (9) | Password1A (10) | Password12A (11) | H8: 9 chars rejected; 10 and 11 accepted - confirms min:10 is inclusive | J8: Medium | K8: Minor | L8: Boundary | M8: Staging - Chrome 126 (Win 11) | N8: Not Executed
A9: AUTH-008 | B9: Authentication | C9: Registration - duplicate email | D9: Register twice with the same email address | E9: qa.personal01@example.com already registered | F9: 1. Register again using the same email | G9: email=qa.personal01@example.com | H9: Rejected with a duplicate-email message; exactly one users row exists | J9: High | K9: Major | L9: Negative | M9: Staging - Chrome 126 (Win 11) | N9: Not Executed
A10: AUTH-009 | B10: Authentication | C10: Registration - duplicate email casing | D10: Same address supplied in a different letter case | E10: qa.personal01@example.com exists | F10: 1. Register with QA.Personal01@Example.com | G10: QA.Personal01@Example.com | H10: Treated as the same account and rejected - email matching must be case-insensitive | J10: Medium | K10: Major | L10: Negative / Edge | M10: Staging - Chrome 126 (Win 11) | N10: Not Executed
A11: AUTH-010 | B11: Authentication | C11: Registration - terms checkbox | D11: Submit without accepting the terms | E11: All other fields valid | F11: 1. Fill the form 2. Leave the terms box unticked 3. Submit | G11: terms=unchecked | H11: "Tick the box to continue." is shown and registration is blocked | J11: Medium | K11: Minor | L11: Validation / Negative | M11: Staging - Chrome 126 (Win 11) | N11: Not Executed
A12: AUTH-011 | B12: Authentication | C12: Trade - resale confirmation | D12: Trade signup without resale_confirmed | E12: Account type set to Trade | F12: 1. Fill the trade fields 2. Leave the resale confirmation unticked 3. Submit | G12: resale_confirmed=false | H12: "Trade accounts need this confirmation." is shown; signup blocked | J12: Medium | K12: Minor | L12: Validation / Negative | M12: Staging - Chrome 126 (Win 11) | N12: Not Executed
A13: AUTH-012 | B13: Authentication | C13: Registration - account_type whitelist | D13: Post an account_type outside the allowed set | E13: API client with an otherwise valid payload | F13: 1. POST /api/user/signup with account_type=superadmin | G13: account_type=superadmin | H13: Validation error - only personal, business and trade are accepted; no privileged account is created | J13: High | K13: Critical | L13: Security / Negative | M13: Staging - Postman / REST client | N13: Not Executed | O13: Mass-assignment probe
A14: AUTH-013 | B14: Authentication | C14: Registration - field length limits | D14: Very long values in name and email | E14: On /register | F14: 1. Paste a 300-character name and a 250-character local part 2. Submit | G14: name = A x300; email = <250 chars>@example.com | H14: Values are rejected or safely truncated to the column width; no HTTP 500 and no SQL truncation warning | J14: Medium | K14: Minor | L14: Boundary / Negative | M14: Staging - Chrome 126 (Win 11) | N14: Not Executed
A15: AUTH-014 | B15: Authentication | C15: Registration - script injection | D15: HTML/JS payload in the name field | E15: On /register | F15: 1. Enter the payload as the name 2. Register 3. View the name in the profile and in the admin user list | G15: name=<script>alert(1)</script> | H15: The value is stored escaped and rendered as literal text in both storefront and admin; no alert fires | J15: High | K15: Critical | L15: Security / XSS | M15: Staging - Chrome 126 (Win 11) | N15: Not Executed
A16: AUTH-015 | B16: Authentication | C16: Email verification code | D16: Verify a new account with the emailed code | E16: Account registered and code sent | F16: 1. Read the code from the inbox 2. Enter it on the verify screen 3. Submit | G16: code = value from email | H16: Account is marked verified and the user is signed in or sent to login | J16: High | K16: Critical | L16: Functional / Positive | M16: Staging - Chrome 126 (Win 11) | N16: Not Executed
A17: AUTH-016 | B17: Authentication | C17: Email verification - wrong code | D17: Enter an incorrect verification code | E17: Account awaiting verification | F17: 1. Enter a wrong 4-6 digit code 2. Submit | G17: code=0000 | H17: Rejected with a generic error; the account stays unverified | J17: High | K17: Major | L17: Negative | M17: Staging - Chrome 126 (Win 11) | N17: Not Executed
A18: AUTH-017 | B18: Authentication | C18: Verification code brute force | D18: Repeatedly guess the verification code | E18: Account awaiting verification | F18: 1. POST /api/user/verify 25 times with different codes within one minute | G18: codes 0000 to 0024 | H18: Attempts are throttled or locked after a small number of failures and the code is invalidated - guessing must not be unlimited | J18: High | K18: Critical | L18: Security / Negative | M18: Staging - Postman / REST client | N18: Not Executed | O18: QA audit flagged codes as brute-forceable; regression check
A19: AUTH-018 | B19: Authentication | C19: Verification code expiry | D19: Use a code after its validity window | E19: Code issued longer ago than the configured TTL | F19: 1. Wait past the TTL 2. Submit the old code | G19: stale code | H19: Rejected as expired; a fresh code can be requested | J19: Medium | K19: Major | L19: Negative / Boundary | M19: Staging - Chrome 126 (Win 11) | N19: Not Executed
A20: AUTH-019 | B20: Authentication | C20: Login with valid credentials | D20: Sign in as a verified customer | E20: Verified account exists | F20: 1. Open /login 2. Enter email and password 3. Submit | G20: qa.personal01@example.com / Passw0rdTest1 | H20: HTTP 200; a Passport token carrying the user scope is returned; the user lands on the dashboard and the header shows the account menu | J20: High | K20: Critical | L20: Functional / Positive | M20: Staging - Chrome 126 (Win 11) | N20: Not Executed
A21: AUTH-020 | B21: Authentication | C21: Login with wrong password | D21: Sign in with a bad password | E21: Account exists | F21: 1. Enter a valid email with the wrong password 2. Submit | G21: qa.personal01@example.com / WrongPass99 | H21: Generic invalid-credentials error; no token issued; the message does not reveal whether the email exists | J21: High | K21: Critical | L21: Negative / Security | M21: Staging - Chrome 126 (Win 11) | N21: Not Executed
A22: AUTH-021 | B22: Authentication | C22: Login - unknown email | D22: Sign in with an email that is not registered | E22: No matching account | F22: 1. Enter an unregistered email with any password 2. Submit | G22: nobody@example.com / Passw0rdTest1 | H22: The same generic error and a comparable response time as AUTH-020 - no account enumeration | J22: High | K22: Major | L22: Security / Negative | M22: Staging - Chrome 126 (Win 11) | N22: Not Executed
A23: AUTH-022 | B23: Authentication | C23: Login - unverified account | D23: Sign in before verifying the email | E23: Account registered but not verified | F23: 1. Attempt to log in | G23: unverified account | H23: Blocked with a verify-your-email prompt and an option to resend the code | J23: Medium | K23: Major | L23: Negative | M23: Staging - Chrome 126 (Win 11) | N23: Not Executed
A24: AUTH-023 | B24: Authentication | C24: Login - deactivated account | D24: Sign in to a deactivated or blocked account | E24: Admin has deactivated the account | F24: 1. Attempt to log in | G24: deactivated account | H24: Login refused with an account-disabled message; no token issued | J24: High | K24: Major | L24: Negative | M24: Staging - Chrome 126 (Win 11) | N24: Not Executed
A25: AUTH-024 | B25: Authentication | C25: Login - password minimum length | D25: Password shorter than the 6-character API rule | E25: API client available | F25: 1. POST /api/user/signin with a 5-character password | G25: password=Abc12 | H25: Validation error returned before any credential check runs | J25: Low | K25: Minor | L25: Validation / Boundary | M25: Staging - Postman / REST client | N25: Not Executed
A26: AUTH-025 | B26: Authentication | C26: Login rate limiting | D26: Repeated failed logins from one client | E26: Account exists | F26: 1. Submit 20 wrong passwords for the same email within a minute | G26: 20 x WrongPass | H26: Throttling or lockout applies (HTTP 429 or a cooldown message); the correct password still works after the cooldown | J26: High | K26: Critical | L26: Security / Performance | M26: Staging - Postman / REST client | N26: Not Executed
A27: AUTH-026 | B27: Authentication | C27: Login - SQL injection | D27: SQL payloads in the login fields | E27: Login page open | F27: 1. Enter the payload as the email and then as the password 2. Submit | G27: OR 1=1 -- ; admin'-- | H27: Treated as literal text; login fails; no SQL error surfaces and no session is created | J27: High | K27: Critical | L27: Security / Negative | M27: Staging - Chrome 126 (Win 11) | N27: Not Executed
A28: AUTH-027 | B28: Authentication | C28: Passwordless login code - send | D28: Request a one-time login code by email | E28: Verified account exists | F28: 1. POST /api/user/login-code with the email | G28: email=qa.personal01@example.com | H28: A code is emailed; the response does not disclose whether the address exists | J28: Medium | K28: Major | L28: Functional / Positive | M28: Staging - Postman / REST client | N28: Not Executed
A29: AUTH-028 | B29: Authentication | C29: Passwordless login code - verify | D29: Sign in using a valid one-time code | E29: Code just requested | F29: 1. POST /api/user/login-code/verify with email plus code | G29: email plus valid code | H29: A token is issued and the code is consumed - replaying the same code fails | J29: High | K29: Critical | L29: Functional / Positive | M29: Staging - Postman / REST client | N29: Not Executed
A30: AUTH-029 | B30: Authentication | C30: Login code - reuse | D30: Reuse an already-consumed login code | E30: Code used once in AUTH-028 | F30: 1. POST the same code a second time | G30: used code | H30: Rejected - single use is enforced | J30: High | K30: Major | L30: Negative / Security | M30: Staging - Postman / REST client | N30: Not Executed
... A37: AUTH-036 | B37: Authentication | C37: Forgot password - existing email | D37: Request a password reset link | E37: Account exists | F37: 1. Open /forgot-password 2. Enter the email 3. Submit | G37: qa.personal01@example.com | H37: A neutral confirmation is shown and a reset email with a single-use token is delivered | J37: High | K37: Major | L37: Functional / Positive | M37: Staging - Chrome 126 (Win 11) | N37: Not Executed
A38: AUTH-037 | B38: Authentication | C38: Forgot password - unknown email | D38: Request a reset for an address that does not exist | E38: No matching account | F38: 1. Submit an unregistered email | G38: nobody@example.com | H38: Identical wording and comparable timing to AUTH-036 - the response must not enumerate accounts | J38: High | K38: Major | L38: Security / Negative | M38: Staging - Chrome 126 (Win 11) | N38: Not Executed | O38: QA audit flagged reset-flow enumeration
A39: AUTH-038 | B39: Authentication | C39: Reset password - valid token | D39: Set a new password from the emailed link | E39: Reset token issued | F39: 1. Open the emailed link 2. Enter a new password twice 3. Submit | G39: password=NewPassw0rd1 | H39: The password is updated, the token is consumed, the old password stops working, and existing sessions are invalidated | J39: High | K39: Critical | L39: Functional / Positive | M39: Staging - Chrome 126 (Win 11) | N39: Not Executed
A40: AUTH-039 | B40: Authentication | C40: Reset password - token reuse or tamper | D40: Reuse or alter the reset token | E40: Token already used in AUTH-038 | F40: 1. Reopen the same link 2. Then open the link with one character changed | G40: used token; tampered token | H40: Both are rejected with "This reset link is not valid." | J40: High | K40: Critical | L40: Security / Negative | M40: Staging - Chrome 126 (Win 11) | N40: Not Executed
A41: AUTH-040 | B41: Authentication | C41: Reset password - expired token | D41: Use a reset token after its lifetime | E41: Token older than the configured expiry | F41: 1. Open the stale link 2. Submit a new password | G41: expired token | H41: Rejected as expired, with a way to request a fresh link | J41: Medium | K41: Major | L41: Negative / Boundary | M41: Staging - Chrome 126 (Win 11) | N41: Not Executed
A42: AUTH-041 | B42: Authentication | C42: Reset password - strength rule | D42: The new password must meet the 10/capital/digit rule | E42: Valid reset token | F42: 1. Try weak values, then a compliant one | G42: abc | Password1 (9) | Password1A (10) | H42: The first two are rejected with the strength message; the 10-character value is accepted | J42: Medium | K42: Major | L42: Validation / Boundary | M42: Staging - Chrome 126 (Win 11) | N42: Not Executed
A43: AUTH-042 | B43: Authentication | C43: Reset password - cross-account token | D43: Use the account A token with the account B email | E43: Tokens issued for two accounts | F43: 1. POST /reset-password with the A token and the B email | G43: A token plus B email | H43: Rejected - token binding is verified server-side | J43: High | K43: Critical | L43: Security / Negative | M43: Staging - Postman / REST client | N43: Not Executed
A44: AUTH-043 | B44: Authentication | C44: Change password when signed in | D44: Update the password from the account area | E44: Signed-in customer | F44: 1. Open profile security 2. Enter the current and new password 3. Save | G44: current=Passw0rdTest1; new=NewPassw0rd1 | H44: The password changes only when the current password is correct, and a confirmation is shown | J44: High | K44: Major | L44: Functional / Positive | M44: Staging - Chrome 126 (Win 11) | N44: Not Executed
A45: AUTH-044 | B45: Authentication | C45: Change password - wrong current | D45: Update using an incorrect current password | E45: Signed-in customer | F45: 1. Enter a wrong current password with a valid new one 2. Save | G45: current=Wrong123; new=NewPassw0rd1 | H45: Rejected; the stored password is unchanged | J45: High | K45: Critical | L45: Negative / Security | M45: Staging - Chrome 126 (Win 11) | N45: Not Executed
A46: AUTH-045 | B46: Authentication | C46: Social login - Google | D46: Sign in through the Google provider | E46: Google OAuth keys configured under Settings > Social login | F46: 1. Click Continue with Google 2. Complete the consent screen 3. Return through the callback | G46: Google test account | H46: The account is linked or created, the user is signed in, and the email is captured from the provider | J46: Medium | K46: Major | L46: Integration / Positive | M46: Staging - Chrome 126 (Win 11) | N46: Not Executed
A47: AUTH-046 | B47: Authentication | C47: Social login - other providers | D47: Sign in through each remaining enabled provider | E47: Provider keys configured | F47: 1. Repeat AUTH-045 for every enabled provider | G47: Facebook / Apple test accounts | H47: Each provider completes and lands on /social-callback with a valid session | J47: Medium | K47: Major | L47: Integration / Positive | M47: Staging - Chrome 126 (Win 11) | N47: Not Executed
A48: AUTH-047 | B48: Authentication | C48: Social login - user cancels | D48: Abandon the provider consent screen | E48: Provider configured | F48: 1. Start the social login 2. Cancel at the provider | G48: no consent given | H48: The user returns to /login with a friendly message and no partial account is created | J48: Medium | K48: Minor | L48: Negative / Error handling | M48: Staging - Chrome 126 (Win 11) | N48: Not Executed
A49: AUTH-048 | B49: Authentication | C49: Social login - email collision | D49: The provider email matches an existing password account | E49: A password account exists with the same address | F49: 1. Sign in socially using that address | G49: same email | H49: Accounts are linked deliberately, or the user is asked to sign in with a password - never a silent takeover | J49: High | K49: Critical | L49: Security / Edge | M49: Staging - Chrome 126 (Win 11) | N49: Not Executed
A50: AUTH-049 | B50: Authentication | C50: Social login - disabled provider | D50: The provider is switched off in settings | E50: Provider disabled in admin | F50: 1. Call /api/user/social/redirect/{service} | G50: service=google | H50: The request is refused and no button is rendered on the storefront | J50: Low | K50: Minor | L50: Negative | M50: Staging - Postman / REST client | N50: Not Executed
... A57: AUTH-056 | B57: Authentication | C57: Scope enforcement | D57: Use a customer token against an admin endpoint | E57: Valid user-scope token | F57: 1. GET /api/admin/dashboard with the user token | G57: user bearer token | H57: 401 or 403 - the scope:admin middleware rejects it and no admin data leaks | J57: High | K57: Blocker | L57: Security / Negative | M57: Staging - Postman / REST client | N57: Not Executed
A58: AUTH-057 | B58: Authentication | C58: Account deletion | D58: Delete the signed-in account | E58: Signed-in customer with no open orders | F58: 1. Request account deletion 2. Confirm | G58: confirmation | H58: The account is removed or anonymised, sessions are revoked, and personal data is no longer returned by any endpoint | J58: Medium | K58: Major | L58: Functional | M58: Staging - Chrome 126 (Win 11) | N58: Not Executed | O58: GDPR erasure path
A59: AUTH-058 | B59: Authentication | C59: Guest token issue | D59: Issue an anonymous guest token | E59: Fresh browser with no cookies | F59: 1. POST /api/v1/guest/token | G59: no credentials | H59: A server-generated, signed guest token is returned - never a value chosen by the client | J59: High | K59: Critical | L59: Security / Functional | M59: Staging - Postman / REST client | N59: Not Executed | O59: QA audit: guest identity was previously client-generated
A60: AUTH-059 | B60: Authentication | C60: Guest token forgery | D60: Present a hand-written guest token | E60: Guest endpoint reachable | F60: 1. Call a guest endpoint with guest_token set to an arbitrary string | G60: guest_token=aaaaaaaaaaaa | H60: Rejected by the guest.token middleware; no guest cart is created or read | J60: High | K60: Critical | L60: Security / Negative | M60: Staging - Postman / REST client | N60: Not Executed
A61: AUTH-060 | B61: Authentication | C61: Guest to customer cart merge | D61: Sign in after building a guest cart | E61: A guest cart holds two items | F61: 1. Add items as a guest 2. Sign in with an existing account 3. Open the cart | G61: 2 guest items plus 1 pre-existing account item | H61: Guest items merge into the account cart with correct quantities and no duplicate rows | J61: High | K61: Major | L61: Integration / E2E | M61: Staging - Chrome 126 (Win 11) | N61: Not Executed
A62: ADM-001 | B62: Admin Authentication | C62: Admin login | D62: Sign in to the admin panel with valid credentials | E62: An admin account exists with the superadmin role | F62: 1. Open /admin/login 2. Enter email and password 3. Submit | G62: admin@fixmypc.test / Admin@12345 | H62: HTTP 200; an admin-scope token is issued; the dashboard loads with the sidebar filtered by role | J62: High | K62: Critical | L62: Functional / Positive | M62: Staging - Chrome 126 (Win 11) | N62: Not Executed
A63: ADM-002 | B63: Admin Authentication | C63: Admin login - wrong password | D63: Sign in with an incorrect admin password | E63: Admin account exists | F63: 1. Enter the admin email with a wrong password 2. Submit | G63: admin@fixmypc.test / wrong | H63: Generic failure message; no token; the attempt is logged | J63: High | K63: Critical | L63: Negative / Security | M63: Staging - Chrome 126 (Win 11) | N63: Not Executed
A64: ADM-003 | B64: Admin Authentication | C64: Admin login validation | D64: Blank or malformed admin login fields | E64: On /admin/login | F64: 1. Submit blank 2. Submit a malformed email 3. Submit a 5-character password | G64: empty | not-an-email | Abc12 | H64: Field-level errors for required, email and min:6 respectively | J64: Medium | K64: Minor | L64: Validation / Negative | M64: Staging - Chrome 126 (Win 11) | N64: Not Executed
A65: ADM-004 | B65: Admin Authentication | C65: Unauthenticated admin signup | D65: Create an admin account without being signed in | E65: No admin token held | F65: 1. POST /api/admin/signup with a new username, email and password | G65: username=qaadmin; email=qa.admin@example.com; password=Admin@12345 | H65: The request is refused - self-service admin creation must require an authenticated privileged caller | J65: High | K65: Blocker | L65: Security / Negative | M65: Staging - Postman / REST client | N65: Not Executed | O65: QA audit: admin takeover via unauthenticated request
A66: ADM-005 | B66: Admin Authentication | C66: Admin forgot password | D66: Request an admin password reset | E66: Admin account exists | F66: 1. Open /admin/forgot-password 2. Enter the admin email 3. Submit | G66: admin@fixmypc.test | H66: A reset code is emailed and a neutral confirmation is shown | J66: Medium | K66: Major | L66: Functional / Positive | M66: Staging - Chrome 126 (Win 11) | N66: Not Executed
A67: ADM-006 | B67: Admin Authentication | C67: Admin verify code | D67: Complete the admin reset with the emailed code | E67: Reset code issued | F67: 1. Open /admin/verify-code 2. Enter the email, code and new password 3. Submit | G67: code from email; password=NewAdmin@123 | H67: The password is updated and the code is consumed; a wrong code is rejected | J67: Medium | K67: Major | L67: Functional | M67: Staging - Chrome 126 (Win 11) | N67: Not Executed
A68: ADM-007 | B68: Admin Authentication | C68: Admin session expiry | D68: Leave the admin panel idle past the token lifetime | E68: Signed-in admin | F68: 1. Stay idle beyond the configured expiry 2. Click any sidebar item | G68: idle session | H68: The user is redirected to the admin login with a session-expired notice; no stale data is rendered | J68: Medium | K68: Major | L68: Negative / Boundary | M68: Staging - Chrome 126 (Win 11) | N68: Not Executed
A69: ADM-008 | B69: Admin Authentication | C69: Admin logout | D69: Sign out of the admin panel | E69: Signed-in admin | F69: 1. Click Logout 2. Press browser Back | G69: active admin session | H69: The token is revoked and the Back button does not restore an authenticated view | J69: High | K69: Major | L69: Functional / Security | M69: Staging - Chrome 126 (Win 11) | N69: Not Executed
A70: ADM-009 | B70: Admin Authentication | C70: Direct admin URL without a session | D70: Open a deep admin URL while signed out | E70: Signed out | F70: 1. Navigate directly to /admin/orders | G70: no session | H70: Redirected to the admin login; no order data is fetched or briefly flashed on screen | J70: High | K70: Critical | L70: Security / Negative | M70: Staging - Chrome 126 (Win 11) | N70: Not Executed
A71: ADM-010 | B71: Admin Authentication | C71: Admin profile update | D71: Change the signed-in admin username and avatar | E71: Signed-in admin | F71: 1. Open /admin/profile 2. Change the username 3. Upload an avatar 4. Save | G71: username=QA Admin; avatar=avatar.png (400KB) | H71: Both changes persist and are reflected in the header immediately | J71: Low | K71: Minor | L71: Functional | M71: Staging - Chrome 126 (Win 11) | N71: Not Executed
A72: RBAC-001 | B72: Roles & Permissions | C72: Create a role | D72: Create a role with a subset of permissions | E72: Signed in as superadmin | F72: 1. Open /admin/roles-permissions 2. Click Add 3. Name the role and tick only the product group 4. Save | G72: name=Catalogue Editor; permissions=product.* | H72: The role is created and shows only the ticked permissions when reopened | J72: High | K72: Major | L72: Functional / Positive | M72: Staging - Chrome 126 (Win 11) | N72: Not Executed
A73: RBAC-002 | B73: Roles & Permissions | C73: Role name required | D73: Save a role with no name | E73: On the role form | F73: 1. Leave the name blank 2. Save | G73: name empty | H73: Validation error; nothing is saved | J73: Medium | K73: Minor | L73: Validation / Negative | M73: Staging - Chrome 126 (Win 11) | N73: Not Executed
A74: RBAC-003 | B74: Roles & Permissions | C74: Duplicate role name | D74: Create a second role with an existing name | E74: Catalogue Editor exists | F74: 1. Create another role called Catalogue Editor | G74: name=Catalogue Editor | H74: Rejected as a duplicate | J74: Medium | K74: Minor | L74: Negative | M74: Staging - Chrome 126 (Win 11) | N74: Not Executed
A75: RBAC-004 | B75: Roles & Permissions | C75: Assign a role to an admin | D75: Give an admin user a limited role | E75: Catalogue Editor role exists | F75: 1. Open /admin/admins-vendors 2. Edit an admin 3. Assign Catalogue Editor 4. Save | G75: admin=qa.editor@example.com | H75: The role is stored and the sidebar for that admin shows only permitted sections after re-login | J75: High | K75: Critical | L75: Functional / Positive | M75: Staging - Chrome 126 (Win 11) | N75: Not Executed
A76: RBAC-005 | B76: Roles & Permissions | C76: Sidebar filtering by permission | D76: A limited admin only sees permitted menu items | E76: Signed in as the Catalogue Editor | F76: 1. Sign in and inspect the sidebar | G76: Catalogue Editor session | H76: Only Products and related permitted entries render; Orders, Settings and Roles are absent | J76: High | K76: Major | L76: Functional / UI | M76: Staging - Chrome 126 (Win 11) | N76: Not Executed
A77: RBAC-006 | B77: Roles & Permissions | C77: API enforcement of permissions | D77: A limited admin calls an endpoint outside their role | E77: Catalogue Editor token | F77: 1. GET /api/order/all with the Catalogue Editor token | G77: limited admin token | H77: 403 - permission is enforced on the server, not only by hiding menu items | J77: High | K77: Blocker | L77: Security / Negative | M77: Staging - Postman / REST client | N77: Not Executed
... A89: CAT-004 | B89: Catalogue Structure | C89: Category slug format | D89: Slugs with spaces, capitals and symbols | E89: On the category form | F89: 1. Enter each slug value 2. Save | G89: Gaming Laptops | Gaming/Laptops | gaming laptops! | gaming-laptops | H89: Only URL-safe slugs are accepted, or the value is normalised to gaming-laptops; the resulting storefront URL resolves | J89: Medium | K89: Minor | L89: Validation / Boundary | M89: Staging - Chrome 126 (Win 11) | N89: Not Executed
A90: CAT-005 | B90: Catalogue Structure | C90: Category image validation | D90: Upload an oversized or wrong-type category image | E90: On the category form | F90: 1. Upload a 5MB JPEG 2. Upload a .exe renamed to .jpg 3. Upload an .svg | G90: 5MB jpg; payload.exe.jpg; icon.svg | H90: Files over MAX_IMAGE_SIZE (1024KB) are rejected; non-image content is rejected on MIME sniffing, not extension; SVG is refused | J90: High | K90: Critical | L90: Validation / Security | M90: Staging - Chrome 126 (Win 11) | N90: Not Executed | O90: QA audit flagged SVG upload acceptance
A91: CAT-006 | B91: Catalogue Structure | C91: Edit a category | D91: Change a category title and image | E91: Category exists | F91: 1. Open the category 2. Change the title and replace the image 3. Save | G91: title=Laptops & Notebooks | H91: Changes persist, the storefront reflects them after cache clear, and the old image is not left orphaned | J91: Medium | K91: Minor | L91: Functional | M91: Staging - Chrome 126 (Win 11) | N91: Not Executed
A92: CAT-007 | B92: Catalogue Structure | C92: Delete an empty category | D92: Delete a category with no products | E92: Empty category exists | F92: 1. Delete the category 2. Confirm | G92: empty category | H92: Removed from admin and storefront; the old URL returns a 404 or a redirect, not a 500 | J92: Medium | K92: Minor | L92: Functional | M92: Staging - Chrome 126 (Win 11) | N92: Not Executed
A93: CAT-008 | B93: Catalogue Structure | C93: Delete a category holding products | D93: Delete a category that still has products and sub-categories | E93: Category with 5 products and 2 sub-categories | F93: 1. Attempt the delete | G93: populated category | H93: Either blocked with a clear message, or cascaded cleanly - no orphaned product_categories rows and no broken storefront menu | J93: High | K93: Major | L93: Negative / Edge | M93: Staging - Chrome 126 (Win 11) | N93: Not Executed
A94: CAT-009 | B94: Catalogue Structure | C94: Create a sub-category | D94: Add a sub-category under a parent | E94: Parent category exists | F94: 1. Open /admin/sub-categories 2. Add with title, parent category, slug and meta fields 3. Save | G94: title=Gaming Laptops; category_id=Laptops | H94: Created and shown nested under the parent in the storefront menu | J94: High | K94: Major | L94: Functional / Positive | M94: Staging - Chrome 126 (Win 11) | N94: Not Executed
A95: CAT-010 | B95: Catalogue Structure | C95: Sub-category without a parent | D95: Save a sub-category with no category selected | E95: On the sub-category form | F95: 1. Leave the parent unselected 2. Save | G95: category_id=0 | H95: Validation error - the rule is required|numeric|min:0|not_in:0 | J95: Medium | K95: Major | L95: Validation / Negative | M95: Staging - Chrome 126 (Win 11) | N95: Not Executed
A96: CAT-011 | B96: Catalogue Structure | C96: Re-parent a sub-category | D96: Move a sub-category to a different parent | E96: Two parents and one populated sub-category | F96: 1. Change the parent 2. Save 3. Browse both parents on the storefront | G96: move Gaming Laptops to Computers | H96: Products follow the sub-category to the new parent and disappear from the old one | J96: Medium | K96: Major | L96: Functional / Integration | M96: Staging - Chrome 126 (Win 11) | N96: Not Executed
A97: CAT-012 | B97: Catalogue Structure | C97: Category tree ordering | D97: Change the display sort order | E97: Several categories exist | F97: 1. Drag to reorder or set sort values 2. POST update-sort-order 3. Reload the storefront menu | G97: sort 1,2,3 | H97: The storefront menu honours the new order and it survives a reload | J97: Low | K97: Minor | L97: Functional / UI | M97: Staging - Chrome 126 (Win 11) | N97: Not Executed
A98: CAT-013 | B98: Catalogue Structure | C98: Create a brand | D98: Create a brand with a logo and slug | E98: Signed in with brand permission | F98: 1. Open /admin/brands 2. Add with title, slug and logo 3. Save | G98: title=Lenovo; slug=lenovo | H98: Brand created and listed at /brands and on the brand landing page | J98: Medium | K98: Major | L98: Functional / Positive | M98: Staging - Chrome 126 (Win 11) | N98: Not Executed
A99: CAT-014 | B99: Catalogue Structure | C99: Brand duplicate slug | D99: Reuse a brand slug | E99: lenovo exists | F99: 1. Create a brand with slug=lenovo | G99: slug=lenovo | H99: Rejected or auto-suffixed - brand URLs stay unique | J99: Medium | K99: Minor | L99: Negative | M99: Staging - Chrome 126 (Win 11) | N99: Not Executed
A100: CAT-015 | B100: Catalogue Structure | C100: Delete a brand in use | D100: Delete a brand attached to live products | E100: Brand with 3 products | F100: 1. Delete the brand | G100: brand in use | H100: Blocked or cascaded safely; product pages do not 500 on a missing brand relation | J100: Medium | K100: Major | L100: Negative / Edge | M100: Staging - Chrome 126 (Win 11) | N100: Not Executed
A101: CAT-016 | B101: Catalogue Structure | C101: Create an attribute | D101: Create an attribute such as Colour | E101: Signed in with attribute permission | F101: 1. Open /admin/attributes 2. Add title=Colour 3. Save | G101: title=Colour | H101: Attribute created and selectable when building product variants | J101: High | K101: Major | L101: Functional / Positive | M101: Staging - Chrome 126 (Win 11) | N101: Not Executed
A102: CAT-017 | B102: Catalogue Structure | C102: Create attribute values | D102: Add values under an attribute | E102: Colour attribute exists | F102: 1. Add values Black, Silver, Space Grey 2. Save | G102: Black | Silver | Space Grey | H102: All three values are stored against attribute_id and offered on the variant builder | J102: High | K102: Major | L102: Functional / Positive | M102: Staging - Chrome 126 (Win 11) | N102: Not Executed
... A111: PROD-002 | B111: Product Management | C111: Product required fields | D111: Save a product with every mandatory field blank | E111: On the product form | F111: 1. Click Save with an empty form | G111: all blank | H111: Errors on title, unit, meta_title, meta_description, description, overview, selling, purchased, tax_rule_id and shipping_rule_id | J111: High | K111: Major | L111: Validation / Negative | M111: Staging - Chrome 126 (Win 11) | N111: Not Executed
A112: PROD-003 | B112: Product Management | C112: Selling price must be non-zero | D112: Save with selling price 0 | E112: On the product form | F112: 1. Set selling=0 2. Save | G112: selling=0 | H112: Rejected by required|numeric|min:0|not_in:0 - no free product is published by accident | J112: High | K112: Critical | L112: Validation / Boundary | M112: Staging - Chrome 126 (Win 11) | N112: Not Executed | O112: QA audit found four live products priced at zero
A113: PROD-004 | B113: Product Management | C113: Negative and non-numeric prices | D113: Enter invalid price values | E113: On the product form | F113: 1. Try each value in selling and purchased 2. Save | G113: -10 | abc | 1e5 | 12.999 | 0.01 | H113: Negative and non-numeric values are rejected; decimals are rounded or stored to exactly two places with no silent truncation | J113: High | K113: Major | L113: Validation / Boundary | M113: Staging - Chrome 126 (Win 11) | N113: Not Executed
A114: PROD-005 | B114: Product Management | C114: Offer price must not exceed selling | D114: Set an offer price above the selling price | E114: On the product form | F114: 1. Set selling=100 and offered=150 2. Save | G114: selling=100; offered=150 | H114: Rejected by nullable|numeric|min:0|lte:selling | J114: High | K114: Critical | L114: Validation / Negative | M114: Staging - Chrome 126 (Win 11) | N114: Not Executed | O114: QA audit PRC-02 regression check
A115: PROD-006 | B115: Product Management | C115: Offer price boundary | D115: Offer price exactly equal to the selling price | E115: On the product form | F115: 1. Set selling=100 and offered=100 2. Save 3. Then try offered=100.01 | G115: offered=100 then 100.01 | H115: 100 is accepted (lte is inclusive); 100.01 is rejected | J115: Medium | K115: Minor | L115: Boundary | M115: Staging - Chrome 126 (Win 11) | N115: Not Executed
A116: PROD-007 | B116: Product Management | C116: Offer price cleared | D116: Remove an offer price from a discounted product | E116: Product has an offer price | F116: 1. Clear the offered field 2. Save 3. Check the storefront | G116: offered=empty | H116: The offer is removed, the strike-through price disappears and the full selling price is charged in the cart | J116: Medium | K116: Major | L116: Functional | M116: Staging - Chrome 126 (Win 11) | N116: Not Executed
A117: PROD-008 | B117: Product Management | C117: Edit a product | D117: Change the title, description and price of a live product | E117: Published product exists | F117: 1. Edit the fields 2. Save 3. Reload the storefront product page | G117: selling 599.99 to 549.99 | H117: All changes are reflected on the storefront and existing carts are re-priced or clearly flagged | J117: High | K117: Major | L117: Functional | M117: Staging - Chrome 126 (Win 11) | N117: Not Executed
A118: PROD-009 | B118: Product Management | C118: Publish and unpublish | D118: Toggle a product between public and private | E118: Published product exists | F118: 1. Set status to private 2. Save 3. Open the storefront product URL | G118: status=2 (private) | H118: The product disappears from listings and search; the direct URL returns 404 or an unavailable page, never the full detail view | J118: High | K118: Major | L118: Functional / Security | M118: Staging - Chrome 126 (Win 11) | N118: Not Executed
A119: PROD-010 | B119: Product Management | C119: Delete a product | D119: Delete a product that has never been ordered | E119: Unordered product exists | F119: 1. Delete the product 2. Confirm | G119: unordered product | H119: Removed together with its images, inventories and category links; no orphaned rows remain | J119: Medium | K119: Major | L119: Functional | M119: Staging - Chrome 126 (Win 11) | N119: Not Executed
A120: PROD-011 | B120: Product Management | C120: Delete a product with order history | D120: Delete a product that appears on past orders | E120: Product with 2 completed orders | F120: 1. Attempt the delete 2. Open a historical order | G120: ordered product | H120: The delete is blocked or soft-deletes; historical orders still show the product name and price they were bought at | J120: High | K120: Critical | L120: Negative / Data integrity | M120: Staging - Chrome 126 (Win 11) | N120: Not Executed
A121: PROD-012 | B121: Product Management | C121: Duplicate a product | D121: Clone an existing product | E121: Product with variants and images | F121: 1. POST /api/admin/products/{id}/duplicate 2. Open the copy | G121: source product id | H121: A full copy is created with a unique slug and SKU; the original is untouched and no images are shared by reference in a way that a delete would break | J121: Medium | K121: Major | L121: Functional | M121: Staging - Chrome 126 (Win 11) | N121: Not Executed
A122: PROD-013 | B122: Product Management | C122: Product slug uniqueness | D122: Two products with the same title | E122: A product titled QA Test Laptop exists | F122: 1. Create a second product with the same title | G122: title=QA Test Laptop | H122: Slugs are made unique automatically; both product pages resolve to the right record | J122: Medium | K122: Major | L122: Boundary / Negative | M122: Staging - Chrome 126 (Win 11) | N122: Not Executed
A123: PROD-014 | B123: Product Management | C123: Upload product images | D123: Attach multiple gallery images | E123: Product exists | F123: 1. Upload 5 images 2. Set the main image 3. Reorder them 4. Save | G123: 5 JPEGs under 1MB each | H123: All are stored, the chosen main image leads the gallery and the order persists after reload | J123: Medium | K123: Major | L123: Functional | M123: Staging - Chrome 126 (Win 11) | N123: Not Executed
A124: PROD-015 | B124: Product Management | C124: Image upload limit | D124: Exceed the maximum image count | E124: Product with 10 images (MAX_IMG_UPLOAD) | F124: 1. Upload an 11th image | G124: 11th image | H124: Blocked with a clear message at the configured limit of 10 | J124: Low | K124: Minor | L124: Boundary / Negative | M124: Staging - Chrome 126 (Win 11) | N124: Not Executed
A125: PROD-016 | B125: Product Management | C125: Image file type and size | D125: Upload disallowed image files | E125: On the product image uploader | F125: 1. Upload a 3MB PNG 2. Upload a .svg 3. Upload a .php renamed to .jpg 4. Upload a 0-byte file | G125: 3MB png; logo.svg; shell.php.jpg; empty.jpg | H125: Each is rejected with a specific message; nothing executable is written to the uploads directory | J125: High | K125: Blocker | L125: Security / Validation | M125: Staging - Chrome 126 (Win 11) | N125: Not Executed
A126: PROD-017 | B126: Product Management | C126: Concurrent image upload filenames | D126: Two admins upload files with the same name at once | E126: Two admin sessions | F126: 1. Both upload photo.jpg to different products simultaneously | G126: photo.jpg x2 | H126: Both files are stored under distinct names; neither overwrites the other | J126: Medium | K126: Major | L126: Security / Concurrency | M126: Staging - Chrome 126 (Win 11) | N126: Not Executed | O126: QA audit flagged filename collisions under concurrency
A127: PROD-018 | B127: Product Management | C127: Delete a product image | D127: Remove one gallery image | E127: Product with 3 images | F127: 1. Delete the middle image 2. Reload | G127: image id | H127: Only that image is removed, the remaining order is sensible and the main image is reassigned if it was the one deleted | J127: Medium | K127: Minor | L127: Functional | M127: Staging - Chrome 126 (Win 11) | N127: Not Executed
A128: PROD-019 | B128: Product Management | C128: Delete the last remaining image | D128: Remove the only image a product has | E128: Product with one image | F128: 1. Delete it 2. View the storefront product page | G128: single image | H128: Either blocked, or the placeholder DEFAULT_IMAGE renders - never a broken image icon | J128: Low | K128: Minor | L128: Edge / UI | M128: Staging - Chrome 126 (Win 11) | N128: Not Executed
A129: PROD-020 | B129: Product Management | C129: Variant image mapping | D129: Bind gallery images to attribute values | E129: Product with Colour variants | F129: 1. POST set-variant-images mapping Black and Silver images 2. Open the storefront page 3. Switch colour | G129: Black -> img1; Silver -> img2 | H129: The gallery swaps to the mapped image when the shopper changes variant | J129: Medium | K129: Minor | L129: Functional / UI | M129: Staging - Chrome 126 (Win 11) | N129: Not Executed
A130: PROD-021 | B130: Product Management | C130: Product video upload | D130: Attach a product video | E130: Product exists | F130: 1. Upload a 1.5MB MP4 2. Then upload a 5MB MP4 | G130: 1.5MB mp4; 5MB mp4 | H130: The first is accepted; the second is rejected against MAX_VIDEO_SIZE (2048KB) | J130: Low | K130: Minor | L130: Boundary / Validation | M130: Staging - Chrome 126 (Win 11) | N130: Not Executed
A131: PROD-022 | B131: Product Management | C131: Rich text description | D131: Use the WYSIWYG editor with formatting and an embedded image | E131: On the product form | F131: 1. Add headings, a list, a link and an inline image 2. Save 3. View the storefront | G131: formatted HTML | H131: The formatting survives round-trip, the embedded image loads, and the output is sanitised - script tags are stripped | J131: High | K131: Critical | L131: Functional / Security | M131: Staging - Chrome 126 (Win 11) | N131: Not Executed
...

Sheet Dashboard
B2: EXECUTION DASHBOARD
B3: All figures are live formulas over the Test Cases sheet. Fill in Status there and these update automatically.
B5: OVERALL | I5: BY PRIORITY
B6: Metric | C6: Count | D6: % of Total | I6: Priority | J6: Total | K6: Passed | L6: Failed
B7: Total test cases | C7: =COUNTA('Test Cases'!$A$2:$A$643) -> 0 | D7: =IF($C$7=0,0,C7/$C$7) -> 0 | I7: High | J7: =COUNTIF('Test Cases'!$J$2:$J$643,"High") -> 0 | K7: =_xlfn.COUNTIFS('Test Cases'!$J$2:$J$643,"High",'Test Cases'!$N$2:$N$643,"Pass") -> 0 | L7: =_xlfn.COUNTIFS('Test Cases'!$J$2:$J$643,"High",'Test Cases'!$N$2:$N$643,"Fail") -> 0
B8: Not Executed | C8: =COUNTIF('Test Cases'!$N$2:$N$643,"Not Executed") -> 0 | D8: =IF($C$7=0,0,C8/$C$7) -> 0 | I8: Medium | J8: =COUNTIF('Test Cases'!$J$2:$J$643,"Medium") -> 0 | K8: =_xlfn.COUNTIFS('Test Cases'!$J$2:$J$643,"Medium",'Test Cases'!$N$2:$N$643,"Pass") -> 0 | L8: =_xlfn.COUNTIFS('Test Cases'!$J$2:$J$643,"Medium",'Test Cases'!$N$2:$N$643,"Fail") -> 0
B9: Passed | C9: =COUNTIF('Test Cases'!$N$2:$N$643,"Pass") -> 0 | D9: =IF($C$7=0,0,C9/$C$7) -> 0 | I9: Low | J9: =COUNTIF('Test Cases'!$J$2:$J$643,"Low") -> 0 | K9: =_xlfn.COUNTIFS('Test Cases'!$J$2:$J$643,"Low",'Test Cases'!$N$2:$N$643,"Pass") -> 0 | L9: =_xlfn.COUNTIFS('Test Cases'!$J$2:$J$643,"Low",'Test Cases'!$N$2:$N$643,"Fail") -> 0
B10: Failed | C10: =COUNTIF('Test Cases'!$N$2:$N$643,"Fail") -> 0 | D10: =IF($C$7=0,0,C10/$C$7) -> 0
B11: Blocked | C11: =COUNTIF('Test Cases'!$N$2:$N$643,"Blocked") -> 0 | D11: =IF($C$7=0,0,C11/$C$7) -> 0 | I11: BY SEVERITY
B12: Deferred | C12: =COUNTIF('Test Cases'!$N$2:$N$643,"Deferred") -> 0 | D12: =IF($C$7=0,0,C12/$C$7) -> 0 | I12: Severity | J12: Total | K12: Passed | L12: Failed
B13: Not applicable | C13: =COUNTIF('Test Cases'!$N$2:$N$643,"N-A") -> 0 | D13: =IF($C$7=0,0,C13/$C$7) -> 0 | I13: Blocker | J13: =COUNTIF('Test Cases'!$K$2:$K$643,"Blocker") -> 0 | K13: =_xlfn.COUNTIFS('Test Cases'!$K$2:$K$643,"Blocker",'Test Cases'!$N$2:$N$643,"Pass") -> 0 | L13: =_xlfn.COUNTIFS('Test Cases'!$K$2:$K$643,"Blocker",'Test Cases'!$N$2:$N$643,"Fail") -> 0
B14: Executed | C14: =$C$7-$C$8 -> 0 | D14: =IF($C$7=0,0,C14/$C$7) -> 0 | I14: Critical | J14: =COUNTIF('Test Cases'!$K$2:$K$643,"Critical") -> 0 | K14: =_xlfn.COUNTIFS('Test Cases'!$K$2:$K$643,"Critical",'Test Cases'!$N$2:$N$643,"Pass") -> 0 | L14: =_xlfn.COUNTIFS('Test Cases'!$K$2:$K$643,"Critical",'Test Cases'!$N$2:$N$643,"Fail") -> 0
I15: Major | J15: =COUNTIF('Test Cases'!$K$2:$K$643,"Major") -> 0 | K15: =_xlfn.COUNTIFS('Test Cases'!$K$2:$K$643,"Major",'Test Cases'!$N$2:$N$643,"Pass") -> 0 | L15: =_xlfn.COUNTIFS('Test Cases'!$K$2:$K$643,"Major",'Test Cases'!$N$2:$N$643,"Fail") -> 0
B16: Execution progress | C16: =IF($C$7=0,0,$C$14/$C$7) -> 0 | I16: Minor | J16: =COUNTIF('Test Cases'!$K$2:$K$643,"Minor") -> 0 | K16: =_xlfn.COUNTIFS('Test Cases'!$K$2:$K$643,"Minor",'Test Cases'!$N$2:$N$643,"Pass") -> 0 | L16: =_xlfn.COUNTIFS('Test Cases'!$K$2:$K$643,"Minor",'Test Cases'!$N$2:$N$643,"Fail") -> 0
B17: Pass rate (of executed) | C17: =IF($C$14=0,0,$C$9/$C$14) -> 0
B20: BY MODULE | I20: BY TEST TYPE (primary)
B21: Module | C21: Total | D21: Passed | E21: Failed | F21: Blocked | G21: Not Executed | I21: Test Type | J21: Total | K21: Passed | L21: Failed
B22: API | C22: =COUNTIF('Test Cases'!$B$2:$B$643,"API") -> 0 | D22: =_xlfn.COUNTIFS('Test Cases'!$B$2:$B$643,"API",'Test Cases'!$N$2:$N$643,"Pass") -> 0 | E22: =_xlfn.COUNTIFS('Test Cases'!$B$2:$B$643,"API",'Test Cases'!$N$2:$N$643,"Fail") -> 0 | F22: =_xlfn.COUNTIFS('Test Cases'!$B$2:$B$643,"API",'Test Cases'!$N$2:$N$643,"Blocked") -> 0 | G22: =_xlfn.COUNTIFS('Test Cases'!$B$2:$B$643,"API",'Test Cases'!$N$2:$N$643,"Not Executed") -> 0 | I22: Functional | J22: =COUNTIF('Test Cases'!$L$2:$L$643,"Functional*") -> 0 | K22: =_xlfn.COUNTIFS('Test Cases'!$L$2:$L$643,"Functional*",'Test Cases'!$N$2:$N$643,"Pass") -> 0 | L22: =_xlfn.COUNTIFS('Test Cases'!$L$2:$L$643,"Functional*",'Test Cases'!$N$2:$N$643,"Fail") -> 0
B23: Accessibility | C23: =COUNTIF('Test Cases'!$B$2:$B$643,"Accessibility") -> 0 | D23: =_xlfn.COUNTIFS('Test Cases'!$B$2:$B$643,"Accessibility",'Test Cases'!$N$2:$N$643,"Pass") -> 0 | E23: =_xlfn.COUNTIFS('Test Cases'!$B$2:$B$643,"Accessibility",'Test Cases'!$N$2:$N$643,"Fail") -> 0 | F23: =_xlfn.COUNTIFS('Test Cases'!$B$2:$B$643,"Accessibility",'Test Cases'!$N$2:$N$643,"Blocked") -> 0 | G23: =_xlfn.COUNTIFS('Test Cases'!$B$2:$B$643,"Accessibility",'Test Cases'!$N$2:$N$643,"Not Executed") -> 0 | I23: Security | J23: =COUNTIF('Test Cases'!$L$2:$L$643,"Security*") -> 0 | K23: =_xlfn.COUNTIFS('Test Cases'!$L$2:$L$643,"Security*",'Test Cases'!$N$2:$N$643,"Pass") -> 0 | L23: =_xlfn.COUNTIFS('Test Cases'!$L$2:$L$643,"Security*",'Test Cases'!$N$2:$N$643,"Fail") -> 0
B24: Admin Authentication | C24: =COUNTIF('Test Cases'!$B$2:$B$643,"Admin Authentication") -> 0 | D24: =_xlfn.COUNTIFS('Test Cases'!$B$2:$B$643,"Admin Authentication",'Test Cases'!$N$2:$N$643,"Pass") -> 0 | E24: =_xlfn.COUNTIFS('Test Cases'!$B$2:$B$643,"Admin Authentication",'Test Cases'!$N$2:$N$643,"Fail") -> 0 | F24: =_xlfn.COUNTIFS('Test Cases'!$B$2:$B$643,"Admin Authentication",'Test Cases'!$N$2:$N$643,"Blocked") -> 0 | G24: =_xlfn.COUNTIFS('Test Cases'!$B$2:$B$643,"Admin Authentication",'Test Cases'!$N$2:$N$643,"Not Executed") -> 0 | I24: Negative | J24: =COUNTIF('Test Cases'!$L$2:$L$643,"Negative*") -> 0 | K24: =_xlfn.COUNTIFS('Test Cases'!$L$2:$L$643,"Negative*",'Test Cases'!$N$2:$N$643,"Pass") -> 0 | L24: =_xlfn.COUNTIFS('Test Cases'!$L$2:$L$643,"Negative*",'Test Cases'!$N$2:$N$643,"Fail") -> 0
B25: Authentication | C25: =COUNTIF('Test Cases'!$B$2:$B$643,"Authentication") -> 0 | D25: =_xlfn.COUNTIFS('Test Cases'!$B$2:$B$643,"Authentication",'Test Cases'!$N$2:$N$643,"Pass") -> 0 | E25: =_xlfn.COUNTIFS('Test Cases'!$B$2:$B$643,"Authentication",'Test Cases'!$N$2:$N$643,"Fail") -> 0 | F25: =_xlfn.COUNTIFS('Test Cases'!$B$2:$B$643,"Authentication",'Test Cases'!$N$2:$N$643,"Blocked") -> 0 | G25: =_xlfn.COUNTIFS('Test Cases'!$B$2:$B$643,"Authentication",'Test Cases'!$N$2:$N$643,"Not Executed") -> 0 | I25: Validation | J25: =COUNTIF('Test Cases'!$L$2:$L$643,"Validation*") -> 0 | K25: =_xlfn.COUNTIFS('Test Cases'!$L$2:$L$643,"Validation*",'Test Cases'!$N$2:$N$643,"Pass") -> 0 | L25: =_xlfn.COUNTIFS('Test Cases'!$L$2:$L$643,"Validation*",'Test Cases'!$N$2:$N$643,"Fail") -> 0
B26: Cart | C26: =COUNTIF('Test Cases'!$B$2:$B$643,"Cart") -> 0 | D26: =_xlfn.COUNTIFS('Test Cases'!$B$2:$B$643,"Cart",'Test Cases'!$N$2:$N$643,"Pass") -> 0 | E26: =_xlfn.COUNTIFS('Test Cases'!$B$2:$B$643,"Cart",'Test Cases'!$N$2:$N$643,"Fail") -> 0 | F26: =_xlfn.COUNTIFS('Test Cases'!$B$2:$B$643,"Cart",'Test Cases'!$N$2:$N$643,"Blocked") -> 0 | G26: =_xlfn.COUNTIFS('Test Cases'!$B$2:$B$643,"Cart",'Test Cases'!$N$2:$N$643,"Not Executed") -> 0 | I26: Boundary | J26: =COUNTIF('Test Cases'!$L$2:$L$643,"Boundary*") -> 0 | K26: =_xlfn.COUNTIFS('Test Cases'!$L$2:$L$643,"Boundary*",'Test Cases'!$N$2:$N$643,"Pass") -> 0 | L26: =_xlfn.COUNTIFS('Test Cases'!$L$2:$L$643,"Boundary*",'Test Cases'!$N$2:$N$643,"Fail") -> 0
B27: Catalogue Structure | C27: =COUNTIF('Test Cases'!$B$2:$B$643,"Catalogue Structure") -> 0 | D27: =_xlfn.COUNTIFS('Test Cases'!$B$2:$B$643,"Catalogue Structure",'Test Cases'!$N$2:$N$643,"Pass") -> 0 | E27: =_xlfn.COUNTIFS('Test Cases'!$B$2:$B$643,"Catalogue Structure",'Test Cases'!$N$2:$N$643,"Fail") -> 0 | F27: =_xlfn.COUNTIFS('Test Cases'!$B$2:$B$643,"Catalogue Structure",'Test Cases'!$N$2:$N$643,"Blocked") -> 0 | G27: =_xlfn.COUNTIFS('Test Cases'!$B$2:$B$643,"Catalogue Structure",'Test Cases'!$N$2:$N$643,"Not Executed") -> 0 | I27: Integration | J27: =COUNTIF('Test Cases'!$L$2:$L$643,"Integration*") -> 0 | K27: =_xlfn.COUNTIFS('Test Cases'!$L$2:$L$643,"Integration*",'Test Cases'!$N$2:$N$643,"Pass") -> 0 | L27: =_xlfn.COUNTIFS('Test Cases'!$L$2:$L$643,"Integration*",'Test Cases'!$N$2:$N$643,"Fail") -> 0
B28: Checkout | C28: =COUNTIF('Test Cases'!$B$2:$B$643,"Checkout") -> 0 | D28: =_xlfn.COUNTIFS('Test Cases'!$B$2:$B$643,"Checkout",'Test Cases'!$N$2:$N$643,"Pass") -> 0 | E28: =_xlfn.COUNTIFS('Test Cases'!$B$2:$B$643,"Checkout",'Test Cases'!$N$2:$N$643,"Fail") -> 0 | F28: =_xlfn.COUNTIFS('Test Cases'!$B$2:$B$643,"Checkout",'Test Cases'!$N$2:$N$643,"Blocked") -> 0 | G28: =_xlfn.COUNTIFS('Test Cases'!$B$2:$B$643,"Checkout",'Test Cases'!$N$2:$N$643,"Not Executed") -> 0 | I28: Edge | J28: =COUNTIF('Test Cases'!$L$2:$L$643,"Edge*") -> 0 | K28: =_xlfn.COUNTIFS('Test Cases'!$L$2:$L$643,"Edge*",'Test Cases'!$N$2:$N$643,"Pass") -> 0 | L28: =_xlfn.COUNTIFS('Test Cases'!$L$2:$L$643,"Edge*",'Test Cases'!$N$2:$N$643,"Fail") -> 0
B29: Compatibility | C29: =COUNTIF('Test Cases'!$B$2:$B$643,"Compatibility") -> 0 | D29: =_xlfn.COUNTIFS('Test Cases'!$B$2:$B$643,"Compatibility",'Test Cases'!$N$2:$N$643,"Pass") -> 0 | E29: =_xlfn.COUNTIFS('Test Cases'!$B$2:$B$643,"Compatibility",'Test Cases'!$N$2:$N$643,"Fail") -> 0 | F29: =_xlfn.COUNTIFS('Test Cases'!$B$2:$B$643,"Compatibility",'Test Cases'!$N$2:$N$643,"Blocked") -> 0 | G29: =_xlfn.COUNTIFS('Test Cases'!$B$2:$B$643,"Compatibility",'Test Cases'!$N$2:$N$643,"Not Executed") -> 0 | I29: Data integrity | J29: =COUNTIF('Test Cases'!$L$2:$L$643,"Data integrity*") -> 0 | K29: =_xlfn.COUNTIFS('Test Cases'!$L$2:$L$643,"Data integrity*",'Test Cases'!$N$2:$N$643,"Pass") -> 0 | L29: =_xlfn.COUNTIFS('Test Cases'!$L$2:$L$643,"Data integrity*",'Test Cases'!$N$2:$N$643,"Fail") -> 0
B30: Content Management | C30: =COUNTIF('Test Cases'!$B$2:$B$643,"Content Management") -> 0 | D30: =_xlfn.COUNTIFS('Test Cases'!$B$2:$B$643,"Content Management",'Test Cases'!$N$2:$N$643,"Pass") -> 0 | E30: =_xlfn.COUNTIFS('Test Cases'!$B$2:$B$643,"Content Management",'Test Cases'!$N$2:$N$643,"Fail") -> 0 | F30: =_xlfn.COUNTIFS('Test Cases'!$B$2:$B$643,"Content Management",'Test Cases'!$N$2:$N$643,"Blocked") -> 0 | G30: =_xlfn.COUNTIFS('Test Cases'!$B$2:$B$643,"Content Management",'Test Cases'!$N$2:$N$643,"Not Executed") -> 0 | I30: E2E | J30: =COUNTIF('Test Cases'!$L$2:$L$643,"E2E*") -> 0 | K30: =_xlfn.COUNTIFS('Test Cases'!$L$2:$L$643,"E2E*",'Test Cases'!$N$2:$N$643,"Pass") -> 0 | L30: =_xlfn.COUNTIFS('Test Cases'!$L$2:$L$643,"E2E*",'Test Cases'!$N$2:$N$643,"Fail") -> 0
B31: Customer Account | C31: =COUNTIF('Test Cases'!$B$2:$B$643,"Customer Account") -> 0 | D31: =_xlfn.COUNTIFS('Test Cases'!$B$2:$B$643,"Customer Account",'Test Cases'!$N$2:$N$643,"Pass") -> 0 | E31: =_xlfn.COUNTIFS('Test Cases'!$B$2:$B$643,"Customer Account",'Test Cases'!$N$2:$N$643,"Fail") -> 0 | F31: =_xlfn.COUNTIFS('Test Cases'!$B$2:$B$643,"Customer Account",'Test Cases'!$N$2:$N$643,"Blocked") -> 0 | G31: =_xlfn.COUNTIFS('Test Cases'!$B$2:$B$643,"Customer Account",'Test Cases'!$N$2:$N$643,"Not Executed") -> 0 | I31: Performance | J31: =COUNTIF('Test Cases'!$L$2:$L$643,"Performance*") -> 0 | K31: =_xlfn.COUNTIFS('Test Cases'!$L$2:$L$643,"Performance*",'Test Cases'!$N$2:$N$643,"Pass") -> 0 | L31: =_xlfn.COUNTIFS('Test Cases'!$L$2:$L$643,"Performance*",'Test Cases'!$N$2:$N$643,"Fail") -> 0
B32: Database | C32: =COUNTIF('Test Cases'!$B$2:$B$643,"Database") -> 0 | D32: =_xlfn.COUNTIFS('Test Cases'!$B$2:$B$643,"Database",'Test Cases'!$N$2:$N$643,"Pass") -> 0 | E32: =_xlfn.COUNTIFS('Test Cases'!$B$2:$B$643,"Database",'Test Cases'!$N$2:$N$643,"Fail") -> 0 | F32: =_xlfn.COUNTIFS('Test Cases'!$B$2:$B$643,"Database",'Test Cases'!$N$2:$N$643,"Blocked") -> 0 | G32: =_xlfn.COUNTIFS('Test Cases'!$B$2:$B$643,"Database",'Test Cases'!$N$2:$N$643,"Not Executed") -> 0 | I32: Accessibility | J32: =COUNTIF('Test Cases'!$L$2:$L$643,"Accessibility*") -> 0 | K32: =_xlfn.COUNTIFS('Test Cases'!$L$2:$L$643,"Accessibility*",'Test Cases'!$N$2:$N$643,"Pass") -> 0 | L32: =_xlfn.COUNTIFS('Test Cases'!$L$2:$L$643,"Accessibility*",'Test Cases'!$N$2:$N$643,"Fail") -> 0
B33: End-to-End | C33: =COUNTIF('Test Cases'!$B$2:$B$643,"End-to-End") -> 0 | D33: =_xlfn.COUNTIFS('Test Cases'!$B$2:$B$643,"End-to-End",'Test Cases'!$N$2:$N$643,"Pass") -> 0 | E33: =_xlfn.COUNTIFS('Test Cases'!$B$2:$B$643,"End-to-End",'Test Cases'!$N$2:$N$643,"Fail") -> 0 | F33: =_xlfn.COUNTIFS('Test Cases'!$B$2:$B$643,"End-to-End",'Test Cases'!$N$2:$N$643,"Blocked") -> 0 | G33: =_xlfn.COUNTIFS('Test Cases'!$B$2:$B$643,"End-to-End",'Test Cases'!$N$2:$N$643,"Not Executed") -> 0 | I33: Compatibility | J33: =COUNTIF('Test Cases'!$L$2:$L$643,"Compatibility*") -> 0 | K33: =_xlfn.COUNTIFS('Test Cases'!$L$2:$L$643,"Compatibility*",'Test Cases'!$N$2:$N$643,"Pass") -> 0 | L33: =_xlfn.COUNTIFS('Test Cases'!$L$2:$L$643,"Compatibility*",'Test Cases'!$N$2:$N$643,"Fail") -> 0
B34: Error Handling | C34: =COUNTIF('Test Cases'!$B$2:$B$643,"Error Handling") -> 0 | D34: =_xlfn.COUNTIFS('Test Cases'!$B$2:$B$643,"Error Handling",'Test Cases'!$N$2:$N$643,"Pass") -> 0 | E34: =_xlfn.COUNTIFS('Test Cases'!$B$2:$B$643,"Error Handling",'Test Cases'!$N$2:$N$643,"Fail") -> 0 | F34: =_xlfn.COUNTIFS('Test Cases'!$B$2:$B$643,"Error Handling",'Test Cases'!$N$2:$N$643,"Blocked") -> 0 | G34: =_xlfn.COUNTIFS('Test Cases'!$B$2:$B$643,"Error Handling",'Test Cases'!$N$2:$N$643,"Not Executed") -> 0 | I34: Error handling | J34: =COUNTIF('Test Cases'!$L$2:$L$643,"Error handling*") -> 0 | K34: =_xlfn.COUNTIFS('Test Cases'!$L$2:$L$643,"Error handling*",'Test Cases'!$N$2:$N$643,"Pass") -> 0 | L34: =_xlfn.COUNTIFS('Test Cases'!$L$2:$L$643,"Error handling*",'Test Cases'!$N$2:$N$643,"Fail") -> 0
B35: Installation | C35: =COUNTIF('Test Cases'!$B$2:$B$643,"Installation") -> 0 | D35: =_xlfn.COUNTIFS('Test Cases'!$B$2:$B$643,"Installation",'Test Cases'!$N$2:$N$643,"Pass") -> 0 | E35: =_xlfn.COUNTIFS('Test Cases'!$B$2:$B$643,"Installation",'Test Cases'!$N$2:$N$643,"Fail") -> 0 | F35: =_xlfn.COUNTIFS('Test Cases'!$B$2:$B$643,"Installation",'Test Cases'!$N$2:$N$643,"Blocked") -> 0 | G35: =_xlfn.COUNTIFS('Test Cases'!$B$2:$B$643,"Installation",'Test Cases'!$N$2:$N$643,"Not Executed") -> 0 | I35: Responsive | J35: =COUNTIF('Test Cases'!$L$2:$L$643,"Responsive*") -> 0 | K35: =_xlfn.COUNTIFS('Test Cases'!$L$2:$L$643,"Responsive*",'Test Cases'!$N$2:$N$643,"Pass") -> 0 | L35: =_xlfn.COUNTIFS('Test Cases'!$L$2:$L$643,"Responsive*",'Test Cases'!$N$2:$N$643,"Fail") -> 0
B36: Inventory & Stock | C36: =COUNTIF('Test Cases'!$B$2:$B$643,"Inventory & Stock") -> 0 | D36: =_xlfn.COUNTIFS('Test Cases'!$B$2:$B$643,"Inventory & Stock",'Test Cases'!$N$2:$N$643,"Pass") -> 0 | E36: =_xlfn.COUNTIFS('Test Cases'!$B$2:$B$643,"Inventory & Stock",'Test Cases'!$N$2:$N$643,"Fail") -> 0 | F36: =_xlfn.COUNTIFS('Test Cases'!$B$2:$B$643,"Inventory & Stock",'Test Cases'!$N$2:$N$643,"Blocked") -> 0 | G36: =_xlfn.COUNTIFS('Test Cases'!$B$2:$B$643,"Inventory & Stock",'Test Cases'!$N$2:$N$643,"Not Executed") -> 0 | I36: i18n | J36: =COUNTIF('Test Cases'!$L$2:$L$643,"i18n*") -> 0 | K36: =_xlfn.COUNTIFS('Test Cases'!$L$2:$L$643,"i18n*",'Test Cases'!$N$2:$N$643,"Pass") -> 0 | L36: =_xlfn.COUNTIFS('Test Cases'!$L$2:$L$643,"i18n*",'Test Cases'!$N$2:$N$643,"Fail") -> 0
B37: Localisation | C37: =COUNTIF('Test Cases'!$B$2:$B$643,"Localisation") -> 0 | D37: =_xlfn.COUNTIFS('Test Cases'!$B$2:$B$643,"Localisation",'Test Cases'!$N$2:$N$643,"Pass") -> 0 | E37: =_xlfn.COUNTIFS('Test Cases'!$B$2:$B$643,"Localisation",'Test Cases'!$N$2:$N$643,"Fail") -> 0 | F37: =_xlfn.COUNTIFS('Test Cases'!$B$2:$B$643,"Localisation",'Test Cases'!$N$2:$N$643,"Blocked") -> 0 | G37: =_xlfn.COUNTIFS('Test Cases'!$B$2:$B$643,"Localisation",'Test Cases'!$N$2:$N$643,"Not Executed") -> 0 | I37: UI | J37: =COUNTIF('Test Cases'!$L$2:$L$643,"UI*") -> 0 | K37: =_xlfn.COUNTIFS('Test Cases'!$L$2:$L$643,"UI*",'Test Cases'!$N$2:$N$643,"Pass") -> 0 | L37: =_xlfn.COUNTIFS('Test Cases'!$L$2:$L$643,"UI*",'Test Cases'!$N$2:$N$643,"Fail") -> 0
B38: Order Management | C38: =COUNTIF('Test Cases'!$B$2:$B$643,"Order Management") -> 0 | D38: =_xlfn.COUNTIFS('Test Cases'!$B$2:$B$643,"Order Management",'Test Cases'!$N$2:$N$643,"Pass") -> 0 | E38: =_xlfn.COUNTIFS('Test Cases'!$B$2:$B$643,"Order Management",'Test Cases'!$N$2:$N$643,"Fail") -> 0 | F38: =_xlfn.COUNTIFS('Test Cases'!$B$2:$B$643,"Order Management",'Test Cases'!$N$2:$N$643,"Blocked") -> 0 | G38: =_xlfn.COUNTIFS('Test Cases'!$B$2:$B$643,"Order Management",'Test Cases'!$N$2:$N$643,"Not Executed") -> 0 | I38: Concurrency | J38: =COUNTIF('Test Cases'!$L$2:$L$643,"Concurrency*") -> 0 | K38: =_xlfn.COUNTIFS('Test Cases'!$L$2:$L$643,"Concurrency*",'Test Cases'!$N$2:$N$643,"Pass") -> 0 | L38: =_xlfn.COUNTIFS('Test Cases'!$L$2:$L$643,"Concurrency*",'Test Cases'!$N$2:$N$643,"Fail") -> 0
B39: Payments | C39: =COUNTIF('Test Cases'!$B$2:$B$643,"Payments") -> 0 | D39: =_xlfn.COUNTIFS('Test Cases'!$B$2:$B$643,"Payments",'Test Cases'!$N$2:$N$643,"Pass") -> 0 | E39: =_xlfn.COUNTIFS('Test Cases'!$B$2:$B$643,"Payments",'Test Cases'!$N$2:$N$643,"Fail") -> 0 | F39: =_xlfn.COUNTIFS('Test Cases'!$B$2:$B$643,"Payments",'Test Cases'!$N$2:$N$643,"Blocked") -> 0 | G39: =_xlfn.COUNTIFS('Test Cases'!$B$2:$B$643,"Payments",'Test Cases'!$N$2:$N$643,"Not Executed") -> 0 | I39: Recovery | J39: =COUNTIF('Test Cases'!$L$2:$L$643,"Recovery*") -> 0 | K39: =_xlfn.COUNTIFS('Test Cases'!$L$2:$L$643,"Recovery*",'Test Cases'!$N$2:$N$643,"Pass") -> 0 | L39: =_xlfn.COUNTIFS('Test Cases'!$L$2:$L$643,"Recovery*",'Test Cases'!$N$2:$N$643,"Fail") -> 0
B40: Performance | C40: =COUNTIF('Test Cases'!$B$2:$B$643,"Performance") -> 0 | D40: =_xlfn.COUNTIFS('Test Cases'!$B$2:$B$643,"Performance",'Test Cases'!$N$2:$N$643,"Pass") -> 0 | E40: =_xlfn.COUNTIFS('Test Cases'!$B$2:$B$643,"Performance",'Test Cases'!$N$2:$N$643,"Fail") -> 0 | F40: =_xlfn.COUNTIFS('Test Cases'!$B$2:$B$643,"Performance",'Test Cases'!$N$2:$N$643,"Blocked") -> 0 | G40: =_xlfn.COUNTIFS('Test Cases'!$B$2:$B$643,"Performance",'Test Cases'!$N$2:$N$643,"Not Executed") -> 0 | I40: Deployment | J40: =COUNTIF('Test Cases'!$L$2:$L$643,"Deployment*") -> 0 | K40: =_xlfn.COUNTIFS('Test Cases'!$L$2:$L$643,"Deployment*",'Test Cases'!$N$2:$N$643,"Pass") -> 0 | L40: =_xlfn.COUNTIFS('Test Cases'!$L$2:$L$643,"Deployment*",'Test Cases'!$N$2:$N$643,"Fail") -> 0
B41: Point of Sale | C41: =COUNTIF('Test Cases'!$B$2:$B$643,"Point of Sale") -> 0 | D41: =_xlfn.COUNTIFS('Test Cases'!$B$2:$B$643,"Point of Sale",'Test Cases'!$N$2:$N$643,"Pass") -> 0 | E41: =_xlfn.COUNTIFS('Test Cases'!$B$2:$B$643,"Point of Sale",'Test Cases'!$N$2:$N$643,"Fail") -> 0 | F41: =_xlfn.COUNTIFS('Test Cases'!$B$2:$B$643,"Point of Sale",'Test Cases'!$N$2:$N$643,"Blocked") -> 0 | G41: =_xlfn.COUNTIFS('Test Cases'!$B$2:$B$643,"Point of Sale",'Test Cases'!$N$2:$N$643,"Not Executed") -> 0 | I41: TOTAL | J41: =SUM(J$22:J$40) -> 0 | K41: =SUM(K$22:K$40) -> 0 | L41: =SUM(L$22:L$40) -> 0
B42: Pricing & Promotions | C42: =COUNTIF('Test Cases'!$B$2:$B$643,"Pricing & Promotions") -> 0 | D42: =_xlfn.COUNTIFS('Test Cases'!$B$2:$B$643,"Pricing & Promotions",'Test Cases'!$N$2:$N$643,"Pass") -> 0 | E42: =_xlfn.COUNTIFS('Test Cases'!$B$2:$B$643,"Pricing & Promotions",'Test Cases'!$N$2:$N$643,"Fail") -> 0 | F42: =_xlfn.COUNTIFS('Test Cases'!$B$2:$B$643,"Pricing & Promotions",'Test Cases'!$N$2:$N$643,"Blocked") -> 0 | G42: =_xlfn.COUNTIFS('Test Cases'!$B$2:$B$643,"Pricing & Promotions",'Test Cases'!$N$2:$N$643,"Not Executed") -> 0
B43: Procurement | C43: =COUNTIF('Test Cases'!$B$2:$B$643,"Procurement") -> 0 | D43: =_xlfn.COUNTIFS('Test Cases'!$B$2:$B$643,"Procurement",'Test Cases'!$N$2:$N$643,"Pass") -> 0 | E43: =_xlfn.COUNTIFS('Test Cases'!$B$2:$B$643,"Procurement",'Test Cases'!$N$2:$N$643,"Fail") -> 0 | F43: =_xlfn.COUNTIFS('Test Cases'!$B$2:$B$643,"Procurement",'Test Cases'!$N$2:$N$643,"Blocked") -> 0 | G43: =_xlfn.COUNTIFS('Test Cases'!$B$2:$B$643,"Procurement",'Test Cases'!$N$2:$N$643,"Not Executed") -> 0
B44: Product Management | C44: =COUNTIF('Test Cases'!$B$2:$B$643,"Product Management") -> 0 | D44: =_xlfn.COUNTIFS('Test Cases'!$B$2:$B$643,"Product Management",'Test Cases'!$N$2:$N$643,"Pass") -> 0 | E44: =_xlfn.COUNTIFS('Test Cases'!$B$2:$B$643,"Product Management",'Test Cases'!$N$2:$N$643,"Fail") -> 0 | F44: =_xlfn.COUNTIFS('Test Cases'!$B$2:$B$643,"Product Management",'Test Cases'!$N$2:$N$643,"Blocked") -> 0 | G44: =_xlfn.COUNTIFS('Test Cases'!$B$2:$B$643,"Product Management",'Test Cases'!$N$2:$N$643,"Not Executed") -> 0
B45: Responsive & UI | C45: =COUNTIF('Test Cases'!$B$2:$B$643,"Responsive & UI") -> 0 | D45: =_xlfn.COUNTIFS('Test Cases'!$B$2:$B$643,"Responsive & UI",'Test Cases'!$N$2:$N$643,"Pass") -> 0 | E45: =_xlfn.COUNTIFS('Test Cases'!$B$2:$B$643,"Responsive & UI",'Test Cases'!$N$2:$N$643,"Fail") -> 0 | F45: =_xlfn.COUNTIFS('Test Cases'!$B$2:$B$643,"Responsive & UI",'Test Cases'!$N$2:$N$643,"Blocked") -> 0 | G45: =_xlfn.COUNTIFS('Test Cases'!$B$2:$B$643,"Responsive & UI",'Test Cases'!$N$2:$N$643,"Not Executed") -> 0
B46: Reviews & Ratings | C46: =COUNTIF('Test Cases'!$B$2:$B$643,"Reviews & Ratings") -> 0 | D46: =_xlfn.COUNTIFS('Test Cases'!$B$2:$B$643,"Reviews & Ratings",'Test Cases'!$N$2:$N$643,"Pass") -> 0 | E46: =_xlfn.COUNTIFS('Test Cases'!$B$2:$B$643,"Reviews & Ratings",'Test Cases'!$N$2:$N$643,"Fail") -> 0 | F46: =_xlfn.COUNTIFS('Test Cases'!$B$2:$B$643,"Reviews & Ratings",'Test Cases'!$N$2:$N$643,"Blocked") -> 0 | G46: =_xlfn.COUNTIFS('Test Cases'!$B$2:$B$643,"Reviews & Ratings",'Test Cases'!$N$2:$N$643,"Not Executed") -> 0
B47: Roles & Permissions | C47: =COUNTIF('Test Cases'!$B$2:$B$643,"Roles & Permissions") -> 0 | D47: =_xlfn.COUNTIFS('Test Cases'!$B$2:$B$643,"Roles & Permissions",'Test Cases'!$N$2:$N$643,"Pass") -> 0 | E47: =_xlfn.COUNTIFS('Test Cases'!$B$2:$B$643,"Roles & Permissions",'Test Cases'!$N$2:$N$643,"Fail") -> 0 | F47: =_xlfn.COUNTIFS('Test Cases'!$B$2:$B$643,"Roles & Permissions",'Test Cases'!$N$2:$N$643,"Blocked") -> 0 | G47: =_xlfn.COUNTIFS('Test Cases'!$B$2:$B$643,"Roles & Permissions",'Test Cases'!$N$2:$N$643,"Not Executed") -> 0
B48: Search & Browse | C48: =COUNTIF('Test Cases'!$B$2:$B$643,"Search & Browse") -> 0 | D48: =_xlfn.COUNTIFS('Test Cases'!$B$2:$B$643,"Search & Browse",'Test Cases'!$N$2:$N$643,"Pass") -> 0 | E48: =_xlfn.COUNTIFS('Test Cases'!$B$2:$B$643,"Search & Browse",'Test Cases'!$N$2:$N$643,"Fail") -> 0 | F48: =_xlfn.COUNTIFS('Test Cases'!$B$2:$B$643,"Search & Browse",'Test Cases'!$N$2:$N$643,"Blocked") -> 0 | G48: =_xlfn.COUNTIFS('Test Cases'!$B$2:$B$643,"Search & Browse",'Test Cases'!$N$2:$N$643,"Not Executed") -> 0
B49: Security | C49: =COUNTIF('Test Cases'!$B$2:$B$643,"Security") -> 0 | D49: =_xlfn.COUNTIFS('Test Cases'!$B$2:$B$643,"Security",'Test Cases'!$N$2:$N$643,"Pass") -> 0 | E49: =_xlfn.COUNTIFS('Test Cases'!$B$2:$B$643,"Security",'Test Cases'!$N$2:$N$643,"Fail") -> 0 | F49: =_xlfn.COUNTIFS('Test Cases'!$B$2:$B$643,"Security",'Test Cases'!$N$2:$N$643,"Blocked") -> 0 | G49: =_xlfn.COUNTIFS('Test Cases'!$B$2:$B$643,"Security",'Test Cases'!$N$2:$N$643,"Not Executed") -> 0
B50: Settings | C50: =COUNTIF('Test Cases'!$B$2:$B$643,"Settings") -> 0 | D50: =_xlfn.COUNTIFS('Test Cases'!$B$2:$B$643,"Settings",'Test Cases'!$N$2:$N$643,"Pass") -> 0 | E50: =_xlfn.COUNTIFS('Test Cases'!$B$2:$B$643,"Settings",'Test Cases'!$N$2:$N$643,"Fail") -> 0 | F50: =_xlfn.COUNTIFS('Test Cases'!$B$2:$B$643,"Settings",'Test Cases'!$N$2:$N$643,"Blocked") -> 0 | G50: =_xlfn.COUNTIFS('Test Cases'!$B$2:$B$643,"Settings",'Test Cases'!$N$2:$N$643,"Not Executed") -> 0
B51: Storefront | C51: =COUNTIF('Test Cases'!$B$2:$B$643,"Storefront") -> 0 | D51: =_xlfn.COUNTIFS('Test Cases'!$B$2:$B$643,"Storefront",'Test Cases'!$N$2:$N$643,"Pass") -> 0 | E51: =_xlfn.COUNTIFS('Test Cases'!$B$2:$B$643,"Storefront",'Test Cases'!$N$2:$N$643,"Fail") -> 0 | F51: =_xlfn.COUNTIFS('Test Cases'!$B$2:$B$643,"Storefront",'Test Cases'!$N$2:$N$643,"Blocked") -> 0 | G51: =_xlfn.COUNTIFS('Test Cases'!$B$2:$B$643,"Storefront",'Test Cases'!$N$2:$N$643,"Not Executed") -> 0
B52: Vendor & Store | C52: =COUNTIF('Test Cases'!$B$2:$B$643,"Vendor & Store") -> 0 | D52: =_xlfn.COUNTIFS('Test Cases'!$B$2:$B$643,"Vendor & Store",'Test Cases'!$N$2:$N$643,"Pass") -> 0 | E52: =_xlfn.COUNTIFS('Test Cases'!$B$2:$B$643,"Vendor & Store",'Test Cases'!$N$2:$N$643,"Fail") -> 0 | F52: =_xlfn.COUNTIFS('Test Cases'!$B$2:$B$643,"Vendor & Store",'Test Cases'!$N$2:$N$643,"Blocked") -> 0 | G52: =_xlfn.COUNTIFS('Test Cases'!$B$2:$B$643,"Vendor & Store",'Test Cases'!$N$2:$N$643,"Not Executed") -> 0
B53: Vouchers & Coupons | C53: =COUNTIF('Test Cases'!$B$2:$B$643,"Vouchers & Coupons") -> 0 | D53: =_xlfn.COUNTIFS('Test Cases'!$B$2:$B$643,"Vouchers & Coupons",'Test Cases'!$N$2:$N$643,"Pass") -> 0 | E53: =_xlfn.COUNTIFS('Test Cases'!$B$2:$B$643,"Vouchers & Coupons",'Test Cases'!$N$2:$N$643,"Fail") -> 0 | F53: =_xlfn.COUNTIFS('Test Cases'!$B$2:$B$643,"Vouchers & Coupons",'Test Cases'!$N$2:$N$643,"Blocked") -> 0 | G53: =_xlfn.COUNTIFS('Test Cases'!$B$2:$B$643,"Vouchers & Coupons",'Test Cases'!$N$2:$N$643,"Not Executed") -> 0
B54: Wallet & Loyalty | C54: =COUNTIF('Test Cases'!$B$2:$B$643,"Wallet & Loyalty") -> 0 | D54: =_xlfn.COUNTIFS('Test Cases'!$B$2:$B$643,"Wallet & Loyalty",'Test Cases'!$N$2:$N$643,"Pass") -> 0 | E54: =_xlfn.COUNTIFS('Test Cases'!$B$2:$B$643,"Wallet & Loyalty",'Test Cases'!$N$2:$N$643,"Fail") -> 0 | F54: =_xlfn.COUNTIFS('Test Cases'!$B$2:$B$643,"Wallet & Loyalty",'Test Cases'!$N$2:$N$643,"Blocked") -> 0 | G54: =_xlfn.COUNTIFS('Test Cases'!$B$2:$B$643,"Wallet & Loyalty",'Test Cases'!$N$2:$N$643,"Not Executed") -> 0
B55: TOTAL | C55: =SUM(C$22:C$54) -> 0 | D55: =SUM(D$22:D$54) -> 0 | E55: =SUM(E$22:E$54) -> 0 | F55: =SUM(F$22:F$54) -> 0 | G55: =SUM(G$22:G$54) -> 0

Sheet Traceability
A1: Module | B1: ID Prefix | C1: Test Cases | D1: High Priority | E1: Blocker + Critical | F1: Primary Application Area | G1: Key Risk Focus
A2: API | B2: API | C2: 14 | D2: 1 | E2: 1 | F2: routes/api.php contract surface | G2: Response consistency, status codes, type handling, concurrency
A3: Accessibility | B3: A11Y | C3: 12 | D3: 3 | E3: 0 | F3: Cross-cutting - storefront and admin | G3: Keyboard operation, labels, contrast, screen reader journeys
A4: Admin Authentication | B4: ADM | C4: 10 | D4: 5 | E4: 4 | F4: AdminsController, admin-panel/pages/login.vue | G4: Unauthenticated admin creation, session handling, direct URL access
A5: Authentication | B5: AUTH | C5: 60 | D5: 38 | E5: 22 | F5: app/Http/Controllers/UsersController.php, TwoFactorController, routes/api.php user group | G5: Account takeover, code brute force, enumeration, guest token forgery, scope enforcement
A6: Cart | B6: CART | C6: 27 | D6: 15 | E6: 11 | F6: CartsController, SaveForLaterController, UserWishlistsController, CompareListsController | G6: Client-supplied prices, quantity bounds, IDOR on cart rows, buy-now scope
A7: Catalogue Structure | B7: CAT | C7: 24 | D7: 10 | E7: 3 | F7: CategoriesController, SubCategoriesController, BrandsController, AttributesController | G7: Slug integrity, cascade deletes, image upload safety, stored XSS
A8: Checkout | B8: CHK | C8: 26 | D8: 13 | E8: 10 | F8: OrdersController, Validation::order, frontend-panel/pages/checkout.vue | G8: Payload tampering, guest path, double submit, stock re-check, confirmation email
A9: Compatibility | B9: COMP | C9: 12 | D9: 5 | E9: 0 | F9: Cross-cutting - browsers, devices, email clients | G9: Rendering parity, blockers, degraded modes
A10: Content Management | B10: CMS | C10: 20 | D10: 1 | E10: 2 | F10: PagesController, BannersController, HomeSlidersController, CustomScriptsController | G10: Editor sanitisation, upload validation, stored script feature control
A11: Customer Account | B11: USR | C11: 18 | D11: 4 | E11: 4 | F11: UsersController, UserAddressesController, ContactUsController | G11: Profile and address IDOR, email change verification, data retention
A12: Database | B12: DB | C12: 12 | D12: 8 | E12: 8 | F12: database/migrations, models and relations | G12: Referential integrity, atomicity, monetary precision, reconciliation
A13: End-to-End | B13: E2E | C13: 14 | D13: 11 | E13: 10 | F13: Full stack across all modules | G13: Journey completeness and money, stock and notification reconciliation
... A34: Wallet & Loyalty | B34: WAL | C34: 18 | D34: 13 | E34: 12 | F34: WalletController, WalletOverviewController, LoyaltyGroupController | G34: Balance integrity, unauthenticated access, points timing, concurrent spend
A35: TOTAL | C35: =SUM(C2:C34) -> 0 | D35: =SUM(D2:D34) -> 0 | E35: =SUM(E2:E34) -> 0

Sheet Defect Log
A1: Defect ID | B1: Test Case ID | C1: Module | D1: Summary | E1: Steps to Reproduce | F1: Expected | G1: Actual | H1: Severity | I1: Priority | J1: Environment | K1: Reported By | L1: Reported On | M1: Assigned To | N1: Status | O1: Fixed In Build | P1: Retest Result | Q1: Remarks
A2: DEF-001 | D2: Example row - delete before use. One defect per row; always reference the Test Case ID it came from.

Sheet Test Data
A1: Category | B1: Item | C1: Value / Detail | D1: Notes
A2: Accounts | B2: Superadmin | C2: admin@fixmypc.test / Admin@12345 | D2: Full permissions. Used for every admin-only case.
A3: Accounts | B3: Limited admin (Catalogue Editor) | C3: qa.editor@fixmypc.test / Editor@12345 | D3: Product permissions only. Used for permission-enforcement cases.
A4: Accounts | B4: Vendor A | C4: vendor.a@fixmypc.test / Vendor@12345 | D4: Approved vendor with products, orders and a payout balance.
A5: Accounts | B5: Vendor B | C5: vendor.b@fixmypc.test / Vendor@12345 | D5: Second vendor - the counterparty for cross-vendor isolation cases.
A6: Accounts | B6: Customer A (personal) | C6: qa.personal01@example.com / Passw0rdTest1 | D6: Verified, has order history, saved addresses, wallet balance and points.
A7: Accounts | B7: Customer B (personal) | C7: qa.personal02@example.com / Passw0rdTest1 | D7: The counterparty for every IDOR case - never share resources with A.
A8: Accounts | B8: Customer (business) | C8: qa.business01@example.com / Passw0rdTest1 | D8: Approved business account with a company profile.
A9: Accounts | B9: Customer (trade) | C9: qa.trade01@example.com / Passw0rdTest1 | D9: Approved trade account - used for trade pricing cases.
A10: Accounts | B10: Unverified customer | C10: qa.unverified@example.com / Passw0rdTest1 | D10: Registered but never verified. Do not verify it.
A11: Accounts | B11: Deactivated customer | C11: qa.disabled@example.com / Passw0rdTest1 | D11: Set to inactive. Used for blocked-login cases.
A12: Accounts | B12: 2FA-enabled customer | C12: qa.twofactor@example.com / Passw0rdTest1 | D12: TOTP configured. Keep the seed with the QA lead.
... A55: Boundaries | B55: Awkward money values | C55: 0.01, 19.99, 1234.56, 999999.99 | D55: Precision and rounding checks.

Sheet Environments
A1: Environment Label | B1: Type | C1: Operating System | D1: Browser / Client | E1: Viewport / Device | F1: Purpose
A2: Staging - Chrome 126 (Win 11) | B2: Web UI | C2: Windows 11 | D2: Chrome 126 | E2: 1920x1080 | F2: Primary execution environment for functional, UI and validation cases.
A3: Staging - Postman / REST client | B3: API | C3: Any | D3: Postman / curl | E3: n/a | F3: Direct API cases - security, contract, IDOR and concurrency.
A4: Staging - iOS Safari 17 + Android Chrome 126 | B4: Web UI (mobile) | C4: iOS 17 / Android 13 | D4: Safari 17 / Chrome 126 | E4: iPhone 13, Pixel 6 | F4: Responsive, mobile end-to-end and PWA cases.
A5: Staging - MySQL 8 / phpMyAdmin | B5: Database | C5: Linux | D5: phpMyAdmin / CLI | E5: n/a | F5: Data integrity, reconciliation, migration and backup cases.
A6: Staging - Firefox 127 | B6: Web UI | C6: Windows 11 | D6: Firefox 127 | E6: 1920x1080 | F6: Cross-browser compatibility pass.
A7: Staging - Safari 17 (macOS) | B7: Web UI | C7: macOS Sonoma | D7: Safari 17 | E7: 1440x900 | F7: Cross-browser compatibility pass, payment sheet behaviour.
A8: Staging - Edge 126 | B8: Web UI | C8: Windows 11 | D8: Edge 126 | E8: 1920x1080 | F8: Cross-browser compatibility pass.
A9: Staging - Tablet | B9: Web UI | C9: iPadOS 17 | D9: Safari 17 | E9: 768x1024 | F9: Tablet breakpoint and admin-on-tablet cases.
A10: Staging - Load harness | B10: Performance | C10: Linux | D10: k6 / JMeter | E10: n/a | F10: Load, soak and concurrency cases.
A11: Staging - Assistive tech | B11: Accessibility | C11: Windows 11 / macOS | D11: NVDA / VoiceOver | E11: 1920x1080 | F11: Screen reader and keyboard-only cases.
A12: Pre-production | B12: Full stack | C12: Production parity | D12: Chrome 126 | E12: 1920x1080 | F12: Release-candidate smoke and end-to-end regression only.
A15: ENTRY AND EXIT CRITERIA
A16: Entry criteria | B16: The build is deployed to staging, seed data is loaded, all gateways are in test mode, and the smoke suite E2E-014 passes.
A17: Exit criteria | B17: Every High priority case is executed; no Blocker or Critical defect is open; at least 95% of executed cases pass; all remaining defects are triaged and accepted by the product owner.
A18: Suspension criteria | B18: The smoke suite fails, the environment is unavailable for more than half a day, or a Blocker defect prevents more than 30% of the suite from running.
A19: Resumption criteria | B19: The blocking defect is fixed and verified, and the smoke suite passes again.
A20: Execution order | B20: Run the QA-audit regression cases first (those citing an audit reference in Remarks), then all remaining High priority cases, then Medium, then Low.
