Workbook

Sheet Cover
B2: FixMyPC - Business & Trade Account QA
B3: Personal, Business and Trade accounts: registration, entitlement, pricing, basket, tax, decision emails, admin workflow, state transitions and security.
B6: Document | C6: Business & Trade QA test cases v1.0
B7: Companion to | C7: reference/qa/FixMyPC-Test-Cases-v1.0.xlsx (same columns and vocabulary)
B8: Run date | C8: 14 Sep 2026
B9: Executed by | C9: Automated QA pass (tests/Feature/ManualQaSuiteTest.php)
B10: Environment | C10: Local - Laravel HTTP kernel via PHPUnit, MySQL 8, array mail transport
B12: Total test cases | C12: 223
B13: Executed | C13: 214
B14: Passed | C14: 214
B15: Failed | C15: 0
B16: Blocked | C16: 9
B17: Pass rate (of executed) | C17: 100%
B19: How results were obtained | C19: Each case runs against the real application and database inside a transaction that is rolled back, and asserts the backend result - the stored row, the API payload, the entitlement method the pricing path calls, or the rendered email. Not a screen check.
B20: Suite validity | C20: Two deliberate regressions were introduced and the run repeated, to confirm the cases can fail: removing the suspension check from User::hasBusinessPricing() was caught by 4 cases, removing the duplicate-email guard by 2. Both were reverted.
B21: Severity mapping | C21: The run records Critical/High/Medium/Low. This workbook splits that across the master template vocabulary: Severity is Blocker/Critical/Major/Minor and Priority is High/Medium/Low, so the Dashboard formulas count correctly.
B22: Not signed off | C22: Payment, order and invoice (PAY-01, PAY-02, ORD-01, INV-01) could not be executed. Two are Critical. See the Blocked Items sheet.

Sheet Test Cases
A1: Test Case ID | B1: Module | C1: Feature / Functionality | D1: Test Scenario | E1: Preconditions | F1: Test Steps | G1: Test Data | H1: Expected Result | I1: Actual Result | J1: Priority | K1: Severity | L1: Test Type | M1: Environment | N1: Status | O1: Remarks
A2: AT-PER-01 | B2: Account type | C2: Account type selection and integrity | D2: Personal account type is stored as chosen | E2: No account on the address | F2: POST /api/v1/user/signup with a complete payload for the type | G2: account_type=personal | H2: users.account_type = personal | I2: account_type=personal | J2: High | K2: Major | L2: Functional / Positive | M2: Local - PHPUnit / Laravel HTTP kernel + MySQL 8 | N2: Pass
A3: AT-BUS-01 | B3: Account type | C3: Account type selection and integrity | D3: Business account type is stored as chosen | E3: No account on the address | F3: POST /api/v1/user/signup with a complete payload for the type | G3: account_type=business | H3: users.account_type = business | I3: account_type=business | J3: High | K3: Major | L3: Functional / Positive | M3: Local - PHPUnit / Laravel HTTP kernel + MySQL 8 | N3: Pass
A4: AT-TRA-01 | B4: Account type | C4: Account type selection and integrity | D4: Trade account type is stored as chosen | E4: No account on the address | F4: POST /api/v1/user/signup with a complete payload for the type | G4: account_type=trade | H4: users.account_type = trade | I4: account_type=trade | J4: High | K4: Major | L4: Functional / Positive | M4: Local - PHPUnit / Laravel HTTP kernel + MySQL 8 | N4: Pass
A5: AT-DEF-01 | B5: Account type | C5: Account type selection and integrity | D5: Signup with no account_type defaults to Personal | E5: Legacy caller that sends no account_type | F5: POST /api/v1/user/signup omitting account_type | G5: name, email, password only | H5: Account created as personal, legacy validation used | I5: account_type=personal | J5: Medium | K5: Minor | L5: Functional / Positive | M5: Local - PHPUnit / Laravel HTTP kernel + MySQL 8 | N5: Pass
A6: AT-INV-01 | B6: Account type | C6: Account type selection and integrity | D6: Unknown account_type is refused, not silently defaulted | E6: None | F6: POST /api/v1/user/signup with an invented type | G6: account_type='wholesale' | H6: Validation error on account_type; no account created | I6: status=201 fields=account_type created=no | J6: High | K6: Major | L6: Validation / Negative | M6: Local - PHPUnit / Laravel HTTP kernel + MySQL 8 | N6: Pass
A7: AT-INV-02 | B7: Account type | C7: Account type selection and integrity | D7: Array injected as account_type does not crash or elevate | E7: None | F7: POST signup with an array account_type | G7: account_type=["trade"] | H7: Refused cleanly, no account, no 500 | I7: http=200 status=201 | J7: High | K7: Major | L7: Validation / Negative | M7: Local - PHPUnit / Laravel HTTP kernel + MySQL 8 | N7: Pass
A8: AT-SEC-01 | B8: Account type | C8: Account type selection and integrity | D8: Signup cannot self-approve trade or self-verify | E8: None | F8: POST signup for a trade account with privileged fields injected | G8: trade_status=approved, verified=1, verification_status=verified | H8: trade_status=pending, verified=0, verification=pending, not entitled | I8: trade_status=pending verified=0 verification=pending entitled=no | J8: High | K8: Critical | L8: Validation / Negative | M8: Local - PHPUnit / Laravel HTTP kernel + MySQL 8 | N8: Pass
A9: AT-SEC-02 | B9: Account type | C9: Account type selection and integrity | D9: Personal signup carrying stale trade fields creates no trade profile | E9: Customer switched Trade -> Personal before submitting; form posts whole model | F9: POST signup as personal with the trade block still attached | G9: account_type=personal + company_name, trade, vat_number, resale_confirmed | H9: personal account, no user_business_profiles row, trade_status null | I9: type=personal trade_status=NULL profile=none | J9: High | K9: Major | L9: Functional / Positive | M9: Local - PHPUnit / Laravel HTTP kernel + MySQL 8 | N9: Pass
A10: AT-SEC-03 | B10: Account type | C10: Account type selection and integrity | D10: Trade signup does not persist business-only fields | E10: Customer switched Business -> Trade, business fields still posted | F10: POST signup as trade with the business block attached | G10: account_type=trade + sector, requires_po, credit_application | H10: sector null; requires_po and credit_application false | I10: sector=NULL requires_po=false credit=false | J10: Medium | K10: Minor | L10: Validation / Negative | M10: Local - PHPUnit / Laravel HTTP kernel + MySQL 8 | N10: Pass
A11: AT-SEC-04 | B11: Account type | C11: Account type selection and integrity | D11: Signed-in customer cannot change their own account type | E11: Active personal account | F11: Authenticate as customer, POST /api/v1/user/update-profile | G11: update-profile with account_type=business, trade_status=approved | H11: account_type unchanged, not entitled to business pricing | I11: type=personal entitled=no | J11: High | K11: Critical | L11: Validation / Negative | M11: Local - PHPUnit / Laravel HTTP kernel + MySQL 8 | N11: Pass
A12: REG-B-01 | B12: Business registration | C12: Business account registration | D12: Valid business registration | E12: No account on the address | F12: POST /api/v1/user/signup | G12: complete valid payload | H12: Accepted; account created with the right type | I12: status=200 fields= created=business | J12: High | K12: Major | L12: Functional / Positive | M12: Local - PHPUnit / Laravel HTTP kernel + MySQL 8 | N12: Pass
A13: REG-B-02 | B13: Business registration | C13: Business account registration | D13: Business with no company name | E13: No account on the address | F13: POST /api/v1/user/signup | G13: {"company_name":""} | H13: Rejected with a validation error on 'company_name'; no account created | I13: status=201 fields=company_name created=no | J13: High | K13: Major | L13: Validation / Negative | M13: Local - PHPUnit / Laravel HTTP kernel + MySQL 8 | N13: Pass
... A39: REG-E-03 | B39: Registration edge cases | C39: Registration duplicates and re-registration | D39: Duplicate phone on a verified account is refused | E39: A verified account already holds the number | F39: POST business signup with that phone | G39: Existing verified phone | H39: Validation error on phone | I39: fields=phone | J39: Medium | K39: Minor | L39: Validation / Negative | M39: Local - PHPUnit / Laravel HTTP kernel + MySQL 8 | N39: Pass
A40: REG-E-04 | B40: Registration edge cases | C40: Registration duplicates and re-registration | D40: Re-registering an unverified address overwrites it rather than duplicating | E40: An unverified signup exists on the address | F40: POST business signup, then POST trade signup on the same address | G40: Same email, this time as trade | H40: One user row, now trade, still unverified | I40: rows=1 type=trade verified=0 | J40: Medium | K40: Minor | L40: Functional / Positive | M40: Local - PHPUnit / Laravel HTTP kernel + MySQL 8 | N40: Pass | O40: This is how somebody who lost their code starts again.
A41: REG-E-05 | B41: Registration edge cases | C41: Registration duplicates and re-registration | D41: Suspended account cannot be laundered by re-registering | E41: Unverified account on the address, status suspended | F41: POST business signup on the suspended address | G41: Same email | H41: Refused; status stays suspended | I41: status=201 account_status=suspended | J41: High | K41: Critical | L41: Validation / Negative | M41: Local - PHPUnit / Laravel HTTP kernel + MySQL 8 | N41: Pass
A42: REG-E-06 | B42: Registration edge cases | C42: Registration duplicates and re-registration | D42: Double-clicked submit creates one account, not two | E42: None | F42: POST signup twice with the same payload | G42: Identical business payload posted twice | H42: Exactly one users row | I42: user rows=1 | J42: High | K42: Major | L42: Validation / Negative | M42: Local - PHPUnit / Laravel HTTP kernel + MySQL 8 | N42: Pass
A43: REG-H-01 | B43: Business registration | C43: Business account registration | D43: Very long company name | E43: None | F43: POST /api/v1/user/signup as business | G43: {"company_name":"AAAAAAAAAAAAAAAAAAAAAAAAAAAAAAAAAAAAAAAAAAAAAAAAAAAAAAAAA..."} | H43: Either accepted and stored without corruption, or rejected cleanly. No 500. | I43: accepted; stored company_name=NULL | J43: Low | K43: Minor | L43: Boundary / Negative | M43: Local - PHPUnit / Laravel HTTP kernel + MySQL 8 | N43: Pass
A44: REG-H-02 | B44: Business registration | C44: Business account registration | D44: Company name with special characters | E44: None | F44: POST /api/v1/user/signup as business | G44: {"company_name":"O'Brien & Sons (Kilcock) Ltd \u2014 #1"} | H44: Either accepted and stored without corruption, or rejected cleanly. No 500. | I44: accepted; stored company_name='O\'Brien & Sons (Kilcock) Ltd — #1' | J44: Low | K44: Minor | L44: Boundary / Negative | M44: Local - PHPUnit / Laravel HTTP kernel + MySQL 8 | N44: Pass
A45: REG-H-03 | B45: Business registration | C45: Business account registration | D45: Leading and trailing spaces on company name | E45: None | F45: POST /api/v1/user/signup as business | G45: {"company_name":" Spaced Ltd "} | H45: Either accepted and stored without corruption, or rejected cleanly. No 500. | I45: accepted; stored company_name='Spaced Ltd' | J45: Low | K45: Minor | L45: Boundary / Negative | M45: Local - PHPUnit / Laravel HTTP kernel + MySQL 8 | N45: Pass
A46: REG-H-04 | B46: Business registration | C46: Business account registration | D46: Unicode company name | E46: None | F46: POST /api/v1/user/signup as business | G46: {"company_name":"\u00d3 Briain Teoranta \u65e5\u672c"} | H46: Either accepted and stored without corruption, or rejected cleanly. No 500. | I46: accepted; stored company_name='Ó Briain Teoranta 日本' | J46: Low | K46: Minor | L46: Boundary / Negative | M46: Local - PHPUnit / Laravel HTTP kernel + MySQL 8 | N46: Pass
A47: REG-H-05 | B47: Business registration | C47: Business account registration | D47: HTML injected into company name | E47: None | F47: POST /api/v1/user/signup as business | G47: {"company_name":"<script>alert(1)<\/script>"} | H47: Either accepted and stored without corruption, or rejected cleanly. No 500. | I47: accepted; stored company_name='<script>alert(1)</script>' | J47: Medium | K47: Minor | L47: Security / XSS | M47: Local - PHPUnit / Laravel HTTP kernel + MySQL 8 | N47: Pass
A48: REG-H-06 | B48: Business registration | C48: Business account registration | D48: Very long billing address | E48: None | F48: POST /api/v1/user/signup as business | G48: {"billing_address":"AAAAAAAAAAAAAAAAAAAAAAAAAAAAAAAAAAAAAAAAAAAAAAAAAAAAAAAAA..."} | H48: Either accepted and stored without corruption, or rejected cleanly. No 500. | I48: accepted; stored company_name='QA Supplies Ltd' | J48: Low | K48: Minor | L48: Boundary / Negative | M48: Local - PHPUnit / Laravel HTTP kernel + MySQL 8 | N48: Pass
A49: REG-H-07 | B49: Business registration | C49: Business account registration | D49: Whitespace-only company name is not accepted as a name | E49: None | F49: POST signup as business | G49: company_name=' ' | H49: Rejected on company_name | I49: fields=company_name | J49: Medium | K49: Minor | L49: Boundary / Negative | M49: Local - PHPUnit / Laravel HTTP kernel + MySQL 8 | N49: Pass | O49: TrimStrings middleware should reduce this to empty and required should fire.
A50: REG-H-08 | B50: Business registration | C50: Business account registration | D50: Email with surrounding whitespace is normalised, not rejected | E50: None | F50: POST signup as business | G50: email=' name@example.test ' | H50: Accepted, stored trimmed | I50: status=200 stored=yes | J50: Low | K50: Minor | L50: Boundary / Negative | M50: Local - PHPUnit / Laravel HTTP kernel + MySQL 8 | N50: Pass
A51: PRC-ENT-184D | B51: Pricing | C51: Account-based product pricing | D51: Entitlement flag for Personal | E51: Customer in state: Personal | F51: Read the entitlement the whole pricing path asks | G51: User::hasBusinessPricing() | H51: false | I51: hasBusinessPricing=false | J51: High | K51: Critical | L51: Functional / Positive | M51: Local - PHPUnit / Laravel HTTP kernel + MySQL 8 | N51: Pass
A52: PRC-PDP-184D | B52: Pricing | C52: Account-based product pricing | D52: Product page price for Personal | E52: Customer in state: Personal; product has bands from qty 5 | F52: GET /api/v1/product/{id} authenticated as the customer | G52: product=99240288, quantity 1 | H52: Retail price, because no band covers quantity 1 | I52: display_price=505 (retail 505) | J52: High | K52: Major | L52: Functional / Positive | M52: Local - PHPUnit / Laravel HTTP kernel + MySQL 8 | N52: Pass | O52: Bands on this product start at qty 5, so every account sees retail at qty 1.
A53: PRC-CART-184D | B53: Pricing | C53: Account-based product pricing | D53: Basket unit price at qty 5 for Personal | E53: Customer in state: Personal | F53: Create a basket line at qty 5, GET /api/v1/cart/by-user | G53: product=99240288, quantity 5 (band 5-10 = 450.00) | H53: 505 | I53: unit_price=505.0 (expected 505) | J53: High | K53: Critical | L53: Functional / Positive | M53: Local - PHPUnit / Laravel HTTP kernel + MySQL 8 | N53: Pass
A54: PRC-BAND-184D | B54: Pricing | C54: Account-based product pricing | D54: Advertised bands for Personal | E54: Customer in state: Personal | F54: Read the band table the product page renders | G54: GET /api/v1/business-product/99240288 | H54: Empty list | I54: bands=0 | J54: High | K54: Major | L54: Functional / Positive | M54: Local - PHPUnit / Laravel HTTP kernel + MySQL 8 | N54: Pass
A55: PRC-ENT-D6E6 | B55: Pricing | C55: Account-based product pricing | D55: Entitlement flag for Business | E55: Customer in state: Business | F55: Read the entitlement the whole pricing path asks | G55: User::hasBusinessPricing() | H55: true | I55: hasBusinessPricing=true | J55: High | K55: Critical | L55: Functional / Positive | M55: Local - PHPUnit / Laravel HTTP kernel + MySQL 8 | N55: Pass
A56: PRC-PDP-D6E6 | B56: Pricing | C56: Account-based product pricing | D56: Product page price for Business | E56: Customer in state: Business; product has bands from qty 5 | F56: GET /api/v1/product/{id} authenticated as the customer | G56: product=99240288, quantity 1 | H56: Retail price, because no band covers quantity 1 | I56: display_price=505 (retail 505) | J56: High | K56: Major | L56: Functional / Positive | M56: Local - PHPUnit / Laravel HTTP kernel + MySQL 8 | N56: Pass | O56: Bands on this product start at qty 5, so every account sees retail at qty 1.
A57: PRC-CART-D6E6 | B57: Pricing | C57: Account-based product pricing | D57: Basket unit price at qty 5 for Business | E57: Customer in state: Business | F57: Create a basket line at qty 5, GET /api/v1/cart/by-user | G57: product=99240288, quantity 5 (band 5-10 = 450.00) | H57: 450.00 | I57: unit_price=450.0 (expected 450) | J57: High | K57: Critical | L57: Functional / Positive | M57: Local - PHPUnit / Laravel HTTP kernel + MySQL 8 | N57: Pass
A58: PRC-BAND-D6E6 | B58: Pricing | C58: Account-based product pricing | D58: Advertised bands for Business | E58: Customer in state: Business | F58: Read the band table the product page renders | G58: GET /api/v1/business-product/99240288 | H58: Bands returned | I58: bands=3 | J58: High | K58: Major | L58: Functional / Positive | M58: Local - PHPUnit / Laravel HTTP kernel + MySQL 8 | N58: Pass
A59: PRC-ENT-13CE | B59: Pricing | C59: Account-based product pricing | D59: Entitlement flag for Trade pending | E59: Customer in state: Trade pending | F59: Read the entitlement the whole pricing path asks | G59: User::hasBusinessPricing() | H59: false | I59: hasBusinessPricing=false | J59: High | K59: Critical | L59: Functional / Positive | M59: Local - PHPUnit / Laravel HTTP kernel + MySQL 8 | N59: Pass
A60: PRC-PDP-13CE | B60: Pricing | C60: Account-based product pricing | D60: Product page price for Trade pending | E60: Customer in state: Trade pending; product has bands from qty 5 | F60: GET /api/v1/product/{id} authenticated as the customer | G60: product=99240288, quantity 1 | H60: Retail price, because no band covers quantity 1 | I60: display_price=505 (retail 505) | J60: High | K60: Major | L60: Functional / Positive | M60: Local - PHPUnit / Laravel HTTP kernel + MySQL 8 | N60: Pass | O60: Bands on this product start at qty 5, so every account sees retail at qty 1.
A61: PRC-CART-13CE | B61: Pricing | C61: Account-based product pricing | D61: Basket unit price at qty 5 for Trade pending | E61: Customer in state: Trade pending | F61: Create a basket line at qty 5, GET /api/v1/cart/by-user | G61: product=99240288, quantity 5 (band 5-10 = 450.00) | H61: 505 | I61: unit_price=505.0 (expected 505) | J61: High | K61: Critical | L61: Functional / Positive | M61: Local - PHPUnit / Laravel HTTP kernel + MySQL 8 | N61: Pass
A62: PRC-BAND-13CE | B62: Pricing | C62: Account-based product pricing | D62: Advertised bands for Trade pending | E62: Customer in state: Trade pending | F62: Read the band table the product page renders | G62: GET /api/v1/business-product/99240288 | H62: Empty list | I62: bands=0 | J62: High | K62: Major | L62: Functional / Positive | M62: Local - PHPUnit / Laravel HTTP kernel + MySQL 8 | N62: Pass
A63: PRC-ENT-8D2A | B63: Pricing | C63: Account-based product pricing | D63: Entitlement flag for Trade approved | E63: Customer in state: Trade approved | F63: Read the entitlement the whole pricing path asks | G63: User::hasBusinessPricing() | H63: true | I63: hasBusinessPricing=true | J63: High | K63: Critical | L63: Functional / Positive | M63: Local - PHPUnit / Laravel HTTP kernel + MySQL 8 | N63: Pass
A64: PRC-PDP-8D2A | B64: Pricing | C64: Account-based product pricing | D64: Product page price for Trade approved | E64: Customer in state: Trade approved; product has bands from qty 5 | F64: GET /api/v1/product/{id} authenticated as the customer | G64: product=99240288, quantity 1 | H64: Retail price, because no band covers quantity 1 | I64: display_price=505 (retail 505) | J64: High | K64: Major | L64: Functional / Positive | M64: Local - PHPUnit / Laravel HTTP kernel + MySQL 8 | N64: Pass | O64: Bands on this product start at qty 5, so every account sees retail at qty 1.
A65: PRC-CART-8D2A | B65: Pricing | C65: Account-based product pricing | D65: Basket unit price at qty 5 for Trade approved | E65: Customer in state: Trade approved | F65: Create a basket line at qty 5, GET /api/v1/cart/by-user | G65: product=99240288, quantity 5 (band 5-10 = 450.00) | H65: 450.00 | I65: unit_price=450.0 (expected 450) | J65: High | K65: Critical | L65: Functional / Positive | M65: Local - PHPUnit / Laravel HTTP kernel + MySQL 8 | N65: Pass
A66: PRC-BAND-8D2A | B66: Pricing | C66: Account-based product pricing | D66: Advertised bands for Trade approved | E66: Customer in state: Trade approved | F66: Read the band table the product page renders | G66: GET /api/v1/business-product/99240288 | H66: Bands returned | I66: bands=3 | J66: High | K66: Major | L66: Functional / Positive | M66: Local - PHPUnit / Laravel HTTP kernel + MySQL 8 | N66: Pass
A67: PRC-ENT-A2D8 | B67: Pricing | C67: Account-based product pricing | D67: Entitlement flag for Trade rejected | E67: Customer in state: Trade rejected | F67: Read the entitlement the whole pricing path asks | G67: User::hasBusinessPricing() | H67: false | I67: hasBusinessPricing=false | J67: High | K67: Critical | L67: Validation / Negative | M67: Local - PHPUnit / Laravel HTTP kernel + MySQL 8 | N67: Pass
A68: PRC-PDP-A2D8 | B68: Pricing | C68: Account-based product pricing | D68: Product page price for Trade rejected | E68: Customer in state: Trade rejected; product has bands from qty 5 | F68: GET /api/v1/product/{id} authenticated as the customer | G68: product=99240288, quantity 1 | H68: Retail price, because no band covers quantity 1 | I68: display_price=505 (retail 505) | J68: High | K68: Major | L68: Validation / Negative | M68: Local - PHPUnit / Laravel HTTP kernel + MySQL 8 | N68: Pass | O68: Bands on this product start at qty 5, so every account sees retail at qty 1.
A69: PRC-CART-A2D8 | B69: Pricing | C69: Account-based product pricing | D69: Basket unit price at qty 5 for Trade rejected | E69: Customer in state: Trade rejected | F69: Create a basket line at qty 5, GET /api/v1/cart/by-user | G69: product=99240288, quantity 5 (band 5-10 = 450.00) | H69: 505 | I69: unit_price=505.0 (expected 505) | J69: High | K69: Critical | L69: Validation / Negative | M69: Local - PHPUnit / Laravel HTTP kernel + MySQL 8 | N69: Pass
A70: PRC-BAND-A2D8 | B70: Pricing | C70: Account-based product pricing | D70: Advertised bands for Trade rejected | E70: Customer in state: Trade rejected | F70: Read the band table the product page renders | G70: GET /api/v1/business-product/99240288 | H70: Empty list | I70: bands=0 | J70: High | K70: Major | L70: Validation / Negative | M70: Local - PHPUnit / Laravel HTTP kernel + MySQL 8 | N70: Pass
A71: PRC-ENT-5928 | B71: Pricing | C71: Account-based product pricing | D71: Entitlement flag for Trade suspended | E71: Customer in state: Trade suspended | F71: Read the entitlement the whole pricing path asks | G71: User::hasBusinessPricing() | H71: false | I71: hasBusinessPricing=false | J71: High | K71: Critical | L71: Functional / Positive | M71: Local - PHPUnit / Laravel HTTP kernel + MySQL 8 | N71: Pass
A72: PRC-PDP-5928 | B72: Pricing | C72: Account-based product pricing | D72: Product page price for Trade suspended | E72: Customer in state: Trade suspended; product has bands from qty 5 | F72: GET /api/v1/product/{id} authenticated as the customer | G72: product=99240288, quantity 1 | H72: Retail price, because no band covers quantity 1 | I72: display_price=505 (retail 505) | J72: High | K72: Major | L72: Functional / Positive | M72: Local - PHPUnit / Laravel HTTP kernel + MySQL 8 | N72: Pass | O72: Bands on this product start at qty 5, so every account sees retail at qty 1.
A73: PRC-CART-5928 | B73: Pricing | C73: Account-based product pricing | D73: Basket unit price at qty 5 for Trade suspended | E73: Customer in state: Trade suspended | F73: Create a basket line at qty 5, GET /api/v1/cart/by-user | G73: product=99240288, quantity 5 (band 5-10 = 450.00) | H73: 505 | I73: unit_price=505.0 (expected 505) | J73: High | K73: Critical | L73: Functional / Positive | M73: Local - PHPUnit / Laravel HTTP kernel + MySQL 8 | N73: Pass
A74: PRC-BAND-5928 | B74: Pricing | C74: Account-based product pricing | D74: Advertised bands for Trade suspended | E74: Customer in state: Trade suspended | F74: Read the band table the product page renders | G74: GET /api/v1/business-product/99240288 | H74: Empty list | I74: bands=0 | J74: High | K74: Major | L74: Functional / Positive | M74: Local - PHPUnit / Laravel HTTP kernel + MySQL 8 | N74: Pass
A75: PRC-ENT-9991 | B75: Pricing | C75: Account-based product pricing | D75: Entitlement flag for Account suspended | E75: Customer in state: Account suspended | F75: Read the entitlement the whole pricing path asks | G75: User::hasBusinessPricing() | H75: false | I75: hasBusinessPricing=false | J75: High | K75: Critical | L75: Functional / Positive | M75: Local - PHPUnit / Laravel HTTP kernel + MySQL 8 | N75: Pass
A76: PRC-PDP-9991 | B76: Pricing | C76: Account-based product pricing | D76: Product page price for Account suspended | E76: Customer in state: Account suspended; product has bands from qty 5 | F76: GET /api/v1/product/{id} authenticated as the customer | G76: product=99240288, quantity 1 | H76: Retail price, because no band covers quantity 1 | I76: display_price=505 (retail 505) | J76: High | K76: Major | L76: Functional / Positive | M76: Local - PHPUnit / Laravel HTTP kernel + MySQL 8 | N76: Pass | O76: Bands on this product start at qty 5, so every account sees retail at qty 1.
A77: PRC-CART-9991 | B77: Pricing | C77: Account-based product pricing | D77: Basket unit price at qty 5 for Account suspended | E77: Customer in state: Account suspended | F77: Create a basket line at qty 5, GET /api/v1/cart/by-user | G77: product=99240288, quantity 5 (band 5-10 = 450.00) | H77: 505 | I77: unit_price=505.0 (expected 505) | J77: High | K77: Critical | L77: Functional / Positive | M77: Local - PHPUnit / Laravel HTTP kernel + MySQL 8 | N77: Pass
A78: PRC-BAND-9991 | B78: Pricing | C78: Account-based product pricing | D78: Advertised bands for Account suspended | E78: Customer in state: Account suspended | F78: Read the band table the product page renders | G78: GET /api/v1/business-product/99240288 | H78: Empty list | I78: bands=0 | J78: High | K78: Major | L78: Functional / Positive | M78: Local - PHPUnit / Laravel HTTP kernel + MySQL 8 | N78: Pass
A79: QTY-B-001 | B79: Quantity bands | C79: Business quantity band pricing | D79: Business basket unit price at quantity 1 | E79: Business account; product 99240288 with bands 5-10, 11-20, 21-30 | F79: Create the basket line at that quantity, read /api/v1/cart/by-user | G79: quantity=1 | H79: 505.00 (retail, no band covers it) | I79: unit_price=505.0 expected=505 | J79: High | K79: Major | L79: Boundary | M79: Local - PHPUnit / Laravel HTTP kernel + MySQL 8 | N79: Pass
A80: QTY-B-002 | B80: Quantity bands | C80: Business quantity band pricing | D80: Business basket unit price at quantity 2 | E80: Business account; product 99240288 with bands 5-10, 11-20, 21-30 | F80: Create the basket line at that quantity, read /api/v1/cart/by-user | G80: quantity=2 | H80: 505.00 (retail, no band covers it) | I80: unit_price=505.0 expected=505 | J80: High | K80: Major | L80: Boundary | M80: Local - PHPUnit / Laravel HTTP kernel + MySQL 8 | N80: Pass
A81: QTY-B-004 | B81: Quantity bands | C81: Business quantity band pricing | D81: Business basket unit price at quantity 4 | E81: Business account; product 99240288 with bands 5-10, 11-20, 21-30 | F81: Create the basket line at that quantity, read /api/v1/cart/by-user | G81: quantity=4 | H81: 505.00 (retail, no band covers it) | I81: unit_price=505.0 expected=505 | J81: High | K81: Major | L81: Boundary | M81: Local - PHPUnit / Laravel HTTP kernel + MySQL 8 | N81: Pass
A82: QTY-B-005 | B82: Quantity bands | C82: Business quantity band pricing | D82: Business basket unit price at quantity 5 | E82: Business account; product 99240288 with bands 5-10, 11-20, 21-30 | F82: Create the basket line at that quantity, read /api/v1/cart/by-user | G82: quantity=5 | H82: 450.00 (band) | I82: unit_price=450.0 expected=450 | J82: High | K82: Major | L82: Boundary | M82: Local - PHPUnit / Laravel HTTP kernel + MySQL 8 | N82: Pass
A83: QTY-B-006 | B83: Quantity bands | C83: Business quantity band pricing | D83: Business basket unit price at quantity 6 | E83: Business account; product 99240288 with bands 5-10, 11-20, 21-30 | F83: Create the basket line at that quantity, read /api/v1/cart/by-user | G83: quantity=6 | H83: 450.00 (band) | I83: unit_price=450.0 expected=450 | J83: High | K83: Major | L83: Boundary | M83: Local - PHPUnit / Laravel HTTP kernel + MySQL 8 | N83: Pass
A84: QTY-B-009 | B84: Quantity bands | C84: Business quantity band pricing | D84: Business basket unit price at quantity 9 | E84: Business account; product 99240288 with bands 5-10, 11-20, 21-30 | F84: Create the basket line at that quantity, read /api/v1/cart/by-user | G84: quantity=9 | H84: 450.00 (band) | I84: unit_price=450.0 expected=450 | J84: High | K84: Major | L84: Boundary | M84: Local - PHPUnit / Laravel HTTP kernel + MySQL 8 | N84: Pass
A85: QTY-B-010 | B85: Quantity bands | C85: Business quantity band pricing | D85: Business basket unit price at quantity 10 | E85: Business account; product 99240288 with bands 5-10, 11-20, 21-30 | F85: Create the basket line at that quantity, read /api/v1/cart/by-user | G85: quantity=10 | H85: 450.00 (band) | I85: unit_price=450.0 expected=450 | J85: High | K85: Major | L85: Boundary | M85: Local - PHPUnit / Laravel HTTP kernel + MySQL 8 | N85: Pass
A86: QTY-B-011 | B86: Quantity bands | C86: Business quantity band pricing | D86: Business basket unit price at quantity 11 | E86: Business account; product 99240288 with bands 5-10, 11-20, 21-30 | F86: Create the basket line at that quantity, read /api/v1/cart/by-user | G86: quantity=11 | H86: 430.00 (band) | I86: unit_price=430.0 expected=430 | J86: High | K86: Major | L86: Boundary | M86: Local - PHPUnit / Laravel HTTP kernel + MySQL 8 | N86: Pass
A87: QTY-B-020 | B87: Quantity bands | C87: Business quantity band pricing | D87: Business basket unit price at quantity 20 | E87: Business account; product 99240288 with bands 5-10, 11-20, 21-30 | F87: Create the basket line at that quantity, read /api/v1/cart/by-user | G87: quantity=20 | H87: 430.00 (band) | I87: unit_price=430.0 expected=430 | J87: High | K87: Major | L87: Boundary | M87: Local - PHPUnit / Laravel HTTP kernel + MySQL 8 | N87: Pass
A88: QTY-B-021 | B88: Quantity bands | C88: Business quantity band pricing | D88: Business basket unit price at quantity 21 | E88: Business account; product 99240288 with bands 5-10, 11-20, 21-30 | F88: Create the basket line at that quantity, read /api/v1/cart/by-user | G88: quantity=21 | H88: 420.00 (band) | I88: unit_price=420.0 expected=420 | J88: High | K88: Major | L88: Boundary | M88: Local - PHPUnit / Laravel HTTP kernel + MySQL 8 | N88: Pass
... A92: QTY-B-051 | B92: Quantity bands | C92: Business quantity band pricing | D92: Business basket unit price at quantity 51 | E92: Business account; product 99240288 with bands 5-10, 11-20, 21-30 | F92: Create the basket line at that quantity, read /api/v1/cart/by-user | G92: quantity=51 | H92: 505.00 (retail, no band covers it) | I92: unit_price=505.0 expected=505 | J92: High | K92: Major | L92: Boundary | M92: Local - PHPUnit / Laravel HTTP kernel + MySQL 8 | N92: Pass
A93: QTY-P-005 | B93: Quantity bands | C93: Business quantity band pricing | D93: Personal account gets no band at quantity 5 | E93: Personal account; same banded product | F93: Create the basket line, read /api/v1/cart/by-user | G93: quantity=5 | H93: 505.00 at every quantity | I93: unit_price=505.0 expected=505 | J93: High | K93: Critical | L93: Boundary | M93: Local - PHPUnit / Laravel HTTP kernel + MySQL 8 | N93: Pass | O93: Buying in bulk must not be a route to trade rates.
A94: QTY-P-011 | B94: Quantity bands | C94: Business quantity band pricing | D94: Personal account gets no band at quantity 11 | E94: Personal account; same banded product | F94: Create the basket line, read /api/v1/cart/by-user | G94: quantity=11 | H94: 505.00 at every quantity | I94: unit_price=505.0 expected=505 | J94: High | K94: Critical | L94: Boundary | M94: Local - PHPUnit / Laravel HTTP kernel + MySQL 8 | N94: Pass | O94: Buying in bulk must not be a route to trade rates.
A95: QTY-P-021 | B95: Quantity bands | C95: Business quantity band pricing | D95: Personal account gets no band at quantity 21 | E95: Personal account; same banded product | F95: Create the basket line, read /api/v1/cart/by-user | G95: quantity=21 | H95: 505.00 at every quantity | I95: unit_price=505.0 expected=505 | J95: High | K95: Critical | L95: Boundary | M95: Local - PHPUnit / Laravel HTTP kernel + MySQL 8 | N95: Pass | O95: Buying in bulk must not be a route to trade rates.
A96: QTY-P-050 | B96: Quantity bands | C96: Business quantity band pricing | D96: Personal account gets no band at quantity 50 | E96: Personal account; same banded product | F96: Create the basket line, read /api/v1/cart/by-user | G96: quantity=50 | H96: 505.00 at every quantity | I96: unit_price=505.0 expected=505 | J96: High | K96: Critical | L96: Boundary | M96: Local - PHPUnit / Laravel HTTP kernel + MySQL 8 | N96: Pass | O96: Buying in bulk must not be a route to trade rates.
A97: QTY-DIR-01 | B97: Quantity bands | C97: Business quantity band pricing | D97: Increasing then decreasing quantity re-prices both ways | E97: Business account, one basket line | F97: POST /api/v1/cart/action with deltas, reading the stored price each time | G97: qty 1 -> 5 -> 1 (the seeded variant holds 6 units, no backorder) | H97: retail at 1, 450.00 at 5, retail again at 1 | I97: 1=>505 5=>450 1=>505 | J97: High | K97: Major | L97: Boundary | M97: Local - PHPUnit / Laravel HTTP kernel + MySQL 8 | N97: Pass
A98: CART-A-01 | B98: Cart repricing | C98: Server-side basket re-pricing | D98: Scenario A: retail basket re-prices when the account gains entitlement | E98: Personal account with a qty-5 line priced at retail | F98: Create line, change account type in the database, re-read the basket | G98: qty 5, then account_type becomes business | H98: Unit price moves from retail to the 450.00 band | I98: before=505 after=450 | J98: High | K98: Critical | L98: Functional / Positive | M98: Local - PHPUnit / Laravel HTTP kernel + MySQL 8 | N98: Pass
A99: CART-B-01 | B99: Cart repricing | C99: Server-side basket re-pricing | D99: Scenario B: guest basket handed to a business account re-prices | E99: Guest basket at retail, merged onto a business account at sign-in | F99: Build the guest line, perform the merge, re-read the basket | G99: qty 5 guest line, user_token cleared and user_id set | H99: 450.00, and carts.price updated in the database | I99: unit_price=450 carts.price=450 | J99: High | K99: Critical | L99: Functional / Positive | M99: Local - PHPUnit / Laravel HTTP kernel + MySQL 8 | N99: Pass
A100: CART-C-01 | B100: Cart repricing | C100: Server-side basket re-pricing | D100: Scenario C: basket re-prices when the trade application is approved | E100: Trade pending account with a qty-5 line | F100: Create line, approve, re-read the basket | G100: Trade status moves pending -> approved | H100: retail before approval, 450.00 after | I100: before=505 after=450 | J100: High | K100: Critical | L100: Functional / Positive | M100: Local - PHPUnit / Laravel HTTP kernel + MySQL 8 | N100: Pass
A101: CART-D-01 | B101: Cart repricing | C101: Server-side basket re-pricing | D101: Scenario D: trade prices leave the basket when trade is suspended | E101: Approved trade account with a qty-5 line at 450.00 | F101: Create line, read it, suspend trade pricing, re-read | G101: Trade status moves approved -> suspended | H101: 450.00 then retail; stored price updated too | I101: before=450 after=505 carts.price=505 | J101: High | K101: Critical | L101: Functional / Positive | M101: Local - PHPUnit / Laravel HTTP kernel + MySQL 8 | N101: Pass
A102: CART-D-02 | B102: Cart repricing | C102: Server-side basket re-pricing | D102: Suspending the whole account also strips trade prices from the basket | E102: Approved trade account with a qty-5 line at 450.00 | F102: Create line, suspend the account, re-read the basket | G102: Account status moves active -> suspended | H102: Retail price | I102: before=450 after=505 | J102: High | K102: Critical | L102: Functional / Positive | M102: Local - PHPUnit / Laravel HTTP kernel + MySQL 8 | N102: Pass
A103: CART-D-03 | B103: Cart repricing | C103: Server-side basket re-pricing | D103: Reactivating the account restores trade prices in the basket | E103: Suspended approved-trade account with a qty-5 line | F103: Read while suspended, reactivate, re-read | G103: Account status suspended -> active | H103: retail while suspended, 450.00 once active again | I103: suspended=505 reactivated=450 | J103: High | K103: Major | L103: Functional / Positive | M103: Local - PHPUnit / Laravel HTTP kernel + MySQL 8 | N103: Pass
A104: CART-E-01 | B104: Cart repricing | C104: Server-side basket re-pricing | D104: Scenario E: catalogue price change is picked up by an existing basket | E104: Personal account with a line at the old price | F104: Create line, change the price that governs it, re-read the basket | G104: The chosen variation is re-priced to 777.00 after the line was created | H104: Basket shows 777.00, not the price banked when the line was added | I104: before=505 after=777 | J104: High | K104: Major | L104: Validation / Negative | M104: Local - PHPUnit / Laravel HTTP kernel + MySQL 8 | N104: Pass | O104: The buyable rows on this product are variations carrying their own price, and a variant price outranks products.selling by design, so the variant is the figure to move here.
A105: CART-SEC-01 | B105: Cart repricing | C105: Server-side basket re-pricing | D105: A hand-edited basket row is corrected on read | E105: Personal account; carts.price tampered to 0.01 | F105: Write 0.01 into the row, read the basket through the API | G105: Direct UPDATE on carts.price and original_price | H105: Retail price returned and written back to the row | I105: unit_price=505 carts.price=505 | J105: High | K105: Critical | L105: Functional / Positive | M105: Local - PHPUnit / Laravel HTTP kernel + MySQL 8 | N105: Pass
A106: CART-SEC-02 | B106: Cart repricing | C106: Server-side basket re-pricing | D106: A price submitted with add-to-basket is ignored | E106: Personal account | F106: Add to basket sending a price, read the stored row | G106: POST /api/v1/cart/action with price=0.01 | H106: Stored price is the catalogue price | I106: carts.price=505 | J106: High | K106: Critical | L106: Functional / Positive | M106: Local - PHPUnit / Laravel HTTP kernel + MySQL 8 | N106: Pass
A107: CART-ISO-01 | B107: Cart isolation | C107: Basket ownership and isolation | D107: Customer A cannot see customer B basket lines | E107: Two customers, each with a basket line | F107: Read the basket as A and check B line id is absent | G107: Two accounts, one product | H107: Only the caller own lines are returned | I107: ids=1044 | J107: High | K107: Critical | L107: Validation / Negative | M107: Local - PHPUnit / Laravel HTTP kernel + MySQL 8 | N107: Pass
A108: TAX-01 | B108: Tax | C108: VAT and tax rules | D108: VAT-inclusive product adds no tax on top, for any account type | E108: Product with excludeVAT = 0 | F108: Pricing::unitTax with productTaxable false | G108: rule 1 (23%, percentage), unit 100.00, excludeVAT=0 | H108: 0.00 | I108: unitTax=0 | J108: High | K108: Major | L108: Functional / Positive | M108: Local - PHPUnit / Laravel HTTP kernel + MySQL 8 | N108: Pass | O108: Existing store behaviour recorded as TAX-01 in the earlier audit; unchanged.
A109: TAX-02 | B109: Tax | C109: VAT and tax rules | D109: VAT-exclusive product on rule 1 adds 23 percent | E109: Product with excludeVAT = 1 and tax_rule_id = 1 | F109: Pricing::unitTax with productTaxable true | G109: unit 100.00 | H109: 23.00 | I109: unitTax=23 | J109: High | K109: Major | L109: Functional / Positive | M109: Local - PHPUnit / Laravel HTTP kernel + MySQL 8 | N109: Pass
A110: TAX-03 | B110: Tax | C110: VAT and tax rules | D110: A product on tax rule 2 uses rule 2, not rule 1 | E110: tax_rules row 2 = VAT Margin at 0 percent | F110: Pricing::unitTax with the rule the product actually carries | G110: unit 100.00, rule 2, excludeVAT = 1 | H110: 0.00, because rule 2 charges 0 percent | I110: rule2 rate=0 unitTax=0 | J110: High | K110: Major | L110: Validation / Negative | M110: Local - PHPUnit / Laravel HTTP kernel + MySQL 8 | N110: Pass | O110: Guards against assuming tax rule id 1 anywhere in the stack.
A111: TAX-04 | B111: Tax | C111: VAT and tax rules | D111: VAT is charged on the band price, not the retail price | E111: Business account buying into a band | F111: Price the unit with bands, then compute tax on that figure | G111: retail 100.00, band 60.00 at qty 10, rule 1 at 23 percent | H111: 13.80, not 23.00 | I111: unit=60 unitTax=13.8 | J111: High | K111: Critical | L111: Validation / Negative | M111: Local - PHPUnit / Laravel HTTP kernel + MySQL 8 | N111: Pass
A112: TAX-05 | B112: Tax | C112: VAT and tax rules | D112: A flat tax rule does not scale with the band price | E112: A tax rule of type FLAT | F112: Pricing::unitTax on both unit prices | G112: flat 5.00 against unit 100.00 and unit 60.00 | H112: 5.00 in both cases | I112: at100=5 at60=5 | J112: Medium | K112: Minor | L112: Validation / Negative | M112: Local - PHPUnit / Laravel HTTP kernel + MySQL 8 | N112: Pass
A113: TAX-06 | B113: Tax | C113: VAT and tax rules | D113: Missing tax rule yields no tax rather than an error | E113: Product whose tax_rules relation is null | F113: Pricing::unitTax(null, 100, true) | G113: taxRule = null, unit 100.00 | H113: 0.00 and no exception | I113: unitTax=0 | J113: Medium | K113: Minor | L113: Functional / Positive | M113: Local - PHPUnit / Laravel HTTP kernel + MySQL 8 | N113: Pass
A114: TAX-07 | B114: Tax | C114: VAT and tax rules | D114: Free bundle units are not taxed | E114: A buy-X-get-Y bundle on the line | F114: bundleFreeQuantity then tax on the payable quantity | G114: qty 3, bundle buy 2 free 1, unit 100.00, rule 1 | H114: Tax charged on 2 units (46.00), not 3 | I114: free=1 payable=2 tax=46 | J114: High | K114: Major | L114: Validation / Negative | M114: Local - PHPUnit / Laravel HTTP kernel + MySQL 8 | N114: Pass
A115: TRD-APP-01 | B115: Trade approval | C115: Admin trade approval | D115: Authorised admin approves a pending application end to end | E115: Trade account, trade_status = pending, with a company profile | F115: Approve, then read status, entitlement, bands, dashboard and outbox | G115: POST admin/trade-application/action with trade_status=approved | H115: approved, entitled, bands visible, dashboard approved, one email | I115: http_status=200 trade_status=approved verification=verified entitled=true dashboard=approved bands=3 emails=1 | J115: High | K115: Critical | L115: Functional / Positive | M115: Local - PHPUnit / Laravel HTTP kernel + MySQL 8 | N115: Pass
A116: TRD-APP-02 | B116: Trade approval | C116: Admin trade approval | D116: Approval email subject, recipient and content | E116: Pending trade application for Quinn Electrical Ltd | F116: Approve and inspect the rendered message | G116: Approve with a note | H116: Subject exactly "Your Trade Account Has Been Approved", to the applicant, naming the company | I116: subject=Your Trade Account Has Been Approved to=qa.6aa7c203d3736@example.test company=Y note=Y | J116: High | K116: Major | L116: Functional / Positive | M116: Local - PHPUnit / Laravel HTTP kernel + MySQL 8 | N116: Pass
A117: TRD-APP-03 | B117: Trade approval | C117: Admin trade approval | D117: Approval email carries a plain-text alternative | E117: Pending trade application | F117: Inspect the MIME parts of the message | G117: Approve | H117: A text/plain child part is present and non-trivial | I117: parts=text/plain:765 | J117: Low | K117: Minor | L117: Functional / Positive | M117: Local - PHPUnit / Laravel HTTP kernel + MySQL 8 | N117: Pass
A118: TRD-REJ-01 | B118: Trade rejection | C118: Admin trade rejection | D118: Rejection updates status, withholds entitlement and emails once | E118: Trade account, trade_status = pending | F118: Reject, then read status, entitlement, bands, dashboard and outbox | G118: trade_status=rejected with a customer-facing note | H118: rejected, not entitled, no bands, dashboard rejected, one email, still able to check out | I118: trade_status=rejected entitled=false can_checkout=true dashboard=rejected bands=0 emails=1 | J118: High | K118: Critical | L118: Validation / Negative | M118: Local - PHPUnit / Laravel HTTP kernel + MySQL 8 | N118: Pass
A119: TRD-REJ-02 | B119: Trade rejection | C119: Admin trade rejection | D119: Rejection email subject, reason and support route | E119: Pending application | F119: Reject and inspect the rendered message | G119: Reject with a customer-safe reason | H119: Subject exactly "Update on Your Trade Account Application", reason shown, support contact present | I119: subject=Update on Your Trade Account Application reason=Y status=Y support=Y | J119: High | K119: Major | L119: Validation / Negative | M119: Local - PHPUnit / Laravel HTTP kernel + MySQL 8 | N119: Pass
A120: TRD-REJ-03 | B120: Trade rejection | C120: Admin trade rejection | D120: Rejection email exposes no internal identifiers | E120: Pending application with a VAT number on file | F120: Scan the rendered message for ids, column names and the VAT number | G120: Reject with a note | H120: No user id, no column names, no VAT number | I120: no leaks found | J120: High | K120: Major | L120: Validation / Negative | M120: Local - PHPUnit / Laravel HTTP kernel + MySQL 8 | N120: Pass
A121: TRD-REJ-04 | B121: Trade rejection | C121: Admin trade rejection | D121: Rejection with no note omits the reason block entirely | E121: Pending application | F121: Reject with no note and inspect the message | G121: trade_review_note = null | H121: No empty reason heading; the rest of the email still reads | I121: reason_block=absent | J121: Low | K121: Minor | L121: Validation / Negative | M121: Local - PHPUnit / Laravel HTTP kernel + MySQL 8 | N121: Pass
A122: NOT-DUP-01 | B122: Notifications | C122: Trade decision emails | D122: Repeating the same approval does not re-email | E122: Pending application | F122: POST approve, POST approve again, count the outbox | G122: Approve twice with different notes | H122: One email; the second call still succeeds and saves the new note | I122: emails=1 second_status=200 triggered=false note=Corrected note. | J122: High | K122: Major | L122: Validation / Negative | M122: Local - PHPUnit / Laravel HTTP kernel + MySQL 8 | N122: Pass
... A124: NOT-DUP-03 | B124: Notifications | C124: Trade decision emails | D124: Repeated rejection does not re-email | E124: Pending application | F124: POST reject x3, count the outbox | G124: Reject three times | H124: One email | I124: emails=1 | J124: High | K124: Major | L124: Validation / Negative | M124: Local - PHPUnit / Laravel HTTP kernel + MySQL 8 | N124: Pass
A125: NOT-DUP-04 | B125: Notifications | C125: Trade decision emails | D125: Rejected to pending to approved produces a fresh approval email | E125: Pending application | F125: Three decisions in sequence, inspect the outbox | G125: reject, back to pending, approve | H125: Two emails: rejection then approval. Back-to-pending emails nobody. | I125: emails=2 subjects=Update on Your Trade Account Application | Your Trade Account Has Been Approved | J125: High | K125: Major | L125: Validation / Negative | M125: Local - PHPUnit / Laravel HTTP kernel + MySQL 8 | N125: Pass | O125: The duplicate rule must not block a legitimate later decision.
A126: NOT-DUP-05 | B126: Notifications | C126: Trade decision emails | D126: A losing race reports no transition and sends nothing | E126: Two requests hold the application while it still says pending | F126: Load model, update the row underneath it, call applyTrade on the stale model | G126: Row moved to approved between load and write | H126: transitioned = false and the stale note is not written | I126: transitioned=false note=NULL | J126: High | K126: Major | L126: Validation / Negative | M126: Local - PHPUnit / Laravel HTTP kernel + MySQL 8 | N126: Pass
A127: NOT-FAIL-01 | B127: Notification failure | C127: Trade decision email failure handling | D127: Mail transport failure does not reverse the approval | E127: Pending application; mailer throws on send | F127: Mock Mail::send to throw, approve, read status and entitlement | G127: Swift_TransportException | H127: approved and entitled; response reports delivered=false | I127: status=200 trade_status=approved entitled=true delivered=false | J127: High | K127: Critical | L127: Validation / Negative | M127: Local - PHPUnit / Laravel HTTP kernel + MySQL 8 | N127: Pass
A128: NOT-FAIL-02 | B128: Notification failure | C128: Trade decision email failure handling | D128: Customer with no email address is still approved | E128: Trade application whose users.email is null | F128: Approve and inspect status, entitlement and outbox | G128: email = null | H128: approved and entitled; no message handed to the mailer | I128: trade_status=approved emails=0 delivered=false | J128: High | K128: Major | L128: Validation / Negative | M128: Local - PHPUnit / Laravel HTTP kernel + MySQL 8 | N128: Pass
A129: NOT-FAIL-03 | B129: Notification failure | C129: Trade decision email failure handling | D129: Customer with a malformed email is still rejected | E129: Trade application whose email is not an address | F129: Reject and inspect status and outbox | G129: email = 'not-an-address' | H129: rejected; nothing handed to the mailer, no exception | I129: trade_status=rejected emails=0 status=200 | J129: High | K129: Major | L129: Validation / Negative | M129: Local - PHPUnit / Laravel HTTP kernel + MySQL 8 | N129: Pass
...

Sheet Dashboard
B2: EXECUTION DASHBOARD
B3: Every figure is a live formula over the Test Cases sheet.
B5: By status | F5: By priority
B6: Status | C6: Count | D6: Share | F6: Priority | G6: Total | H6: Passed | I6: Failed
B7: Total cases | C7: =COUNTA('Test Cases'!$A$2:$A$224) -> 223 | D7: =IF($C$7=0,0,C7/$C$7) -> 1 | F7: High | G7: =COUNTIF('Test Cases'!$J$2:$J$224,"High") -> 151 | H7: =_xlfn.COUNTIFS('Test Cases'!$J$2:$J$224,"High",'Test Cases'!$N$2:$N$224,"Pass") -> 147 | I7: =_xlfn.COUNTIFS('Test Cases'!$J$2:$J$224,"High",'Test Cases'!$N$2:$N$224,"Fail") -> 0
B8: Passed | C8: =COUNTIF('Test Cases'!$N$2:$N$224,"Pass") -> 214 | D8: =IF($C$7=0,0,C8/$C$7) -> 0.95964126 | F8: Medium | G8: =COUNTIF('Test Cases'!$J$2:$J$224,"Medium") -> 51 | H8: =_xlfn.COUNTIFS('Test Cases'!$J$2:$J$224,"Medium",'Test Cases'!$N$2:$N$224,"Pass") -> 47 | I8: =_xlfn.COUNTIFS('Test Cases'!$J$2:$J$224,"Medium",'Test Cases'!$N$2:$N$224,"Fail") -> 0
B9: Failed | C9: =COUNTIF('Test Cases'!$N$2:$N$224,"Fail") -> 0 | D9: =IF($C$7=0,0,C9/$C$7) -> 0 | F9: Low | G9: =COUNTIF('Test Cases'!$J$2:$J$224,"Low") -> 21 | H9: =_xlfn.COUNTIFS('Test Cases'!$J$2:$J$224,"Low",'Test Cases'!$N$2:$N$224,"Pass") -> 20 | I9: =_xlfn.COUNTIFS('Test Cases'!$J$2:$J$224,"Low",'Test Cases'!$N$2:$N$224,"Fail") -> 0
B10: Blocked | C10: =COUNTIF('Test Cases'!$N$2:$N$224,"Blocked") -> 9 | D10: =IF($C$7=0,0,C10/$C$7) -> 0.040358744
B11: Not executed | C11: =COUNTIF('Test Cases'!$N$2:$N$224,"Not Executed") -> 0 | D11: =IF($C$7=0,0,C11/$C$7) -> 0 | F11: By severity
B12: Pass rate of executed | C12: =IF((C7-C10-C11)=0,0,C8/(C7-C10-C11)) -> 1 | F12: Severity | G12: Total | H12: Passed | I12: Blocked
F13: Blocker | G13: =COUNTIF('Test Cases'!$K$2:$K$224,"Blocker") -> 0 | H13: =_xlfn.COUNTIFS('Test Cases'!$K$2:$K$224,"Blocker",'Test Cases'!$N$2:$N$224,"Pass") -> 0 | I13: =_xlfn.COUNTIFS('Test Cases'!$K$2:$K$224,"Blocker",'Test Cases'!$N$2:$N$224,"Blocked") -> 0
F14: Critical | G14: =COUNTIF('Test Cases'!$K$2:$K$224,"Critical") -> 48 | H14: =_xlfn.COUNTIFS('Test Cases'!$K$2:$K$224,"Critical",'Test Cases'!$N$2:$N$224,"Pass") -> 46 | I14: =_xlfn.COUNTIFS('Test Cases'!$K$2:$K$224,"Critical",'Test Cases'!$N$2:$N$224,"Blocked") -> 2
F15: Major | G15: =COUNTIF('Test Cases'!$K$2:$K$224,"Major") -> 103 | H15: =_xlfn.COUNTIFS('Test Cases'!$K$2:$K$224,"Major",'Test Cases'!$N$2:$N$224,"Pass") -> 101 | I15: =_xlfn.COUNTIFS('Test Cases'!$K$2:$K$224,"Major",'Test Cases'!$N$2:$N$224,"Blocked") -> 2
F16: Minor | G16: =COUNTIF('Test Cases'!$K$2:$K$224,"Minor") -> 72 | H16: =_xlfn.COUNTIFS('Test Cases'!$K$2:$K$224,"Minor",'Test Cases'!$N$2:$N$224,"Pass") -> 67 | I16: =_xlfn.COUNTIFS('Test Cases'!$K$2:$K$224,"Minor",'Test Cases'!$N$2:$N$224,"Blocked") -> 5
B18: Sign-off
B19: Not signed off. PAY-01 and PAY-02 are Critical and could not be executed (no gateway sandbox credentials), and ORD-01 and INV-01 depend on them. Everything that could be executed passed.

Sheet Traceability
A1: Module | B1: ID prefixes | C1: Test cases | D1: Passed | E1: Failed | F1: Blocked | G1: Critical + Major | H1: Primary application area
A2: Account type | B2: AT | C2: 10 | D2: 10 | E2: 0 | F2: 0 | G2: 8 | H2: Account type selection and integrity
A3: Admin management | B3: ADM | C3: 13 | D3: 13 | E3: 0 | F3: 0 | G3: 1 | H3: Admin customer and trade management
A4: Browser/session | B4: BRW | C4: 1 | D4: 0 | E4: 0 | F4: 1 | G4: 0 | H4: Browser and session behaviour
A5: Business registration | B5: REG | C5: 25 | D5: 25 | E5: 0 | F5: 0 | G5: 9 | H5: Business account registration
A6: Cart isolation | B6: CART | C6: 1 | D6: 1 | E6: 0 | F6: 0 | G6: 1 | H6: Basket ownership and isolation
A7: Cart repricing | B7: CART | C7: 9 | D7: 9 | E7: 0 | F7: 0 | G7: 9 | H7: Server-side basket re-pricing
A8: Customer dashboard | B8: DSH | C8: 10 | D8: 10 | E8: 0 | F8: 0 | G8: 9 | H8: Customer account dashboard
A9: Discounts | B9: DSC | C9: 8 | D9: 8 | E9: 0 | F9: 0 | G9: 5 | H9: Vouchers, flash and loyalty discounts
A10: End to end | B10: E2E | C10: 4 | D10: 4 | E10: 0 | F10: 0 | G10: 4 | H10: Full lifecycle journeys
A11: Invoice | B11: INV | C11: 1 | D11: 0 | E11: 0 | F11: 1 | G11: 1 | H11: Invoice document
A12: Notification failure | B12: NOT | C12: 5 | D12: 5 | E12: 0 | F12: 0 | G12: 4 | H12: Trade decision email failure handling
A13: Notifications | B13: NOT | C13: 5 | D13: 5 | E13: 0 | F13: 0 | G13: 5 | H13: Trade decision emails
... A28: Trade rejection | B28: TRD | C28: 4 | D28: 4 | E28: 0 | F28: 0 | G28: 3 | H28: Admin trade rejection

Sheet Blocked Items
A1: Test Case ID | B1: Module | C1: Severity | D1: Scenario | E1: Why it could not be executed | F1: What would unblock it
A2: PAY-01 | B2: Payment | C2: Critical | D2: Successful card payment charges the account-correct total | E2: No gateway sandbox credentials are configured in this environment (.env carries no Stripe/PayPal/SumUp test keys), and the order endpoint verifies the charge with the provider before it will create an order. Needs a sandbox account to run. | F2: Gateway sandbox credentials (Stripe or SumUp test keys) in the environment.
A3: PAY-02 | B3: Payment | C3: Critical | D3: Failed, cancelled and retried payment leave no duplicate order | E3: Same blocker as PAY-01: the provider round trip cannot be exercised without sandbox credentials. | F3: Gateway sandbox credentials, as PAY-01.
A4: ORD-01 | B4: Order | C4: Major | D4: Order totals, lines, tax and PO match the checkout summary | E4: Reaching order creation needs a payable gateway plus a configured shipping rule and place for the product; the storefront blocks checkout before that. The pricing that WOULD be used is covered by PRC/QTY/TAX above, which exercise the same Pricing methods OrdersController calls. | F4: A payable gateway plus a shipping rule and shipping place configured for the product.
A5: INV-01 | B5: Invoice | C5: Major | D5: Invoice PDF totals match the order, showing PO and VAT number | E5: Depends on a created order (ORD-01). The template changes were verified by reading the rendered blade, but the end-to-end PDF was not produced. | F5: A created order (ORD-01), then render the PDF and compare it against the order rows.
A6: RESP-01 | B6: Responsive UI | C6: Minor | D6: Registration, dashboard, checkout and admin on real devices | E6: No browser is driven in this pass. UI-01 to UI-07 statically verify the breakpoints, overflow rules and fixed widths in the shipped files, which is evidence about the source, not about rendering on a device. | F6: A browser driver (Playwright or similar) against the built storefront and admin panel.
A7: BRW-01 | B7: Browser/session | C7: Minor | D7: Back/forward navigation, multiple tabs, session expiry | E7: Requires a real browser session. The server-side halves that matter are covered: basket isolation between customers (CART-ISO-01), guest handover repricing (CART-B-01) and re-read repricing (CART-SEC-01). | F7: A browser driver with session and multi-tab control.
A8: REF-01 | B8: Returns/refunds | C8: Minor | D8: Returns and refunds still work for all account types | E8: Not touched by this work and not exercised here. The refund path (Helper\Refunder, CancellationsController) was not modified in any of the three changesets. | F8: A completed order to return or refund, so also depends on ORD-01.
A9: TAX-08 | B9: Tax | C9: Minor | D9: Country-based VAT: billing vs shipping country, reverse charge | E9: The feature does not exist. Tax is decided per product (products.excludeVAT plus tax_rules) with no country dimension anywhere in the schema or the pricing code. Raised as a product gap, not a defect. | F9: Product decision: country-based VAT does not exist in the schema or the pricing code.
A10: DOC-01 | B10: Trade application | C10: Minor | D10: Supporting document upload, file size and type limits | E10: The feature does not exist. Nothing in the schema stores files against an account, and the trade form collects no upload. Raised as a gap. | F10: Product decision: document upload for trade applications does not exist.

Sheet Defect Log
A1: Defect ID | B1: Test Case ID | C1: Module | D1: Summary | E1: Expected | F1: Actual | G1: Severity | H1: Root cause | I1: Resolution | J1: Status
A2: QA-D01 | B2: TRD-APP-02, TRD-REJ-02, TRD-REJ-04 and 3 more | C2: Notifications | D2: Email assertions read the wrong message | E2: Each case inspects the email it generated | F2: Cases read the previous case email in the same module | G2: Major | H2: The outbox was emptied once per test method, not per case, so modules that send mail in more than one case saw a stale message at index 0. | I2: Harness: the outbox is now flushed before every case. | J2: Closed - not a product defect
A3: QA-D02 | B3: NOT-FAIL-02 to NOT-FAIL-05 | C3: Notification failure | D3: Later cases died on getSwiftMailer() | E3: Each case runs independently | F3: BadMethodCallException on the mocked Mail facade | G3: Major | H3: A Mockery facade mock created in the transport-failure case stands for the rest of the test method, so every later case in it hit the mock instead of the real mailer. | I3: Harness: the transport-failure case was given a method of its own, which gets a fresh application. | J3: Closed - not a product defect
A4: QA-D03 | B4: QTY-DIR-01, E2E-* (4 cases) | C4: Cart repricing | D4: Basket read returned no lines | E4: The caller own basket lines are returned | F4: Empty result, unit price null | G4: Major | H4: Passport::actingAs sets one guard and leaves the others standing. After a case acted as an admin, the admin guard still resolved and CartsController::byUser correctly scoped the basket to admin_id - the application was right, the harness was not. | I4: Harness: switching identity now drops resolved guards first. | J4: Closed - not a product defect
A5: QA-D04 | B5: CART-SEC-02, QTY-DIR-01 | C5: Cart repricing | D5: Add to basket refused | E5: Line created at the catalogue price | F5: Quantity exceeds inventory | G5: Minor | H5: The fixture took the product first inventory row, which holds 0 units with backorder off. The refusal was correct stock behaviour. | I5: Harness: the fixture now selects a purchasable variation. | J5: Closed - not a product defect
A6: QA-D05 | B6: SEC-10, DSH-09 | C6: Security | D6: Guest cases behaved as a signed-in customer | E6: Guest sees no bands and a personal account object | F6: Bands returned; account reported as business | G6: Major | H6: Same guard leakage as QA-D03: the cases never actually became anonymous. | I6: Harness: anonymous cases now clear authentication explicitly. | J6: Closed - not a product defect
A7: QA-D06 | B7: CART-E-01 | C7: Cart repricing | D7: Catalogue price change not reflected in the basket | E7: Basket shows the new price | F7: Basket kept the original price | G7: Major | H7: My expectation was wrong. The buyable rows on the test product are variations carrying their own price, and a variant price outranks products.selling by design, so changing products.selling could not move the line. | I7: Case corrected to move the variation price, which is the figure that governs the line. It re-prices correctly. | J7: Closed - not a product defect
A8: QA-D07 | B8: PO-03, PO-04 | C8: Purchase order | D8: Order refused before the purchase order gate | E8: Refused naming the purchase order number | F8: Gateway is not accepted | G8: Minor | H8: The cases used order_method 1 (Razorpay), which is switched off on this install, so the request was refused at the gateway check first. | I8: Cases now use bank transfer, which is enabled here. The purchase order gate is reached and refuses correctly. | J8: Closed - not a product defect
A9: QA-F01 | B9: Incidental - found while checking enabled gateways | C9: Payments / Security | D9: Live Stripe secret key stored in the development database | E9: Live secrets are not present in a development database | F9: payments row holds a live Stripe secret key and publishable key | G9: Critical | H9: Live credentials were saved into the payments settings row and the database was copied to a development environment. Stripe itself is disabled, so nothing is charging through it. | I9: Recommended: roll the key in the Stripe dashboard and keep live secrets out of any database that reaches a developer machine. Outside the Business and Trade scope. | J9: Open - referred

Sheet Environments
A1: Environment label | B1: Type | C1: Runtime | D1: Data | E1: Mail | F1: Purpose
A2: Local - PHPUnit / Laravel HTTP kernel + MySQL 8 | B2: API / Integration | C2: PHP 8, Laravel 8, PHPUnit 9.6 | D2: Development MySQL; each case in a rolled-back transaction | E2: Array transport, messages captured and inspected | F2: Where every executed case in this workbook ran. Asserts stored rows, API payloads and rendered emails.
A3: Local - static source review | B3: Static | C3: File reads over the shipped source | D3: frontend-panel, admin-panel, resources/views | E3: n/a | F3: UI-01 to UI-07: breakpoints, overflow rules and fixed widths in the files that shipped. Evidence about the source, not about a device.
A4: Not available - payment gateway sandbox | B4: Blocked | C4: n/a | D4: n/a | E4: n/a | F4: Needed for PAY-01 and PAY-02, and therefore for ORD-01 and INV-01.
A5: Not available - browser driver | B5: Blocked | C5: n/a | D5: n/a | E5: n/a | F5: Needed for RESP-01 (device rendering) and BRW-01 (session, tabs, navigation).
