Workbook

Sheet Read me
A1: Returns & Exchanges - QA Test Cases
A2: For the live site after the deploy (git commit dc2ab10). Prepared 21 Oct 2026.
A4: How to use this workbook
A5: 1. Prepare the data in "Before you start" below.
A6: 2. Work through the Test cases sheet. Fill in only the pale yellow columns: Result (dropdown), Tester, Date tested, Notes / defect link.
A7: 3. For a Fail or Blocked case, write what you saw in Notes, with a screenshot or ticket link.
A8: 4. The Summary sheet counts the results by area as you go.
A9: Card refunds and payment links move real money on the live site: use small amounts (EUR 1-5) and refund them afterwards.
A11: Result values
A12: Not run | B12: Not tested yet (the starting value)
A13: Pass | B13: Everything in Expected result happened
A14: Fail | B14: Something differed: describe it in Notes
A15: Blocked | B15: Could not be tested (missing data, another bug): say why in Notes
A17: Example of a filled-in row
A18: ID | B18: Result | C18: Tester | D18: Date tested | E18: Notes / defect link
A19: A-07 | B19: Fail | C19: Priya | D19: 22 Oct 2026 | E19: EUR 470 was accepted on a EUR 461.54 quote; screenshot in ticket QA-112
A20: Example only: the real cases are on the Test cases sheet.
A22: Before you start
A23: What | B23: How to set it up | C23: Used by
A24: Deploy done | B24: Migrations 2026_10_19_000200 to 000500 run with --path; admin panel and storefront rebuilt with API_BASE empty | C24: All
A25: Test customer | B25: A signed-in customer account whose email you can read | C25: C, E, M, L
A26: Guest order | B26: One order placed at guest checkout in a separate browser | C26: C-11, S-02
A27: Delivered card order | B27: Small card order (1 item); admin moves it to Delivered | C27: C-01 to C-03, A-06
A28: Two-unit order | B28: One product, quantity 2, delivered | C28: A-12
A29: Order with a voucher | B29: A voucher applied at checkout, delivered | C29: A-13
A30: Gift card order | B30: Part paid with a gift card, delivered | C30: A-14
A31: Points order | B31: Points spent at checkout, delivered (points earned on delivery) | C31: A-15
A32: Variant product | B32: A product with 3 in-stock variants: one dearer, one same price, one cheaper than the one ordered | C32: E-01 to E-14
A33: Cash on delivery order | B33: COD order, delivered | C33: A-11
A34: Old order | B34: Delivered more than 30 days ago | C34: C-05, A-04
... A38: Card gateway | B38: Payment Setting: SumUp or Stripe switched on as the card gateway | C38: A-06, E-06 to E-09
A39: To make an order Delivered, use the status dropdown on the admin order page: the 30-day return window counts from that change.
A41: Automated tests behind these cases: tests/Isolated/OrderReturnTest, OrderExchangeTest, ReturnRequestAndPayLinkTest, MyOrdersTabsTest (77 tests).

Sheet Test cases
A1: ID | B1: Area | C1: Test case | D1: Steps | E1: Expected result | F1: Result | G1: Tester | H1: Date tested | I1: Notes / defect link
A2: C-01 | B2: Customer request | C2: Button only where allowed | D2: Open a Delivered paid order, then a Pending, an On the way and a Cancelled one | E2: The "Return or exchange" box appears only on the Delivered paid order | F2: Not run
A3: C-02 | B3: Customer request | C3: Form contents | D3: Delivered order > Return or exchange | E3: Days left in the 30-day window, each item with a quantity stepper, reason list, optional note | F3: Not run
A4: C-03 | B4: Customer request | C4: Send a return request | D4: Return for a refund, 1 unit, reason Faulty, a note, Send | E4: Toast "Thanks - we have your request"; Returns box shows RMA number, Return badge, "Request received", Cancel request; customer email "Return request received"; staff email "Return request RMA..." | F4: Not run
A5: C-04 | B5: Customer request | C5: Units cannot be asked twice | D5: After C-03, open the form again on the same order | E5: That unit shows "Already being returned"; no stepper for it | F5: Not run
A6: C-05 | B6: Customer request | C6: Return window | D6: Old order (delivered 31+ days ago) > Return or exchange | E6: Message "Returns can be requested within 30 days of delivery..."; no form | F6: Not run
A7: C-06 | B7: Customer request | C7: Non-refundable product | D7: Non-refundable item: Return for a refund + Changed my mind; then Faulty; then Exchange | E7: Changed my mind refused with a message; Faulty accepted; Exchange accepted | F7: Not run
A8: C-07 | B8: Customer request | C8: Exchange choices | D8: Variant product > Exchange, 1 unit, open Swap for | E8: Only in-stock (or backorder) variants; each shows "EUR X more", "EUR X less" or "same price"; the dearer one shows the payment-link note | F8: Not run
A9: C-08 | B9: Customer request | C9: Exchange needs a variant | D9: Exchange, unit chosen, no variant picked | E9: Send button stays disabled | F9: Not run
A10: C-09 | B10: Customer request | C10: Withdraw a request | D10: After C-03, Cancel request > confirm | E10: Status "Cancelled"; the unit can be requested again | F10: Not run
A11: C-10 | B11: Customer request | C11: No withdraw after receipt | D11: Staff mark a request received (A-05), customer reloads | E11: Cancel request button is gone | F11: Not run
A12: C-11 | B12: Customer request | C12: Guest order | D12: In the guest browser, open the guest order and send a request | E12: Request accepted exactly as for an account | F12: Not run
A13: A-01 | B13: Admin review & refund | C13: Returns list | D13: Open Orders > Returns after C-03 | E13: "To review" tile counts the request; list shows RMA, Type, order, customer, status; status filter and search by RMA, order number or email work | F13: Not run
... A72: S-07 | B72: Security & edge cases | C72: Total never exceeded | D72: Refund every unit of an order across several cases, with delivery | E72: Refunds add up to the order total and stop there; no refund beyond it is offered | F72: Not run

Sheet Summary
A1: Results by area
A2: Counts update from the Result column on the Test cases sheet.
A4: Area | B4: Cases | C4: Pass | D4: Fail | E4: Blocked | F4: Not run | G4: % done | H4: % passed
A5: Customer request | B5: =COUNTIF('Test cases'!$B$2:$B$72,A5) -> 11 | C5: =_xlfn.COUNTIFS('Test cases'!$B$2:$B$72,A5,'Test cases'!$F$2:$F$72,"Pass") -> 0 | D5: =_xlfn.COUNTIFS('Test cases'!$B$2:$B$72,A5,'Test cases'!$F$2:$F$72,"Fail") -> 0 | E5: =_xlfn.COUNTIFS('Test cases'!$B$2:$B$72,A5,'Test cases'!$F$2:$F$72,"Blocked") -> 0 | F5: =B5-C5-D5-E5 -> 11 | G5: =IF(B5=0,0,(C5+D5+E5)/B5) -> 0 | H5: =IF(C5+D5=0,0,C5/(C5+D5)) -> 0
A6: Admin review & refund | B6: =COUNTIF('Test cases'!$B$2:$B$72,A6) -> 19 | C6: =_xlfn.COUNTIFS('Test cases'!$B$2:$B$72,A6,'Test cases'!$F$2:$F$72,"Pass") -> 0 | D6: =_xlfn.COUNTIFS('Test cases'!$B$2:$B$72,A6,'Test cases'!$F$2:$F$72,"Fail") -> 0 | E6: =_xlfn.COUNTIFS('Test cases'!$B$2:$B$72,A6,'Test cases'!$F$2:$F$72,"Blocked") -> 0 | F6: =B6-C6-D6-E6 -> 19 | G6: =IF(B6=0,0,(C6+D6+E6)/B6) -> 0 | H6: =IF(C6+D6=0,0,C6/(C6+D6)) -> 0
A7: Exchanges & payment links | B7: =COUNTIF('Test cases'!$B$2:$B$72,A7) -> 14 | C7: =_xlfn.COUNTIFS('Test cases'!$B$2:$B$72,A7,'Test cases'!$F$2:$F$72,"Pass") -> 0 | D7: =_xlfn.COUNTIFS('Test cases'!$B$2:$B$72,A7,'Test cases'!$F$2:$F$72,"Fail") -> 0 | E7: =_xlfn.COUNTIFS('Test cases'!$B$2:$B$72,A7,'Test cases'!$F$2:$F$72,"Blocked") -> 0 | F7: =B7-C7-D7-E7 -> 14 | G7: =IF(B7=0,0,(C7+D7+E7)/B7) -> 0 | H7: =IF(C7+D7=0,0,C7/(C7+D7)) -> 0
A8: My Orders tabs | B8: =COUNTIF('Test cases'!$B$2:$B$72,A8) -> 14 | C8: =_xlfn.COUNTIFS('Test cases'!$B$2:$B$72,A8,'Test cases'!$F$2:$F$72,"Pass") -> 0 | D8: =_xlfn.COUNTIFS('Test cases'!$B$2:$B$72,A8,'Test cases'!$F$2:$F$72,"Fail") -> 0 | E8: =_xlfn.COUNTIFS('Test cases'!$B$2:$B$72,A8,'Test cases'!$F$2:$F$72,"Blocked") -> 0 | F8: =B8-C8-D8-E8 -> 14 | G8: =IF(B8=0,0,(C8+D8+E8)/B8) -> 0 | H8: =IF(C8+D8=0,0,C8/(C8+D8)) -> 0
A9: Emails & languages | B9: =COUNTIF('Test cases'!$B$2:$B$72,A9) -> 6 | C9: =_xlfn.COUNTIFS('Test cases'!$B$2:$B$72,A9,'Test cases'!$F$2:$F$72,"Pass") -> 0 | D9: =_xlfn.COUNTIFS('Test cases'!$B$2:$B$72,A9,'Test cases'!$F$2:$F$72,"Fail") -> 0 | E9: =_xlfn.COUNTIFS('Test cases'!$B$2:$B$72,A9,'Test cases'!$F$2:$F$72,"Blocked") -> 0 | F9: =B9-C9-D9-E9 -> 6 | G9: =IF(B9=0,0,(C9+D9+E9)/B9) -> 0 | H9: =IF(C9+D9=0,0,C9/(C9+D9)) -> 0
A10: Security & edge cases | B10: =COUNTIF('Test cases'!$B$2:$B$72,A10) -> 7 | C10: =_xlfn.COUNTIFS('Test cases'!$B$2:$B$72,A10,'Test cases'!$F$2:$F$72,"Pass") -> 0 | D10: =_xlfn.COUNTIFS('Test cases'!$B$2:$B$72,A10,'Test cases'!$F$2:$F$72,"Fail") -> 0 | E10: =_xlfn.COUNTIFS('Test cases'!$B$2:$B$72,A10,'Test cases'!$F$2:$F$72,"Blocked") -> 0 | F10: =B10-C10-D10-E10 -> 7 | G10: =IF(B10=0,0,(C10+D10+E10)/B10) -> 0 | H10: =IF(C10+D10=0,0,C10/(C10+D10)) -> 0
A11: Total | B11: =SUM(B5:B10) -> 71 | C11: =SUM(C5:C10) -> 0 | D11: =SUM(D5:D10) -> 0 | E11: =SUM(E5:E10) -> 0 | F11: =SUM(F5:F10) -> 71 | G11: =IF(B11=0,0,(C11+D11+E11)/B11) -> 0 | H11: =IF(C11+D11=0,0,C11/(C11+D11)) -> 0
A13: % done = cases with any result other than Not run. % passed = Pass / (Pass + Fail); Blocked cases are left out of it.
